Workbook
Name LST_LIGNES: OFFSET(PARAMETRES!$I$7,0,0,MAX(1,COUNTA(PARAMETRES!$I$7:$I$36)),1)
Name LST_EQUIPES: OFFSET(PARAMETRES!$J$7,0,0,MAX(1,COUNTA(PARAMETRES!$J$7:$J$36)),1)
Name LST_PILOTES: OFFSET(PARAMETRES!$K$7,0,0,MAX(1,COUNTA(PARAMETRES!$K$7:$K$36)),1)
Name LST_PRODUITS: OFFSET(PARAMETRES!$M$7,0,0,MAX(1,COUNTA(PARAMETRES!$M$7:$M$36)),1)
Name LST_CAUSES: OFFSET(PARAMETRES!$R$7,0,0,MAX(1,COUNTA(PARAMETRES!$R$7:$R$46)),1)
Name LST_POSTES: OFFSET(PARAMETRES!$X$7,0,0,MAX(1,COUNTA(PARAMETRES!$X$7:$X$26)),1)
Name LST_FAM5M: OFFSET(PARAMETRES!$AB$7,0,0,MAX(1,COUNTA(PARAMETRES!$AB$7:$AB$26)),1)
Name LST_SOURCES: OFFSET(PARAMETRES!$AC$7,0,0,MAX(1,COUNTA(PARAMETRES!$AC$7:$AC$26)),1)
Name LST_NATURES: OFFSET(PARAMETRES!$AD$7,0,0,MAX(1,COUNTA(PARAMETRES!$AD$7:$AD$26)),1)
Name LST_STATUTS: OFFSET(PARAMETRES!$AE$7,0,0,MAX(1,COUNTA(PARAMETRES!$AE$7:$AE$26)),1)
Name LST_EFFICACITE: OFFSET(PARAMETRES!$AF$7,0,0,MAX(1,COUNTA(PARAMETRES!$AF$7:$AF$26)),1)
Name LST_OUINON: OFFSET(PARAMETRES!$AG$7,0,0,MAX(1,COUNTA(PARAMETRES!$AG$7:$AG$26)),1)
Name LST_CONTROLE: OFFSET(PARAMETRES!$AH$7,0,0,MAX(1,COUNTA(PARAMETRES!$AH$7:$AH$26)),1)
Name LST_SQCDP: OFFSET(PARAMETRES!$AI$7,0,0,MAX(1,COUNTA(PARAMETRES!$AI$7:$AI$26)),1)
Name LST_F_LIGNES: OFFSET(PARAMETRES!$AJ$7,0,0,MAX(1,COUNTA(PARAMETRES!$AJ$7:$AJ$26)),1)
Name LST_F_EQUIPES: OFFSET(PARAMETRES!$AK$7,0,0,MAX(1,COUNTA(PARAMETRES!$AK$7:$AK$26)),1)
Name LST_RUBRIQUES: OFFSET(PARAMETRES!$AL$7,0,0,MAX(1,COUNTA(PARAMETRES!$AL$7:$AL$26)),1)
Name LST_MOIS: OFFSET(PARAMETRES!$AM$7,0,0,MAX(1,COUNTA(PARAMETRES!$AM$7:$AM$26)),1)

Sheet LISEZ-MOI
A1: PILOTAGE DE LA PRODUCTION — MODE D'EMPLOI
A2: Classeur de pilotage opérationnel destiné au superviseur de production : saisie quotidienne, calcul normalisé du TRS, analyse des pertes et animation du plan d'actions.
A4: 1. ARCHITECTURE DU CLASSEUR
A5: Onglet | B5: Rôle
A6: COCKPIT | B6: Tableau de bord de la revue de performance : 12 indicateurs, 7 graphiques, top 5 des causes. | G6: Quotidienne (lecture) | I6: Superviseur | K6: Aucune saisie sauf les filtres et le bloc de décisions
A7: SAISIE_PROD | B7: Journal de production : une ligne par jour, par équipe et par ligne. Calcule le TRS et ses composantes. | G7: Quotidienne (5 min) | I7: Superviseur de poste | K7: Colonnes jaunes uniquement
A8: ARRETS | B8: Journal événementiel des arrêts : horaire, durée, code cause, famille 5M. Base de l'analyse de Pareto. | G8: À chaque arrêt | I8: Chef d'équipe | K8: Colonnes jaunes uniquement
A9: PLAN_ACTIONS | B9: Plan d'actions structuré : fait mesuré, cotation de criticité, cause racine, pilote, vérification d'efficacité. | G9: À chaque écart | I9: Superviseur / pilotes | K9: Colonnes jaunes uniquement
A10: POLYVALENCE | B10: Matrice de compétences ILUO et couverture des postes : risque de mono-compétence, plan de formation. | G10: Mensuelle | I10: Responsable de production | K10: Niveaux 0 à 4 et informations collaborateur
A11: AUDIT_5S | B11: Grille d'audit 5S pondérée : 25 critères, score par domaine, comparaison à l'audit précédent, historique. | G11: Mensuelle | I11: Auditeur désigné | K11: Pondérations, notes, constats et actions
A12: PRISE_DE_POSTE | B12: Standard de prise de poste et de passation SQCDP, matrice d'escalade et visa. | G12: À chaque relève | I12: Superviseur entrant / sortant | K12: Statuts, constats, actions et passation
A13: PARAMETRES | B13: Référentiels du site : objectifs et seuils, lignes, équipes, produits, causes d'arrêt, postes, listes de choix. | G13: À la mise en service, puis à chaque évolution | I13: Responsable de production | K13: Toutes les cellules bleues
A14: GLOSSAIRE | B14: Définition, formule et interprétation de chaque indicateur ; règles de gestion du classeur. | G14: Référence | I14: — | K14: Aucune
A15: CALC | B15: Moteur de calcul : agrégations filtrées, séries journalières, Pareto, cascade, historique 13 mois. | G15: Automatique | I15: — | K15: Aucune — ne pas modifier
A17: 2. LÉGENDE DES COULEURS
B18: Cellule à saisir | E18: Fond jaune, texte bleu : donnée saisie par l'utilisateur.
B19: Cellule calculée | E19: Fond bleu clair, texte noir : formule, ne pas écraser.
B20: Lien vers un référentiel | E20: Fond vert clair, texte vert : valeur reprise de l'onglet PARAMETRES.
B21: Objectif atteint | E21: La valeur est au niveau de la cible ou au-delà.
B22: Vigilance | E22: La valeur est entre la cible et le seuil d'alerte.
B23: Alerte | E23: La valeur a franchi le seuil d'alerte : action requise le jour même.
A25: 3. RITUEL DE MANAGEMENT
A26: Échéance | C26: Contenu
A27: Chaque fin de poste | C27: 5 min | D27: Saisir la ligne du jour dans SAISIE_PROD et les arrêts dans ARRETS ; vérifier la colonne de contrôle de cohérence.
A28: Chaque matin | C28: 5 min | D28: Lire le COCKPIT devant l'équipe : une carte rouge = une action ouverte le jour même dans PLAN_ACTIONS.
A29: Chaque semaine | C29: 30 min | D29: Revue du Pareto et de la cascade des pertes : choisir le chantier prioritaire, vérifier l'avancement des actions.
A30: Chaque mois | C30: 60 min | D30: Revue de performance : tendance 13 mois, audit 5S, matrice de polyvalence, efficacité des actions soldées.
A31: Chaque trimestre | C31: — | D31: Révision des objectifs et des seuils d'alerte dans PARAMETRES au regard des résultats obtenus.
A33: 4. MISE EN SERVICE — à réaliser avant la première saisie
A34: 1. Ouvrir l'onglet PARAMETRES et renseigner l'identification du site (cellules bleues).
A35: 2. Ajuster les objectifs et les seuils d'alerte au contrat de performance de l'entité.
A36: 3. Saisir les lignes de production, les équipes, les pilotes et les postes de travail.
A37: 4. Compléter le référentiel produits : chaque référence doit porter sa cadence nominale en pièces/minute, sans laquelle le taux de performance ne peut pas être calculé.
A38: 5. Adapter si besoin le référentiel des causes d'arrêt : conserver la colonne « Rubrique de saisie », qui relie chaque code à la colonne correspondante de SAISIE_PROD.
A39: 6. Supprimer le jeu de démonstration : sélectionner les lignes 5 à 46 de SAISIE_PROD, les lignes 5 à 203 de ARRETS et les lignes 9 à 16 de PLAN_ACTIONS, puis effacer uniquement le contenu des colonnes jaunes (touche Suppr). Ne jamais supprimer les lignes elles-mêmes : les formules des colonnes calculées seraient perdues.
A40: 7. Dans le COCKPIT, positionner l'année et le mois de travail, puis démarrer la saisie quotidienne.
A42: 5. JEU DE DÉMONSTRATION LIVRÉ AVEC LE CLASSEUR
A43: Le classeur est livré avec un mois complet de données fictives (janvier 2026, deux lignes de production, 42 journées de production, 199 arrêts horodatés, 8 actions correctives, 12 collaborateurs et un audit 5S). Ces données sont cohérentes entre elles — les arrêts du journal alimentent exactement les rubriques de perte de la saisie — afin que le cockpit soit immédiatement lisible et que chaque calcul puisse être vérifié. Elles n'ont aucune valeur métier et doivent être effacées avant la mise en service réelle (voir étape 6 ci-dessus). Le compteur « actions en retard » se calcule par rapport à la date du jour : les actions de démonstration, datées de janvier 2026, apparaissent donc en retard dès que le fichier est ouvert plus tard dans l'année.

Sheet COCKPIT
A1: COCKPIT DE PILOTAGE DE LA PRODUCTION
A2: =PARAMETRES!$C$5&" — "&PARAMETRES!$C$6&" | Revue quotidienne de performance | Édition du "&TEXT(TODAY(),"dd/mm/yyyy")
A4: Année : | B4: 2026 | C4: Mois : | D4: 1 | E4: =INDEX(PARAMETRES!$AM$7:$AM$18,$D$4)&" "&TEXT($B$4,"0000") | G4: Ligne : | H4: Toutes | J4: Équipe : | K4: Toutes | N4: ="Jours de production saisis : "&CALC!$B$9&" | Lignes suivies : "&COUNTIF(CALC!$D$72:$D$76,">0")
T5: Bloc technique — pilotage des couleurs (ne pas modifier)
A6: TRS DU MOIS (rendement synthétique) | D6: DISPONIBILITÉ | G6: PERFORMANCE (tenue de cadence) | J6: QUALITÉ AU PREMIER PASSAGE | M6: TRG (sur temps d'ouverture) | P6: TAUX DE SERVICE | T6: TRS | U6: =A7 | V6: =INDEX(PARAMETRES!$D$16:$D$29,MATCH("TRS",PARAMETRES!$A$16:$A$29,0)) | W6: =INDEX(PARAMETRES!$E$16:$E$29,MATCH("TRS",PARAMETRES!$A$16:$A$29,0)) | X6: =INDEX(PARAMETRES!$F$16:$F$29,MATCH("TRS",PARAMETRES!$A$16:$A$29,0)) | Y6: =IF($U6="","",IF($X6=1,IF($U6>=$V6,1,IF($U6<$W6,3,2)),IF($U6<=$V6,1,IF($U6>$W6,3,2))))
A7: =IFERROR(CALC!$V$20/CALC!$V$18,"") | D7: =IFERROR(CALC!$V$19/CALC!$V$18,"") | G7: =IFERROR((CALC!$V$19-CALC!$V$16)/CALC!$V$19,"") | J7: =IFERROR(CALC!$V$23/CALC!$V$22,"") | M7: =IFERROR(CALC!$V$20/CALC!$V$8,"") | P7: =IFERROR((CALC!$V$23+CALC!$V$24)/CALC!$V$25,"") | T7: DISPO | U7: =D7 | V7: =INDEX(PARAMETRES!$D$16:$D$29,MATCH("DISPO",PARAMETRES!$A$16:$A$29,0)) | W7: =INDEX(PARAMETRES!$E$16:$E$29,MATCH("DISPO",PARAMETRES!$A$16:$A$29,0)) | X7: =INDEX(PARAMETRES!$F$16:$F$29,MATCH("DISPO",PARAMETRES!$A$16:$A$29,0)) | Y7: =IF($U7="","",IF($X7=1,IF($U7>=$V7,1,IF($U7<$W7,3,2)),IF($U7<=$V7,1,IF($U7>$W7,3,2))))
T8: PERF | U8: =G7 | V8: =INDEX(PARAMETRES!$D$16:$D$29,MATCH("PERF",PARAMETRES!$A$16:$A$29,0)) | W8: =INDEX(PARAMETRES!$E$16:$E$29,MATCH("PERF",PARAMETRES!$A$16:$A$29,0)) | X8: =INDEX(PARAMETRES!$F$16:$F$29,MATCH("PERF",PARAMETRES!$A$16:$A$29,0)) | Y8: =IF($U8="","",IF($X8=1,IF($U8>=$V8,1,IF($U8<$W8,3,2)),IF($U8<=$V8,1,IF($U8>$W8,3,2))))
A9: ="Cible : "&TEXT($V$6,"0.0%") | D9: ="Cible : "&TEXT($V$7,"0.0%") | G9: ="Cible : "&TEXT($V$8,"0.0%") | J9: ="Cible : "&TEXT($V$9,"0.0%") | M9: ="Cible : "&TEXT($V$10,"0.0%") | P9: ="Cible : "&TEXT($V$11,"0.0%") | T9: QUAL | U9: =J7 | V9: =INDEX(PARAMETRES!$D$16:$D$29,MATCH("QUAL",PARAMETRES!$A$16:$A$29,0)) | W9: =INDEX(PARAMETRES!$E$16:$E$29,MATCH("QUAL",PARAMETRES!$A$16:$A$29,0)) | X9: =INDEX(PARAMETRES!$F$16:$F$29,MATCH("QUAL",PARAMETRES!$A$16:$A$29,0)) | Y9: =IF($U9="","",IF($X9=1,IF($U9>=$V9,1,IF($U9<$W9,3,2)),IF($U9<=$V9,1,IF($U9>$W9,3,2))))
A10: =IF(CALC!$L$99="","Mois précédent : non disponible","M-1 : "&TEXT(CALC!$L$99,"0.0%")&" "&TEXT(($U$6-CALC!$L$99)*100,"+0.0 pt;-0.0 pt;0.0 pt")) | D10: =IF(CALC!$M$99="","Mois précédent : non disponible","M-1 : "&TEXT(CALC!$M$99,"0.0%")&" "&TEXT(($U$7-CALC!$M$99)*100,"+0.0 pt;-0.0 pt;0.0 pt")) | G10: =IF(CALC!$N$99="","Mois précédent : non disponible","M-1 : "&TEXT(CALC!$N$99,"0.0%")&" "&TEXT(($U$8-CALC!$N$99)*100,"+0.0 pt;-0.0 pt;0.0 pt")) | J10: =IF(CALC!$O$99="","Mois précédent : non disponible","M-1 : "&TEXT(CALC!$O$99,"0.0%")&" "&TEXT(($U$9-CALC!$O$99)*100,"+0.0 pt;-0.0 pt;0.0 pt")) | M10: =IF(CALC!$P$99="","Mois précédent : non disponible","M-1 : "&TEXT(CALC!$P$99,"0.0%")&" "&TEXT(($U$10-CALC!$P$99)*100,"+0.0 pt;-0.0 pt;0.0 pt")) | P10: =IF(CALC!$Q$99="","Mois précédent : non disponible","M-1 : "&TEXT(CALC!$Q$99,"0.0%")&" "&TEXT(($U$11-CALC!$Q$99)*100,"+0.0 pt;-0.0 pt;0.0 pt")) | T10: TRG | U10: =M7 | V10: =INDEX(PARAMETRES!$D$16:$D$29,MATCH("TRG",PARAMETRES!$A$16:$A$29,0)) | W10: =INDEX(PARAMETRES!$E$16:$E$29,MATCH("TRG",PARAMETRES!$A$16:$A$29,0)) | X10: =INDEX(PARAMETRES!$F$16:$F$29,MATCH("TRG",PARAMETRES!$A$16:$A$29,0)) | Y10: =IF($U10="","",IF($X10=1,IF($U10>=$V10,1,IF($U10<$W10,3,2)),IF($U10<=$V10,1,IF($U10>$W10,3,2))))
T11: SERVICE | U11: =P7 | V11: =INDEX(PARAMETRES!$D$16:$D$29,MATCH("SERVICE",PARAMETRES!$A$16:$A$29,0)) | W11: =INDEX(PARAMETRES!$E$16:$E$29,MATCH("SERVICE",PARAMETRES!$A$16:$A$29,0)) | X11: =INDEX(PARAMETRES!$F$16:$F$29,MATCH("SERVICE",PARAMETRES!$A$16:$A$29,0)) | Y11: =IF($U11="","",IF($X11=1,IF($U11>=$V11,1,IF($U11<$W11,3,2)),IF($U11<=$V11,1,IF($U11>$W11,3,2))))
A12: NON-CONFORMITÉS INTERNES | D12: TAUX DE PRÉSENCE | G12: ACCIDENTS AVEC ARRÊT | J12: MTBF (temps entre pannes) | M12: MTTR (temps de réparation) | P12: ACTIONS EN RETARD | T12: PPM | U12: =A13 | V12: =INDEX(PARAMETRES!$D$16:$D$29,MATCH("PPM",PARAMETRES!$A$16:$A$29,0)) | W12: =INDEX(PARAMETRES!$E$16:$E$29,MATCH("PPM",PARAMETRES!$A$16:$A$29,0)) | X12: =INDEX(PARAMETRES!$F$16:$F$29,MATCH("PPM",PARAMETRES!$A$16:$A$29,0)) | Y12: =IF($U12="","",IF($X12=1,IF($U12>=$V12,1,IF($U12<$W12,3,2)),IF($U12<=$V12,1,IF($U12>$W12,3,2))))
A13: =IFERROR((CALC!$V$22-CALC!$V$23)/CALC!$V$22*1000000,"") | D13: =IFERROR(CALC!$V$29/CALC!$V$28,"") | G13: =CALC!$V$26 | J13: =IFERROR(CALC!$V$19/CALC!$V$27,"") | M13: =IFERROR(CALC!$V$10/CALC!$V$27,"") | P13: =PLAN_ACTIONS!$D$6 | T13: PRESENCE | U13: =D13 | V13: =INDEX(PARAMETRES!$D$16:$D$29,MATCH("PRESENCE",PARAMETRES!$A$16:$A$29,0)) | W13: =INDEX(PARAMETRES!$E$16:$E$29,MATCH("PRESENCE",PARAMETRES!$A$16:$A$29,0)) | X13: =INDEX(PARAMETRES!$F$16:$F$29,MATCH("PRESENCE",PARAMETRES!$A$16:$A$29,0)) | Y13: =IF($U13="","",IF($X13=1,IF($U13>=$V13,1,IF($U13<$W13,3,2)),IF($U13<=$V13,1,IF($U13>$W13,3,2))))
T14: ACCIDENT | U14: =G13 | V14: =INDEX(PARAMETRES!$D$16:$D$29,MATCH("ACCIDENT",PARAMETRES!$A$16:$A$29,0)) | W14: =INDEX(PARAMETRES!$E$16:$E$29,MATCH("ACCIDENT",PARAMETRES!$A$16:$A$29,0)) | X14: =INDEX(PARAMETRES!$F$16:$F$29,MATCH("ACCIDENT",PARAMETRES!$A$16:$A$29,0)) | Y14: =IF($U14="","",IF($X14=1,IF($U14>=$V14,1,IF($U14<$W14,3,2)),IF($U14<=$V14,1,IF($U14>$W14,3,2))))
A15: ="Cible : "&TEXT($V$12,"#,##0")&" ppm" | D15: ="Cible : "&TEXT($V$13,"0.0%") | G15: ="Cible : "&TEXT($V$14,"0") | J15: ="Cible : "&TEXT($V$15,"#,##0")&" min" | M15: ="Cible : "&TEXT($V$16,"#,##0")&" min" | P15: ="Cible : "&TEXT($V$17,"0") | T15: MTBF | U15: =J13 | V15: =INDEX(PARAMETRES!$D$16:$D$29,MATCH("MTBF",PARAMETRES!$A$16:$A$29,0)) | W15: =INDEX(PARAMETRES!$E$16:$E$29,MATCH("MTBF",PARAMETRES!$A$16:$A$29,0)) | X15: =INDEX(PARAMETRES!$F$16:$F$29,MATCH("MTBF",PARAMETRES!$A$16:$A$29,0)) | Y15: =IF($U15="","",IF($X15=1,IF($U15>=$V15,1,IF($U15<$W15,3,2)),IF($U15<=$V15,1,IF($U15>$W15,3,2))))
A16: ="Seuil d'alerte : "&TEXT($W$12,"#,##0")&" ppm" | D16: ="Seuil d'alerte : "&TEXT($W$13,"0.0%") | G16: ="Seuil d'alerte : "&TEXT($W$14,"0") | J16: ="Seuil d'alerte : "&TEXT($W$15,"#,##0")&" min" | M16: ="Seuil d'alerte : "&TEXT($W$16,"#,##0")&" min" | P16: ="Seuil d'alerte : "&TEXT($W$17,"0") | T16: MTTR | U16: =M13 | V16: =INDEX(PARAMETRES!$D$16:$D$29,MATCH("MTTR",PARAMETRES!$A$16:$A$29,0)) | W16: =INDEX(PARAMETRES!$E$16:$E$29,MATCH("MTTR",PARAMETRES!$A$16:$A$29,0)) | X16: =INDEX(PARAMETRES!$F$16:$F$29,MATCH("MTTR",PARAMETRES!$A$16:$A$29,0)) | Y16: =IF($U16="","",IF($X16=1,IF($U16>=$V16,1,IF($U16<$W16,3,2)),IF($U16<=$V16,1,IF($U16>$W16,3,2))))
T17: RETARD | U17: =P13 | V17: =INDEX(PARAMETRES!$D$16:$D$29,MATCH("RETARD",PARAMETRES!$A$16:$A$29,0)) | W17: =INDEX(PARAMETRES!$E$16:$E$29,MATCH("RETARD",PARAMETRES!$A$16:$A$29,0)) | X17: =INDEX(PARAMETRES!$F$16:$F$29,MATCH("RETARD",PARAMETRES!$A$16:$A$29,0)) | Y17: =IF($U17="","",IF($X17=1,IF($U17>=$V17,1,IF($U17<$W17,3,2)),IF($U17<=$V17,1,IF($U17>$W17,3,2))))
A18: ANALYSE DE LA PERFORMANCE DU MOIS
A78: TOP 5 DES CAUSES D'ARRÊT SUBI DU MOIS — source : journal des arrêts, hors arrêts planifiés
A79: Rang | C79: Code | E79: Cause d'arrêt | J79: Minutes perdues | L79: Occurrences | N79: Durée moyenne | P79: Part des arrêts subis
A80: =CALC!$A$152 | C80: =CALC!$B$152 | E80: =CALC!$C$152 | J80: =CALC!$D$152 | L80: =CALC!$E$152 | N80: =CALC!$F$152 | P80: =CALC!$G$152
A81: =CALC!$A$153 | C81: =CALC!$B$153 | E81: =CALC!$C$153 | J81: =CALC!$D$153 | L81: =CALC!$E$153 | N81: =CALC!$F$153 | P81: =CALC!$G$153
A82: =CALC!$A$154 | C82: =CALC!$B$154 | E82: =CALC!$C$154 | J82: =CALC!$D$154 | L82: =CALC!$E$154 | N82: =CALC!$F$154 | P82: =CALC!$G$154
A83: =CALC!$A$155 | C83: =CALC!$B$155 | E83: =CALC!$C$155 | J83: =CALC!$D$155 | L83: =CALC!$E$155 | N83: =CALC!$F$155 | P83: =CALC!$G$155
A84: =CALC!$A$156 | C84: =CALC!$B$156 | E84: =CALC!$C$156 | J84: =CALC!$D$156 | L84: =CALC!$E$156 | N84: =CALC!$F$156 | P84: =CALC!$G$156
A87: DÉCISIONS ET ENGAGEMENTS DE LA REVUE — à renseigner pendant l'animation
A88: Écart constaté (fait mesuré) | F88: Décision prise | L88: Pilote | N88: Échéance | P88: N° d'action associé
A95: Lecture des cartes : vert = cible atteinte • orange = entre la cible et le seuil d'alerte • rouge = au-delà du seuil d'alerte. Cibles et seuils sont définis dans l'onglet PARAMETRES. Règle d'animation : toute carte rouge donne lieu, le jour même, à une action ouverte dans le PLAN_ACTIONS avec un pilote nommé et une date cible. Le graphique de suivi journalier affiche la moyenne mobile 7 jours et les limites de contrôle (moyenne ± 2 écarts-types) : un point hors limite signale une cause spéciale à investiguer, à distinguer d'une variation courante du procédé.

Sheet SAISIE_PROD
A1: SAISIE QUOTIDIENNE DE PRODUCTION
A2: Une ligne par jour, par équipe et par ligne de production. Saisir uniquement les colonnes sur fond jaune (5 minutes en fin de poste) : les colonnes bleues sont calculées et alimentent le cockpit.
A3: IDENTIFICATION | F3: TEMPS D'OUVERTURE ET PERTES DE TEMPS (minutes) | O3: PRODUCTION ET QUALITÉ | U3: RESSOURCES ET SÉCURITÉ | Z3: ANALYSE DE L'ÉCART | AB3: INDICATEURS CALCULÉS — ne rien saisir
A4: Date | B4: Équipe | C4: Ligne / ressource | D4: N° d'OF / lot | E4: Référence produit | F4: Temps d'ouverture TO (min) | G4: Arrêts planifiés (min) | H4: Pannes (min) | I4: Changement de série (min) | J4: Réglages et micro-arrêts (min) | K4: Manque matière (min) | L4: Manque personnel (min) | M4: Autres arrêts subis (min) | N4: Nombre de pannes | O4: Cadence nominale (pcs/min) | P4: Qté produite | Q4: Qté conforme 1er passage | R4: Qté retouchée | S4: Qté rebutée | T4: Qté demandée (programme) | U4: Effectif prévu | V4: Effectif présent | W4: Heures supp. | X4: Accidents avec arrêt | Y4: Presqu'accidents et situations dang. | Z4: Code arrêt principal | AA4: Problème principal du poste | AB4: Temps requis TR (min) | AC4: Arrêts subis (min) | AD4: Temps de marche TF (min) | AE4: Temps utile TU (min) | AF4: Disponibilité | AG4: Performance | AH4: Qualité RFT | AI4: TRS | AJ4: TRG | AK4: MTBF (min) | AL4: MTTR (min) | AM4: Non-conformités (ppm) | AN4: Taux de service | AO4: Taux de présence | AP4: Perte de cadence (min) | AQ4: Perte non-qualité (min) | AR4: Contrôle de cohérence | AS4: Filtre cockpit
A5: 46024 | B5: Équipe A (matin) | C5: Ligne 1 - Assemblage | D5: OF-01001 | E5: REF-1001 | F5: 480 | G5: 40 | H5: 49 | I5: 32 | J5: 0 | K5: 0 | L5: 0 | M5: 0 | N5: 1 | O5: =IF($E5="","",IFERROR(INDEX(PARAMETRES!$O$7:$O$36,MATCH($E5,PARAMETRES!$M$7:$M$36,0)),"")) | P5: 4631 | Q5: 4547 | R5: 37 | S5: 47 | T5: 4982 | U5: 12 | V5: 11 | W5: 4 | X5: 0 | Y5: 1 | Z5: PAN-01 | AA5: Panne mécanique — Assemblage | AB5: =IF($A5="","",MAX(0,$F5-$G5)) | AC5: =IF($A5="","",SUM($H5:$M5)) | AD5: =IF($A5="","",MAX(0,$AB5-$AC5)) | AE5: =IF($A5="","",IFERROR($Q5/$O5,"")) | AF5: =IF($A5="","",IFERROR($AD5/$AB5,"")) | AG5: =IF($A5="","",IFERROR(($P5/$O5)/$AD5,"")) | AH5: =IF($A5="","",IFERROR($Q5/$P5,"")) | AI5: =IF($A5="","",IFERROR($AF5*$AG5*$AH5,"")) | AJ5: =IF($A5="","",IFERROR($AE5/$F5,"")) | AK5: =IF($A5="","",IFERROR($AD5/$N5,"")) | AL5: =IF($A5="","",IFERROR($H5/$N5,"")) | AM5: =IF($A5="","",IFERROR(($P5-$Q5)/$P5*1000000,"")) | AN5: =IF($A5="","",IFERROR(($Q5+$R5)/$T5,"")) | AO5: =IF($A5="","",IFERROR($V5/$U5,"")) | AP5: =IF($A5="","",IFERROR(MAX(0,$AD5-$P5/$O5),"")) | AQ5: =IF($A5="","",IFERROR(($P5-$Q5)/$O5,"")) | AR5: =IF($A5="","",IF($F5="","Temps d'ouverture manquant",IF($O5="","Cadence produit inconnue",IF($G5>$F5,"Arrêts planifiés > temps d'ouverture",IF($AC5>$AB5,"Arrêts subis > temps requis",IF($P5<>$Q5+$R5+$S5,"Produite ≠ conforme + retouchée + rebutée",IF($Q5>$P5,"Conforme > produite",IF($V5>$U5,"Présents > prévus","OK")))))))) | AS5: =IF($A5="",0,IF(AND(OR(COCKPIT!$H$4="Toutes",$C5=COCKPIT!$H$4),OR(COCKPIT!$K$4="Toutes",$B5=COCKPIT!$K$4)),1,0))
A6: 46024 | B6: Équipe B (après-midi) | C6: Ligne 2 - Usinage | D6: OF-01002 | E6: REF-2001 | F6: 480 | G6: 40 | H6: 0 | I6: 0 | J6: 14 | K6: 10 | L6: 0 | M6: 17 | N6: 0 | O6: =IF($E6="","",IFERROR(INDEX(PARAMETRES!$O$7:$O$36,MATCH($E6,PARAMETRES!$M$7:$M$36,0)),"")) | P6: 3339 | Q6: 3288 | R6: 22 | S6: 29 | T6: 3559 | U6: 8 | V6: 8 | W6: 0 | X6: 0 | Y6: 0 | Z6: LOG-01 | AA6: Attente cariste / évacuation en-cours — Usinage | AB6: =IF($A6="","",MAX(0,$F6-$G6)) | AC6: =IF($A6="","",SUM($H6:$M6)) | AD6: =IF($A6="","",MAX(0,$AB6-$AC6)) | AE6: =IF($A6="","",IFERROR($Q6/$O6,"")) | AF6: =IF($A6="","",IFERROR($AD6/$AB6,"")) | AG6: =IF($A6="","",IFERROR(($P6/$O6)/$AD6,"")) | AH6: =IF($A6="","",IFERROR($Q6/$P6,"")) | AI6: =IF($A6="","",IFERROR($AF6*$AG6*$AH6,"")) | AJ6: =IF($A6="","",IFERROR($AE6/$F6,"")) | AK6: =IF($A6="","",IFERROR($AD6/$N6,"")) | AL6: =IF($A6="","",IFERROR($H6/$N6,"")) | AM6: =IF($A6="","",IFERROR(($P6-$Q6)/$P6*1000000,"")) | AN6: =IF($A6="","",IFERROR(($Q6+$R6)/$T6,"")) | AO6: =IF($A6="","",IFERROR($V6/$U6,"")) | AP6: =IF($A6="","",IFERROR(MAX(0,$AD6-$P6/$O6),"")) | AQ6: =IF($A6="","",IFERROR(($P6-$Q6)/$O6,"")) | AR6: =IF($A6="","",IF($F6="","Temps d'ouverture manquant",IF($O6="","Cadence produit inconnue",IF($G6>$F6,"Arrêts planifiés > temps d'ouverture",IF($AC6>$AB6,"Arrêts subis > temps requis",IF($P6<>$Q6+$R6+$S6,"Produite ≠ conforme + retouchée + rebutée",IF($Q6>$P6,"Conforme > produite",IF($V6>$U6,"Présents > prévus","OK")))))))) | AS6: =IF($A6="",0,IF(AND(OR(COCKPIT!$H$4="Toutes",$C6=COCKPIT!$H$4),OR(COCKPIT!$K$4="Toutes",$B6=COCKPIT!$K$4)),1,0))
A7: 46027 | B7: Équipe B (après-midi) | C7: Ligne 1 - Assemblage | D7: OF-01003 | E7: REF-1002 | F7: 480 | G7: 40 | H7: 53 | I7: 0 | J7: 13 | K7: 19 | L7: 29 | M7: 15 | N7: 1 | O7: =IF($E7="","",IFERROR(INDEX(PARAMETRES!$O$7:$O$36,MATCH($E7,PARAMETRES!$M$7:$M$36,0)),"")) | P7: 3421 | Q7: 3376 | R7: 20 | S7: 25 | T7: 3430 | U7: 12 | V7: 12 | W7: 0 | X7: 0 | Y7: 0 | Z7: PAN-03 | AA7: Défaut automatisme / supervision — Assemblage | AB7: =IF($A7="","",MAX(0,$F7-$G7)) | AC7: =IF($A7="","",SUM($H7:$M7)) | AD7: =IF($A7="","",MAX(0,$AB7-$AC7)) | AE7: =IF($A7="","",IFERROR($Q7/$O7,"")) | AF7: =IF($A7="","",IFERROR($AD7/$AB7,"")) | AG7: =IF($A7="","",IFERROR(($P7/$O7)/$AD7,"")) | AH7: =IF($A7="","",IFERROR($Q7/$P7,"")) | AI7: =IF($A7="","",IFERROR($AF7*$AG7*$AH7,"")) | AJ7: =IF($A7="","",IFERROR($AE7/$F7,"")) | AK7: =IF($A7="","",IFERROR($AD7/$N7,"")) | AL7: =IF($A7="","",IFERROR($H7/$N7,"")) | AM7: =IF($A7="","",IFERROR(($P7-$Q7)/$P7*1000000,"")) | AN7: =IF($A7="","",IFERROR(($Q7+$R7)/$T7,"")) | AO7: =IF($A7="","",IFERROR($V7/$U7,"")) | AP7: =IF($A7="","",IFERROR(MAX(0,$AD7-$P7/$O7),"")) | AQ7: =IF($A7="","",IFERROR(($P7-$Q7)/$O7,"")) | AR7: =IF($A7="","",IF($F7="","Temps d'ouverture manquant",IF($O7="","Cadence produit inconnue",IF($G7>$F7,"Arrêts planifiés > temps d'ouverture",IF($AC7>$AB7,"Arrêts subis > temps requis",IF($P7<>$Q7+$R7+$S7,"Produite ≠ conforme + retouchée + rebutée",IF($Q7>$P7,"Conforme > produite",IF($V7>$U7,"Présents > prévus","OK")))))))) | AS7: =IF($A7="",0,IF(AND(OR(COCKPIT!$H$4="Toutes",$C7=COCKPIT!$H$4),OR(COCKPIT!$K$4="Toutes",$B7=COCKPIT!$K$4)),1,0))
A8: 46027 | B8: Équipe A (matin) | C8: Ligne 2 - Usinage | D8: OF-01004 | E8: REF-2002 | F8: 480 | G8: 40 | H8: 29 | I8: 0 | J8: 0 | K8: 0 | L8: 0 | M8: 9 | N8: 1 | O8: =IF($E8="","",IFERROR(INDEX(PARAMETRES!$O$7:$O$36,MATCH($E8,PARAMETRES!$M$7:$M$36,0)),"")) | P8: 2864 | Q8: 2835 | R8: 13 | S8: 16 | T8: 2848 | U8: 8 | V8: 8 | W8: 0 | X8: 0 | Y8: 0 | Z8: PAN-02 | AA8: Panne électrique ou capteur — Usinage | AB8: =IF($A8="","",MAX(0,$F8-$G8)) | AC8: =IF($A8="","",SUM($H8:$M8)) | AD8: =IF($A8="","",MAX(0,$AB8-$AC8)) | AE8: =IF($A8="","",IFERROR($Q8/$O8,"")) | AF8: =IF($A8="","",IFERROR($AD8/$AB8,"")) | AG8: =IF($A8="","",IFERROR(($P8/$O8)/$AD8,"")) | AH8: =IF($A8="","",IFERROR($Q8/$P8,"")) | AI8: =IF($A8="","",IFERROR($AF8*$AG8*$AH8,"")) | AJ8: =IF($A8="","",IFERROR($AE8/$F8,"")) | AK8: =IF($A8="","",IFERROR($AD8/$N8,"")) | AL8: =IF($A8="","",IFERROR($H8/$N8,"")) | AM8: =IF($A8="","",IFERROR(($P8-$Q8)/$P8*1000000,"")) | AN8: =IF($A8="","",IFERROR(($Q8+$R8)/$T8,"")) | AO8: =IF($A8="","",IFERROR($V8/$U8,"")) | AP8: =IF($A8="","",IFERROR(MAX(0,$AD8-$P8/$O8),"")) | AQ8: =IF($A8="","",IFERROR(($P8-$Q8)/$O8,"")) | AR8: =IF($A8="","",IF($F8="","Temps d'ouverture manquant",IF($O8="","Cadence produit inconnue",IF($G8>$F8,"Arrêts planifiés > temps d'ouverture",IF($AC8>$AB8,"Arrêts subis > temps requis",IF($P8<>$Q8+$R8+$S8,"Produite ≠ conforme + retouchée + rebutée",IF($Q8>$P8,"Conforme > produite",IF($V8>$U8,"Présents > prévus","OK")))))))) | AS8: =IF($A8="",0,IF(AND(OR(COCKPIT!$H$4="Toutes",$C8=COCKPIT!$H$4),OR(COCKPIT!$K$4="Toutes",$B8=COCKPIT!$K$4)),1,0))
A9: 46028 | B9: Équipe A (matin) | C9: Ligne 1 - Assemblage | D9: OF-01005 | E9: REF-1001 | F9: 480 | G9: 100 | H9: 26 | I9: 18 | J9: 14 | K9: 0 | L9: 15 | M9: 0 | N9: 1 | O9: =IF($E9="","",IFERROR(INDEX(PARAMETRES!$O$7:$O$36,MATCH($E9,PARAMETRES!$M$7:$M$36,0)),"")) | P9: 4144 | Q9: 4110 | R9: 15 | S9: 19 | T9: 4252 | U9: 12 | V9: 12 | W9: 0 | X9: 0 | Y9: 0 | Z9: PAN-01 | AA9: Panne mécanique — Assemblage | AB9: =IF($A9="","",MAX(0,$F9-$G9)) | AC9: =IF($A9="","",SUM($H9:$M9)) | AD9: =IF($A9="","",MAX(0,$AB9-$AC9)) | AE9: =IF($A9="","",IFERROR($Q9/$O9,"")) | AF9: =IF($A9="","",IFERROR($AD9/$AB9,"")) | AG9: =IF($A9="","",IFERROR(($P9/$O9)/$AD9,"")) | AH9: =IF($A9="","",IFERROR($Q9/$P9,"")) | AI9: =IF($A9="","",IFERROR($AF9*$AG9*$AH9,"")) | AJ9: =IF($A9="","",IFERROR($AE9/$F9,"")) | AK9: =IF($A9="","",IFERROR($AD9/$N9,"")) | AL9: =IF($A9="","",IFERROR($H9/$N9,"")) | AM9: =IF($A9="","",IFERROR(($P9-$Q9)/$P9*1000000,"")) | AN9: =IF($A9="","",IFERROR(($Q9+$R9)/$T9,"")) | AO9: =IF($A9="","",IFERROR($V9/$U9,"")) | AP9: =IF($A9="","",IFERROR(MAX(0,$AD9-$P9/$O9),"")) | AQ9: =IF($A9="","",IFERROR(($P9-$Q9)/$O9,"")) | AR9: =IF($A9="","",IF($F9="","Temps d'ouverture manquant",IF($O9="","Cadence produit inconnue",IF($G9>$F9,"Arrêts planifiés > temps d'ouverture",IF($AC9>$AB9,"Arrêts subis > temps requis",IF($P9<>$Q9+$R9+$S9,"Produite ≠ conforme + retouchée + rebutée",IF($Q9>$P9,"Conforme > produite",IF($V9>$U9,"Présents > prévus","OK")))))))) | AS9: =IF($A9="",0,IF(AND(OR(COCKPIT!$H$4="Toutes",$C9=COCKPIT!$H$4),OR(COCKPIT!$K$4="Toutes",$B9=COCKPIT!$K$4)),1,0))
A10: 46028 | B10: Équipe B (après-midi) | C10: Ligne 2 - Usinage | D10: OF-01006 | E10: REF-2001 | F10: 480 | G10: 100 | H10: 23 | I10: 35 | J10: 8 | K10: 17 | L10: 0 | M10: 9 | N10: 1 | O10: =IF($E10="","",IFERROR(INDEX(PARAMETRES!$O$7:$O$36,MATCH($E10,PARAMETRES!$M$7:$M$36,0)),"")) | P10: 2229 | Q10: 2217 | R10: 5 | S10: 7 | T10: 2267 | U10: 8 | V10: 7 | W10: 0 | X10: 0 | Y10: 0 | Z10: CDS-01 | AA10: Changement de série (outillage) — Usinage | AB10: =IF($A10="","",MAX(0,$F10-$G10)) | AC10: =IF($A10="","",SUM($H10:$M10)) | AD10: =IF($A10="","",MAX(0,$AB10-$AC10)) | AE10: =IF($A10="","",IFERROR($Q10/$O10,"")) | AF10: =IF($A10="","",IFERROR($AD10/$AB10,"")) | AG10: =IF($A10="","",IFERROR(($P10/$O10)/$AD10,"")) | AH10: =IF($A10="","",IFERROR($Q10/$P10,"")) | AI10: =IF($A10="","",IFERROR($AF10*$AG10*$AH10,"")) | AJ10: =IF($A10="","",IFERROR($AE10/$F10,"")) | AK10: =IF($A10="","",IFERROR($AD10/$N10,"")) | AL10: =IF($A10="","",IFERROR($H10/$N10,"")) | AM10: =IF($A10="","",IFERROR(($P10-$Q10)/$P10*1000000,"")) | AN10: =IF($A10="","",IFERROR(($Q10+$R10)/$T10,"")) | AO10: =IF($A10="","",IFERROR($V10/$U10,"")) | AP10: =IF($A10="","",IFERROR(MAX(0,$AD10-$P10/$O10),"")) | AQ10: =IF($A10="","",IFERROR(($P10-$Q10)/$O10,"")) | AR10: =IF($A10="","",IF($F10="","Temps d'ouverture manquant",IF($O10="","Cadence produit inconnue",IF($G10>$F10,"Arrêts planifiés > temps d'ouverture",IF($AC10>$AB10,"Arrêts subis > temps requis",IF($P10<>$Q10+$R10+$S10,"Produite ≠ conforme + retouchée + rebutée",IF($Q10>$P10,"Conforme > produite",IF($V10>$U10,"Présents > prévus","OK")))))))) | AS10: =IF($A10="",0,IF(AND(OR(COCKPIT!$H$4="Toutes",$C10=COCKPIT!$H$4),OR(COCKPIT!$K$4="Toutes",$B10=COCKPIT!$K$4)),1,0))
A11: 46029 | B11: Équipe B (après-midi) | C11: Ligne 1 - Assemblage | D11: OF-01007 | E11: REF-1002 | F11: 480 | G11: 40 | H11: 0 | I11: 0 | J11: 0 | K11: 16 | L11: 17 | M11: 9 | N11: 0 | O11: =IF($E11="","",IFERROR(INDEX(PARAMETRES!$O$7:$O$36,MATCH($E11,PARAMETRES!$M$7:$M$36,0)),"")) | P11: 4577 | Q11: 4499 | R11: 35 | S11: 43 | T11: 4772 | U11: 12 | V11: 12 | W11: 0 | X11: 0 | Y11: 0 | Z11: PER-02 | AA11: Accompagnement / montée en compétence — Assemblage | AB11: =IF($A11="","",MAX(0,$F11-$G11)) | AC11: =IF($A11="","",SUM($H11:$M11)) | AD11: =IF($A11="","",MAX(0,$AB11-$AC11)) | AE11: =IF($A11="","",IFERROR($Q11/$O11,"")) | AF11: =IF($A11="","",IFERROR($AD11/$AB11,"")) | AG11: =IF($A11="","",IFERROR(($P11/$O11)/$AD11,"")) | AH11: =IF($A11="","",IFERROR($Q11/$P11,"")) | AI11: =IF($A11="","",IFERROR($AF11*$AG11*$AH11,"")) | AJ11: =IF($A11="","",IFERROR($AE11/$F11,"")) | AK11: =IF($A11="","",IFERROR($AD11/$N11,"")) | AL11: =IF($A11="","",IFERROR($H11/$N11,"")) | AM11: =IF($A11="","",IFERROR(($P11-$Q11)/$P11*1000000,"")) | AN11: =IF($A11="","",IFERROR(($Q11+$R11)/$T11,"")) | AO11: =IF($A11="","",IFERROR($V11/$U11,"")) | AP11: =IF($A11="","",IFERROR(MAX(0,$AD11-$P11/$O11),"")) | AQ11: =IF($A11="","",IFERROR(($P11-$Q11)/$O11,"")) | AR11: =IF($A11="","",IF($F11="","Temps d'ouverture manquant",IF($O11="","Cadence produit inconnue",IF($G11>$F11,"Arrêts planifiés > temps d'ouverture",IF($AC11>$AB11,"Arrêts subis > temps requis",IF($P11<>$Q11+$R11+$S11,"Produite ≠ conforme + retouchée + rebutée",IF($Q11>$P11,"Conforme > produite",IF($V11>$U11,"Présents > prévus","OK")))))))) | AS11: =IF($A11="",0,IF(AND(OR(COCKPIT!$H$4="Toutes",$C11=COCKPIT!$H$4),OR(COCKPIT!$K$4="Toutes",$B11=COCKPIT!$K$4)),1,0))
A12: 46029 | B12: Équipe A (matin) | C12: Ligne 2 - Usinage | D12: OF-01008 | E12: REF-2002 | F12: 480 | G12: 40 | H12: 42 | I12: 17 | J12: 0 | K12: 12 | L12: 0 | M12: 9 | N12: 1 | O12: =IF($E12="","",IFERROR(INDEX(PARAMETRES!$O$7:$O$36,MATCH($E12,PARAMETRES!$M$7:$M$36,0)),"")) | P12: 2376 | Q12: 2342 | R12: 15 | S12: 19 | T12: 2455 | U12: 8 | V12: 8 | W12: 0 | X12: 0 | Y12: 0 | Z12: PAN-02 | AA12: Panne électrique ou capteur — Usinage | AB12: =IF($A12="","",MAX(0,$F12-$G12)) | AC12: =IF($A12="","",SUM($H12:$M12)) | AD12: =IF($A12="","",MAX(0,$AB12-$AC12)) | AE12: =IF($A12="","",IFERROR($Q12/$O12,"")) | AF12: =IF($A12="","",IFERROR($AD12/$AB12,"")) | AG12: =IF($A12="","",IFERROR(($P12/$O12)/$AD12,"")) | AH12: =IF($A12="","",IFERROR($Q12/$P12,"")) | AI12: =IF($A12="","",IFERROR($AF12*$AG12*$AH12,"")) | AJ12: =IF($A12="","",IFERROR($AE12/$F12,"")) | AK12: =IF($A12="","",IFERROR($AD12/$N12,"")) | AL12: =IF($A12="","",IFERROR($H12/$N12,"")) | AM12: =IF($A12="","",IFERROR(($P12-$Q12)/$P12*1000000,"")) | AN12: =IF($A12="","",IFERROR(($Q12+$R12)/$T12,"")) | AO12: =IF($A12="","",IFERROR($V12/$U12,"")) | AP12: =IF($A12="","",IFERROR(MAX(0,$AD12-$P12/$O12),"")) | AQ12: =IF($A12="","",IFERROR(($P12-$Q12)/$O12,"")) | AR12: =IF($A12="","",IF($F12="","Temps d'ouverture manquant",IF($O12="","Cadence produit inconnue",IF($G12>$F12,"Arrêts planifiés > temps d'ouverture",IF($AC12>$AB12,"Arrêts subis > temps requis",IF($P12<>$Q12+$R12+$S12,"Produite ≠ conforme + retouchée + rebutée",IF($Q12>$P12,"Conforme > produite",IF($V12>$U12,"Présents > prévus","OK")))))))) | AS12: =IF($A12="",0,IF(AND(OR(COCKPIT!$H$4="Toutes",$C12=COCKPIT!$H$4),OR(COCKPIT!$K$4="Toutes",$B12=COCKPIT!$K$4)),1,0))
A13: 46030 | B13: Équipe A (matin) | C13: Ligne 1 - Assemblage | D13: OF-01009 | E13: REF-1001 | F13: 480 | G13: 40 | H13: 24 | I13: 18 | J13: 0 | K13: 0 | L13: 0 | M13: 0 | N13: 1 | O13: =IF($E13="","",IFERROR(INDEX(PARAMETRES!$O$7:$O$36,MATCH($E13,PARAMETRES!$M$7:$M$36,0)),"")) | P13: 5611 | Q13: 5543 | R13: 30 | S13: 38 | T13: 5992 | U13: 12 | V13: 12 | W13: 0 | X13: 0 | Y13: 0 | Z13: PAN-01 | AA13: Panne mécanique — Assemblage | AB13: =IF($A13="","",MAX(0,$F13-$G13)) | AC13: =IF($A13="","",SUM($H13:$M13)) | AD13: =IF($A13="","",MAX(0,$AB13-$AC13)) | AE13: =IF($A13="","",IFERROR($Q13/$O13,"")) | AF13: =IF($A13="","",IFERROR($AD13/$AB13,"")) | AG13: =IF($A13="","",IFERROR(($P13/$O13)/$AD13,"")) | AH13: =IF($A13="","",IFERROR($Q13/$P13,"")) | AI13: =IF($A13="","",IFERROR($AF13*$AG13*$AH13,"")) | AJ13: =IF($A13="","",IFERROR($AE13/$F13,"")) | AK13: =IF($A13="","",IFERROR($AD13/$N13,"")) | AL13: =IF($A13="","",IFERROR($H13/$N13,"")) | AM13: =IF($A13="","",IFERROR(($P13-$Q13)/$P13*1000000,"")) | AN13: =IF($A13="","",IFERROR(($Q13+$R13)/$T13,"")) | AO13: =IF($A13="","",IFERROR($V13/$U13,"")) | AP13: =IF($A13="","",IFERROR(MAX(0,$AD13-$P13/$O13),"")) | AQ13: =IF($A13="","",IFERROR(($P13-$Q13)/$O13,"")) | AR13: =IF($A13="","",IF($F13="","Temps d'ouverture manquant",IF($O13="","Cadence produit inconnue",IF($G13>$F13,"Arrêts planifiés > temps d'ouverture",IF($AC13>$AB13,"Arrêts subis > temps requis",IF($P13<>$Q13+$R13+$S13,"Produite ≠ conforme + retouchée + rebutée",IF($Q13>$P13,"Conforme > produite",IF($V13>$U13,"Présents > prévus","OK")))))))) | AS13: =IF($A13="",0,IF(AND(OR(COCKPIT!$H$4="Toutes",$C13=COCKPIT!$H$4),OR(COCKPIT!$K$4="Toutes",$B13=COCKPIT!$K$4)),1,0))
A14: 46030 | B14: Équipe B (après-midi) | C14: Ligne 2 - Usinage | D14: OF-01010 | E14: REF-2001 | F14: 480 | G14: 40 | H14: 0 | I14: 0 | J14: 7 | K14: 23 | L14: 0 | M14: 14 | N14: 0 | O14: =IF($E14="","",IFERROR(INDEX(PARAMETRES!$O$7:$O$36,MATCH($E14,PARAMETRES!$M$7:$M$36,0)),"")) | P14: 3207 | Q14: 3178 | R14: 13 | S14: 16 | T14: 3394 | U14: 8 | V14: 8 | W14: 0 | X14: 0 | Y14: 1 | Z14: MAT-02 | AA14: Matière non conforme (rebut fournisseur) — Usinage | AB14: =IF($A14="","",MAX(0,$F14-$G14)) | AC14: =IF($A14="","",SUM($H14:$M14)) | AD14: =IF($A14="","",MAX(0,$AB14-$AC14)) | AE14: =IF($A14="","",IFERROR($Q14/$O14,"")) | AF14: =IF($A14="","",IFERROR($AD14/$AB14,"")) | AG14: =IF($A14="","",IFERROR(($P14/$O14)/$AD14,"")) | AH14: =IF($A14="","",IFERROR($Q14/$P14,"")) | AI14: =IF($A14="","",IFERROR($AF14*$AG14*$AH14,"")) | AJ14: =IF($A14="","",IFERROR($AE14/$F14,"")) | AK14: =IF($A14="","",IFERROR($AD14/$N14,"")) | AL14: =IF($A14="","",IFERROR($H14/$N14,"")) | AM14: =IF($A14="","",IFERROR(($P14-$Q14)/$P14*1000000,"")) | AN14: =IF($A14="","",IFERROR(($Q14+$R14)/$T14,"")) | AO14: =IF($A14="","",IFERROR($V14/$U14,"")) | AP14: =IF($A14="","",IFERROR(MAX(0,$AD14-$P14/$O14),"")) | AQ14: =IF($A14="","",IFERROR(($P14-$Q14)/$O14,"")) | AR14: =IF($A14="","",IF($F14="","Temps d'ouverture manquant",IF($O14="","Cadence produit inconnue",IF($G14>$F14,"Arrêts planifiés > temps d'ouverture",IF($AC14>$AB14,"Arrêts subis > temps requis",IF($P14<>$Q14+$R14+$S14,"Produite ≠ conforme + retouchée + rebutée",IF($Q14>$P14,"Conforme > produite",IF($V14>$U14,"Présents > prévus","OK")))))))) | AS14: =IF($A14="",0,IF(AND(OR(COCKPIT!$H$4="Toutes",$C14=COCKPIT!$H$4),OR(COCKPIT!$K$4="Toutes",$B14=COCKPIT!$K$4)),1,0))
A15: 46031 | B15: Équipe B (après-midi) | C15: Ligne 1 - Assemblage | D15: OF-01011 | E15: REF-1002 | F15: 480 | G15: 40 | H15: 37 | I15: 0 | J15: 12 | K15: 19 | L15: 24 | M15: 10 | N15: 1 | O15: =IF($E15="","",IFERROR(INDEX(PARAMETRES!$O$7:$O$36,MATCH($E15,PARAMETRES!$M$7:$M$36,0)),"")) | P15: 4056 | Q15: 4027 | R15: 13 | S15: 16 | T15: 4040 | U15: 12 | V15: 12 | W15: 0 | X15: 0 | Y15: 0 | Z15: PAN-03 | AA15: Défaut automatisme / supervision — Assemblage | AB15: =IF($A15="","",MAX(0,$F15-$G15)) | AC15: =IF($A15="","",SUM($H15:$M15)) | AD15: =IF($A15="","",MAX(0,$AB15-$AC15)) | AE15: =IF($A15="","",IFERROR($Q15/$O15,"")) | AF15: =IF($A15="","",IFERROR($AD15/$AB15,"")) | AG15: =IF($A15="","",IFERROR(($P15/$O15)/$AD15,"")) | AH15: =IF($A15="","",IFERROR($Q15/$P15,"")) | AI15: =IF($A15="","",IFERROR($AF15*$AG15*$AH15,"")) | AJ15: =IF($A15="","",IFERROR($AE15/$F15,"")) | AK15: =IF($A15="","",IFERROR($AD15/$N15,"")) | AL15: =IF($A15="","",IFERROR($H15/$N15,"")) | AM15: =IF($A15="","",IFERROR(($P15-$Q15)/$P15*1000000,"")) | AN15: =IF($A15="","",IFERROR(($Q15+$R15)/$T15,"")) | AO15: =IF($A15="","",IFERROR($V15/$U15,"")) | AP15: =IF($A15="","",IFERROR(MAX(0,$AD15-$P15/$O15),"")) | AQ15: =IF($A15="","",IFERROR(($P15-$Q15)/$O15,"")) | AR15: =IF($A15="","",IF($F15="","Temps d'ouverture manquant",IF($O15="","Cadence produit inconnue",IF($G15>$F15,"Arrêts planifiés > temps d'ouverture",IF($AC15>$AB15,"Arrêts subis > temps requis",IF($P15<>$Q15+$R15+$S15,"Produite ≠ conforme + retouchée + rebutée",IF($Q15>$P15,"Conforme > produite",IF($V15>$U15,"Présents > prévus","OK")))))))) | AS15: =IF($A15="",0,IF(AND(OR(COCKPIT!$H$4="Toutes",$C15=COCKPIT!$H$4),OR(COCKPIT!$K$4="Toutes",$B15=COCKPIT!$K$4)),1,0))
A16: 46031 | B16: Équipe A (matin) | C16: Ligne 2 - Usinage | D16: OF-01012 | E16: REF-2002 | F16: 480 | G16: 40 | H16: 23 | I16: 0 | J16: 0 | K16: 0 | L16: 0 | M16: 20 | N16: 1 | O16: =IF($E16="","",IFERROR(INDEX(PARAMETRES!$O$7:$O$36,MATCH($E16,PARAMETRES!$M$7:$M$36,0)),"")) | P16: 2739 | Q16: 2689 | R16: 22 | S16: 28 | T16: 2946 | U16: 8 | V16: 8 | W16: 4 | X16: 0 | Y16: 0 | Z16: PAN-02 | AA16: Panne électrique ou capteur — Usinage | AB16: =IF($A16="","",MAX(0,$F16-$G16)) | AC16: =IF($A16="","",SUM($H16:$M16)) | AD16: =IF($A16="","",MAX(0,$AB16-$AC16)) | AE16: =IF($A16="","",IFERROR($Q16/$O16,"")) | AF16: =IF($A16="","",IFERROR($AD16/$AB16,"")) | AG16: =IF($A16="","",IFERROR(($P16/$O16)/$AD16,"")) | AH16: =IF($A16="","",IFERROR($Q16/$P16,"")) | AI16: =IF($A16="","",IFERROR($AF16*$AG16*$AH16,"")) | AJ16: =IF($A16="","",IFERROR($AE16/$F16,"")) | AK16: =IF($A16="","",IFERROR($AD16/$N16,"")) | AL16: =IF($A16="","",IFERROR($H16/$N16,"")) | AM16: =IF($A16="","",IFERROR(($P16-$Q16)/$P16*1000000,"")) | AN16: =IF($A16="","",IFERROR(($Q16+$R16)/$T16,"")) | AO16: =IF($A16="","",IFERROR($V16/$U16,"")) | AP16: =IF($A16="","",IFERROR(MAX(0,$AD16-$P16/$O16),"")) | AQ16: =IF($A16="","",IFERROR(($P16-$Q16)/$O16,"")) | AR16: =IF($A16="","",IF($F16="","Temps d'ouverture manquant",IF($O16="","Cadence produit inconnue",IF($G16>$F16,"Arrêts planifiés > temps d'ouverture",IF($AC16>$AB16,"Arrêts subis > temps requis",IF($P16<>$Q16+$R16+$S16,"Produite ≠ conforme + retouchée + rebutée",IF($Q16>$P16,"Conforme > produite",IF($V16>$U16,"Présents > prévus","OK")))))))) | AS16: =IF($A16="",0,IF(AND(OR(COCKPIT!$H$4="Toutes",$C16=COCKPIT!$H$4),OR(COCKPIT!$K$4="Toutes",$B16=COCKPIT!$K$4)),1,0))
... A46: 46052 | B46: Équipe B (après-midi) | C46: Ligne 2 - Usinage | D46: OF-01042 | E46: REF-2001 | F46: 480 | G46: 40 | H46: 0 | I46: 0 | J46: 8 | K46: 20 | L46: 0 | M46: 11 | N46: 0 | O46: =IF($E46="","",IFERROR(INDEX(PARAMETRES!$O$7:$O$36,MATCH($E46,PARAMETRES!$M$7:$M$36,0)),"")) | P46: 3212 | Q46: 3170 | R46: 18 | S46: 24 | T46: 3253 | U46: 8 | V46: 8 | W46: 0 | X46: 0 | Y46: 0 | Z46: MAT-02 | AA46: Matière non conforme (rebut fournisseur) — Usinage | AB46: =IF($A46="","",MAX(0,$F46-$G46)) | AC46: =IF($A46="","",SUM($H46:$M46)) | AD46: =IF($A46="","",MAX(0,$AB46-$AC46)) | AE46: =IF($A46="","",IFERROR($Q46/$O46,"")) | AF46: =IF($A46="","",IFERROR($AD46/$AB46,"")) | AG46: =IF($A46="","",IFERROR(($P46/$O46)/$AD46,"")) | AH46: =IF($A46="","",IFERROR($Q46/$P46,"")) | AI46: =IF($A46="","",IFERROR($AF46*$AG46*$AH46,"")) | AJ46: =IF($A46="","",IFERROR($AE46/$F46,"")) | AK46: =IF($A46="","",IFERROR($AD46/$N46,"")) | AL46: =IF($A46="","",IFERROR($H46/$N46,"")) | AM46: =IF($A46="","",IFERROR(($P46-$Q46)/$P46*1000000,"")) | AN46: =IF($A46="","",IFERROR(($Q46+$R46)/$T46,"")) | AO46: =IF($A46="","",IFERROR($V46/$U46,"")) | AP46: =IF($A46="","",IFERROR(MAX(0,$AD46-$P46/$O46),"")) | AQ46: =IF($A46="","",IFERROR(($P46-$Q46)/$O46,"")) | AR46: =IF($A46="","",IF($F46="","Temps d'ouverture manquant",IF($O46="","Cadence produit inconnue",IF($G46>$F46,"Arrêts planifiés > temps d'ouverture",IF($AC46>$AB46,"Arrêts subis > temps requis",IF($P46<>$Q46+$R46+$S46,"Produite ≠ conforme + retouchée + rebutée",IF($Q46>$P46,"Conforme > produite",IF($V46>$U46,"Présents > prévus","OK")))))))) | AS46: =IF($A46="",0,IF(AND(OR(COCKPIT!$H$4="Toutes",$C46=COCKPIT!$H$4),OR(COCKPIT!$K$4="Toutes",$B46=COCKPIT!$K$4)),1,0))
O47: =IF($E47="","",IFERROR(INDEX(PARAMETRES!$O$7:$O$36,MATCH($E47,PARAMETRES!$M$7:$M$36,0)),"")) | AB47: =IF($A47="","",MAX(0,$F47-$G47)) | AC47: =IF($A47="","",SUM($H47:$M47)) | AD47: =IF($A47="","",MAX(0,$AB47-$AC47)) | AE47: =IF($A47="","",IFERROR($Q47/$O47,"")) | AF47: =IF($A47="","",IFERROR($AD47/$AB47,"")) | AG47: =IF($A47="","",IFERROR(($P47/$O47)/$AD47,"")) | AH47: =IF($A47="","",IFERROR($Q47/$P47,"")) | AI47: =IF($A47="","",IFERROR($AF47*$AG47*$AH47,"")) | AJ47: =IF($A47="","",IFERROR($AE47/$F47,"")) | AK47: =IF($A47="","",IFERROR($AD47/$N47,"")) | AL47: =IF($A47="","",IFERROR($H47/$N47,"")) | AM47: =IF($A47="","",IFERROR(($P47-$Q47)/$P47*1000000,"")) | AN47: =IF($A47="","",IFERROR(($Q47+$R47)/$T47,"")) | AO47: =IF($A47="","",IFERROR($V47/$U47,"")) | AP47: =IF($A47="","",IFERROR(MAX(0,$AD47-$P47/$O47),"")) | AQ47: =IF($A47="","",IFERROR(($P47-$Q47)/$O47,"")) | AR47: =IF($A47="","",IF($F47="","Temps d'ouverture manquant",IF($O47="","Cadence produit inconnue",IF($G47>$F47,"Arrêts planifiés > temps d'ouverture",IF($AC47>$AB47,"Arrêts subis > temps requis",IF($P47<>$Q47+$R47+$S47,"Produite ≠ conforme + retouchée + rebutée",IF($Q47>$P47,"Conforme > produite",IF($V47>$U47,"Présents > prévus","OK")))))))) | AS47: =IF($A47="",0,IF(AND(OR(COCKPIT!$H$4="Toutes",$C47=COCKPIT!$H$4),OR(COCKPIT!$K$4="Toutes",$B47=COCKPIT!$K$4)),1,0))
O48: =IF($E48="","",IFERROR(INDEX(PARAMETRES!$O$7:$O$36,MATCH($E48,PARAMETRES!$M$7:$M$36,0)),"")) | AB48: =IF($A48="","",MAX(0,$F48-$G48)) | AC48: =IF($A48="","",SUM($H48:$M48)) | AD48: =IF($A48="","",MAX(0,$AB48-$AC48)) | AE48: =IF($A48="","",IFERROR($Q48/$O48,"")) | AF48: =IF($A48="","",IFERROR($AD48/$AB48,"")) | AG48: =IF($A48="","",IFERROR(($P48/$O48)/$AD48,"")) | AH48: =IF($A48="","",IFERROR($Q48/$P48,"")) | AI48: =IF($A48="","",IFERROR($AF48*$AG48*$AH48,"")) | AJ48: =IF($A48="","",IFERROR($AE48/$F48,"")) | AK48: =IF($A48="","",IFERROR($AD48/$N48,"")) | AL48: =IF($A48="","",IFERROR($H48/$N48,"")) | AM48: =IF($A48="","",IFERROR(($P48-$Q48)/$P48*1000000,"")) | AN48: =IF($A48="","",IFERROR(($Q48+$R48)/$T48,"")) | AO48: =IF($A48="","",IFERROR($V48/$U48,"")) | AP48: =IF($A48="","",IFERROR(MAX(0,$AD48-$P48/$O48),"")) | AQ48: =IF($A48="","",IFERROR(($P48-$Q48)/$O48,"")) | AR48: =IF($A48="","",IF($F48="","Temps d'ouverture manquant",IF($O48="","Cadence produit inconnue",IF($G48>$F48,"Arrêts planifiés > temps d'ouverture",IF($AC48>$AB48,"Arrêts subis > temps requis",IF($P48<>$Q48+$R48+$S48,"Produite ≠ conforme + retouchée + rebutée",IF($Q48>$P48,"Conforme > produite",IF($V48>$U48,"Présents > prévus","OK")))))))) | AS48: =IF($A48="",0,IF(AND(OR(COCKPIT!$H$4="Toutes",$C48=COCKPIT!$H$4),OR(COCKPIT!$K$4="Toutes",$B48=COCKPIT!$K$4)),1,0))
O49: =IF($E49="","",IFERROR(INDEX(PARAMETRES!$O$7:$O$36,MATCH($E49,PARAMETRES!$M$7:$M$36,0)),"")) | AB49: =IF($A49="","",MAX(0,$F49-$G49)) | AC49: =IF($A49="","",SUM($H49:$M49)) | AD49: =IF($A49="","",MAX(0,$AB49-$AC49)) | AE49: =IF($A49="","",IFERROR($Q49/$O49,"")) | AF49: =IF($A49="","",IFERROR($AD49/$AB49,"")) | AG49: =IF($A49="","",IFERROR(($P49/$O49)/$AD49,"")) | AH49: =IF($A49="","",IFERROR($Q49/$P49,"")) | AI49: =IF($A49="","",IFERROR($AF49*$AG49*$AH49,"")) | AJ49: =IF($A49="","",IFERROR($AE49/$F49,"")) | AK49: =IF($A49="","",IFERROR($AD49/$N49,"")) | AL49: =IF($A49="","",IFERROR($H49/$N49,"")) | AM49: =IF($A49="","",IFERROR(($P49-$Q49)/$P49*1000000,"")) | AN49: =IF($A49="","",IFERROR(($Q49+$R49)/$T49,"")) | AO49: =IF($A49="","",IFERROR($V49/$U49,"")) | AP49: =IF($A49="","",IFERROR(MAX(0,$AD49-$P49/$O49),"")) | AQ49: =IF($A49="","",IFERROR(($P49-$Q49)/$O49,"")) | AR49: =IF($A49="","",IF($F49="","Temps d'ouverture manquant",IF($O49="","Cadence produit inconnue",IF($G49>$F49,"Arrêts planifiés > temps d'ouverture",IF($AC49>$AB49,"Arrêts subis > temps requis",IF($P49<>$Q49+$R49+$S49,"Produite ≠ conforme + retouchée + rebutée",IF($Q49>$P49,"Conforme > produite",IF($V49>$U49,"Présents > prévus","OK")))))))) | AS49: =IF($A49="",0,IF(AND(OR(COCKPIT!$H$4="Toutes",$C49=COCKPIT!$H$4),OR(COCKPIT!$K$4="Toutes",$B49=COCKPIT!$K$4)),1,0))
O50: =IF($E50="","",IFERROR(INDEX(PARAMETRES!$O$7:$O$36,MATCH($E50,PARAMETRES!$M$7:$M$36,0)),"")) | AB50: =IF($A50="","",MAX(0,$F50-$G50)) | AC50: =IF($A50="","",SUM($H50:$M50)) | AD50: =IF($A50="","",MAX(0,$AB50-$AC50)) | AE50: =IF($A50="","",IFERROR($Q50/$O50,"")) | AF50: =IF($A50="","",IFERROR($AD50/$AB50,"")) | AG50: =IF($A50="","",IFERROR(($P50/$O50)/$AD50,"")) | AH50: =IF($A50="","",IFERROR($Q50/$P50,"")) | AI50: =IF($A50="","",IFERROR($AF50*$AG50*$AH50,"")) | AJ50: =IF($A50="","",IFERROR($AE50/$F50,"")) | AK50: =IF($A50="","",IFERROR($AD50/$N50,"")) | AL50: =IF($A50="","",IFERROR($H50/$N50,"")) | AM50: =IF($A50="","",IFERROR(($P50-$Q50)/$P50*1000000,"")) | AN50: =IF($A50="","",IFERROR(($Q50+$R50)/$T50,"")) | AO50: =IF($A50="","",IFERROR($V50/$U50,"")) | AP50: =IF($A50="","",IFERROR(MAX(0,$AD50-$P50/$O50),"")) | AQ50: =IF($A50="","",IFERROR(($P50-$Q50)/$O50,"")) | AR50: =IF($A50="","",IF($F50="","Temps d'ouverture manquant",IF($O50="","Cadence produit inconnue",IF($G50>$F50,"Arrêts planifiés > temps d'ouverture",IF($AC50>$AB50,"Arrêts subis > temps requis",IF($P50<>$Q50+$R50+$S50,"Produite ≠ conforme + retouchée + rebutée",IF($Q50>$P50,"Conforme > produite",IF($V50>$U50,"Présents > prévus","OK")))))))) | AS50: =IF($A50="",0,IF(AND(OR(COCKPIT!$H$4="Toutes",$C50=COCKPIT!$H$4),OR(COCKPIT!$K$4="Toutes",$B50=COCKPIT!$K$4)),1,0))
O51: =IF($E51="","",IFERROR(INDEX(PARAMETRES!$O$7:$O$36,MATCH($E51,PARAMETRES!$M$7:$M$36,0)),"")) | AB51: =IF($A51="","",MAX(0,$F51-$G51)) | AC51: =IF($A51="","",SUM($H51:$M51)) | AD51: =IF($A51="","",MAX(0,$AB51-$AC51)) | AE51: =IF($A51="","",IFERROR($Q51/$O51,"")) | AF51: =IF($A51="","",IFERROR($AD51/$AB51,"")) | AG51: =IF($A51="","",IFERROR(($P51/$O51)/$AD51,"")) | AH51: =IF($A51="","",IFERROR($Q51/$P51,"")) | AI51: =IF($A51="","",IFERROR($AF51*$AG51*$AH51,"")) | AJ51: =IF($A51="","",IFERROR($AE51/$F51,"")) | AK51: =IF($A51="","",IFERROR($AD51/$N51,"")) | AL51: =IF($A51="","",IFERROR($H51/$N51,"")) | AM51: =IF($A51="","",IFERROR(($P51-$Q51)/$P51*1000000,"")) | AN51: =IF($A51="","",IFERROR(($Q51+$R51)/$T51,"")) | AO51: =IF($A51="","",IFERROR($V51/$U51,"")) | AP51: =IF($A51="","",IFERROR(MAX(0,$AD51-$P51/$O51),"")) | AQ51: =IF($A51="","",IFERROR(($P51-$Q51)/$O51,"")) | AR51: =IF($A51="","",IF($F51="","Temps d'ouverture manquant",IF($O51="","Cadence produit inconnue",IF($G51>$F51,"Arrêts planifiés > temps d'ouverture",IF($AC51>$AB51,"Arrêts subis > temps requis",IF($P51<>$Q51+$R51+$S51,"Produite ≠ conforme + retouchée + rebutée",IF($Q51>$P51,"Conforme > produite",IF($V51>$U51,"Présents > prévus","OK")))))))) | AS51: =IF($A51="",0,IF(AND(OR(COCKPIT!$H$4="Toutes",$C51=COCKPIT!$H$4),OR(COCKPIT!$K$4="Toutes",$B51=COCKPIT!$K$4)),1,0))
O52: =IF($E52="","",IFERROR(INDEX(PARAMETRES!$O$7:$O$36,MATCH($E52,PARAMETRES!$M$7:$M$36,0)),"")) | AB52: =IF($A52="","",MAX(0,$F52-$G52)) | AC52: =IF($A52="","",SUM($H52:$M52)) | AD52: =IF($A52="","",MAX(0,$AB52-$AC52)) | AE52: =IF($A52="","",IFERROR($Q52/$O52,"")) | AF52: =IF($A52="","",IFERROR($AD52/$AB52,"")) | AG52: =IF($A52="","",IFERROR(($P52/$O52)/$AD52,"")) | AH52: =IF($A52="","",IFERROR($Q52/$P52,"")) | AI52: =IF($A52="","",IFERROR($AF52*$AG52*$AH52,"")) | AJ52: =IF($A52="","",IFERROR($AE52/$F52,"")) | AK52: =IF($A52="","",IFERROR($AD52/$N52,"")) | AL52: =IF($A52="","",IFERROR($H52/$N52,"")) | AM52: =IF($A52="","",IFERROR(($P52-$Q52)/$P52*1000000,"")) | AN52: =IF($A52="","",IFERROR(($Q52+$R52)/$T52,"")) | AO52: =IF($A52="","",IFERROR($V52/$U52,"")) | AP52: =IF($A52="","",IFERROR(MAX(0,$AD52-$P52/$O52),"")) | AQ52: =IF($A52="","",IFERROR(($P52-$Q52)/$O52,"")) | AR52: =IF($A52="","",IF($F52="","Temps d'ouverture manquant",IF($O52="","Cadence produit inconnue",IF($G52>$F52,"Arrêts planifiés > temps d'ouverture",IF($AC52>$AB52,"Arrêts subis > temps requis",IF($P52<>$Q52+$R52+$S52,"Produite ≠ conforme + retouchée + rebutée",IF($Q52>$P52,"Conforme > produite",IF($V52>$U52,"Présents > prévus","OK")))))))) | AS52: =IF($A52="",0,IF(AND(OR(COCKPIT!$H$4="Toutes",$C52=COCKPIT!$H$4),OR(COCKPIT!$K$4="Toutes",$B52=COCKPIT!$K$4)),1,0))
O53: =IF($E53="","",IFERROR(INDEX(PARAMETRES!$O$7:$O$36,MATCH($E53,PARAMETRES!$M$7:$M$36,0)),"")) | AB53: =IF($A53="","",MAX(0,$F53-$G53)) | AC53: =IF($A53="","",SUM($H53:$M53)) | AD53: =IF($A53="","",MAX(0,$AB53-$AC53)) | AE53: =IF($A53="","",IFERROR($Q53/$O53,"")) | AF53: =IF($A53="","",IFERROR($AD53/$AB53,"")) | AG53: =IF($A53="","",IFERROR(($P53/$O53)/$AD53,"")) | AH53: =IF($A53="","",IFERROR($Q53/$P53,"")) | AI53: =IF($A53="","",IFERROR($AF53*$AG53*$AH53,"")) | AJ53: =IF($A53="","",IFERROR($AE53/$F53,"")) | AK53: =IF($A53="","",IFERROR($AD53/$N53,"")) | AL53: =IF($A53="","",IFERROR($H53/$N53,"")) | AM53: =IF($A53="","",IFERROR(($P53-$Q53)/$P53*1000000,"")) | AN53: =IF($A53="","",IFERROR(($Q53+$R53)/$T53,"")) | AO53: =IF($A53="","",IFERROR($V53/$U53,"")) | AP53: =IF($A53="","",IFERROR(MAX(0,$AD53-$P53/$O53),"")) | AQ53: =IF($A53="","",IFERROR(($P53-$Q53)/$O53,"")) | AR53: =IF($A53="","",IF($F53="","Temps d'ouverture manquant",IF($O53="","Cadence produit inconnue",IF($G53>$F53,"Arrêts planifiés > temps d'ouverture",IF($AC53>$AB53,"Arrêts subis > temps requis",IF($P53<>$Q53+$R53+$S53,"Produite ≠ conforme + retouchée + rebutée",IF($Q53>$P53,"Conforme > produite",IF($V53>$U53,"Présents > prévus","OK")))))))) | AS53: =IF($A53="",0,IF(AND(OR(COCKPIT!$H$4="Toutes",$C53=COCKPIT!$H$4),OR(COCKPIT!$K$4="Toutes",$B53=COCKPIT!$K$4)),1,0))
O54: =IF($E54="","",IFERROR(INDEX(PARAMETRES!$O$7:$O$36,MATCH($E54,PARAMETRES!$M$7:$M$36,0)),"")) | AB54: =IF($A54="","",MAX(0,$F54-$G54)) | AC54: =IF($A54="","",SUM($H54:$M54)) | AD54: =IF($A54="","",MAX(0,$AB54-$AC54)) | AE54: =IF($A54="","",IFERROR($Q54/$O54,"")) | AF54: =IF($A54="","",IFERROR($AD54/$AB54,"")) | AG54: =IF($A54="","",IFERROR(($P54/$O54)/$AD54,"")) | AH54: =IF($A54="","",IFERROR($Q54/$P54,"")) | AI54: =IF($A54="","",IFERROR($AF54*$AG54*$AH54,"")) | AJ54: =IF($A54="","",IFERROR($AE54/$F54,"")) | AK54: =IF($A54="","",IFERROR($AD54/$N54,"")) | AL54: =IF($A54="","",IFERROR($H54/$N54,"")) | AM54: =IF($A54="","",IFERROR(($P54-$Q54)/$P54*1000000,"")) | AN54: =IF($A54="","",IFERROR(($Q54+$R54)/$T54,"")) | AO54: =IF($A54="","",IFERROR($V54/$U54,"")) | AP54: =IF($A54="","",IFERROR(MAX(0,$AD54-$P54/$O54),"")) | AQ54: =IF($A54="","",IFERROR(($P54-$Q54)/$O54,"")) | AR54: =IF($A54="","",IF($F54="","Temps d'ouverture manquant",IF($O54="","Cadence produit inconnue",IF($G54>$F54,"Arrêts planifiés > temps d'ouverture",IF($AC54>$AB54,"Arrêts subis > temps requis",IF($P54<>$Q54+$R54+$S54,"Produite ≠ conforme + retouchée + rebutée",IF($Q54>$P54,"Conforme > produite",IF($V54>$U54,"Présents > prévus","OK")))))))) | AS54: =IF($A54="",0,IF(AND(OR(COCKPIT!$H$4="Toutes",$C54=COCKPIT!$H$4),OR(COCKPIT!$K$4="Toutes",$B54=COCKPIT!$K$4)),1,0))
O55: =IF($E55="","",IFERROR(INDEX(PARAMETRES!$O$7:$O$36,MATCH($E55,PARAMETRES!$M$7:$M$36,0)),"")) | AB55: =IF($A55="","",MAX(0,$F55-$G55)) | AC55: =IF($A55="","",SUM($H55:$M55)) | AD55: =IF($A55="","",MAX(0,$AB55-$AC55)) | AE55: =IF($A55="","",IFERROR($Q55/$O55,"")) | AF55: =IF($A55="","",IFERROR($AD55/$AB55,"")) | AG55: =IF($A55="","",IFERROR(($P55/$O55)/$AD55,"")) | AH55: =IF($A55="","",IFERROR($Q55/$P55,"")) | AI55: =IF($A55="","",IFERROR($AF55*$AG55*$AH55,"")) | AJ55: =IF($A55="","",IFERROR($AE55/$F55,"")) | AK55: =IF($A55="","",IFERROR($AD55/$N55,"")) | AL55: =IF($A55="","",IFERROR($H55/$N55,"")) | AM55: =IF($A55="","",IFERROR(($P55-$Q55)/$P55*1000000,"")) | AN55: =IF($A55="","",IFERROR(($Q55+$R55)/$T55,"")) | AO55: =IF($A55="","",IFERROR($V55/$U55,"")) | AP55: =IF($A55="","",IFERROR(MAX(0,$AD55-$P55/$O55),"")) | AQ55: =IF($A55="","",IFERROR(($P55-$Q55)/$O55,"")) | AR55: =IF($A55="","",IF($F55="","Temps d'ouverture manquant",IF($O55="","Cadence produit inconnue",IF($G55>$F55,"Arrêts planifiés > temps d'ouverture",IF($AC55>$AB55,"Arrêts subis > temps requis",IF($P55<>$Q55+$R55+$S55,"Produite ≠ conforme + retouchée + rebutée",IF($Q55>$P55,"Conforme > produite",IF($V55>$U55,"Présents > prévus","OK")))))))) | AS55: =IF($A55="",0,IF(AND(OR(COCKPIT!$H$4="Toutes",$C55=COCKPIT!$H$4),OR(COCKPIT!$K$4="Toutes",$B55=COCKPIT!$K$4)),1,0))
O56: =IF($E56="","",IFERROR(INDEX(PARAMETRES!$O$7:$O$36,MATCH($E56,PARAMETRES!$M$7:$M$36,0)),"")) | AB56: =IF($A56="","",MAX(0,$F56-$G56)) | AC56: =IF($A56="","",SUM($H56:$M56)) | AD56: =IF($A56="","",MAX(0,$AB56-$AC56)) | AE56: =IF($A56="","",IFERROR($Q56/$O56,"")) | AF56: =IF($A56="","",IFERROR($AD56/$AB56,"")) | AG56: =IF($A56="","",IFERROR(($P56/$O56)/$AD56,"")) | AH56: =IF($A56="","",IFERROR($Q56/$P56,"")) | AI56: =IF($A56="","",IFERROR($AF56*$AG56*$AH56,"")) | AJ56: =IF($A56="","",IFERROR($AE56/$F56,"")) | AK56: =IF($A56="","",IFERROR($AD56/$N56,"")) | AL56: =IF($A56="","",IFERROR($H56/$N56,"")) | AM56: =IF($A56="","",IFERROR(($P56-$Q56)/$P56*1000000,"")) | AN56: =IF($A56="","",IFERROR(($Q56+$R56)/$T56,"")) | AO56: =IF($A56="","",IFERROR($V56/$U56,"")) | AP56: =IF($A56="","",IFERROR(MAX(0,$AD56-$P56/$O56),"")) | AQ56: =IF($A56="","",IFERROR(($P56-$Q56)/$O56,"")) | AR56: =IF($A56="","",IF($F56="","Temps d'ouverture manquant",IF($O56="","Cadence produit inconnue",IF($G56>$F56,"Arrêts planifiés > temps d'ouverture",IF($AC56>$AB56,"Arrêts subis > temps requis",IF($P56<>$Q56+$R56+$S56,"Produite ≠ conforme + retouchée + rebutée",IF($Q56>$P56,"Conforme > produite",IF($V56>$U56,"Présents > prévus","OK")))))))) | AS56: =IF($A56="",0,IF(AND(OR(COCKPIT!$H$4="Toutes",$C56=COCKPIT!$H$4),OR(COCKPIT!$K$4="Toutes",$B56=COCKPIT!$K$4)),1,0))
O57: =IF($E57="","",IFERROR(INDEX(PARAMETRES!$O$7:$O$36,MATCH($E57,PARAMETRES!$M$7:$M$36,0)),"")) | AB57: =IF($A57="","",MAX(0,$F57-$G57)) | AC57: =IF($A57="","",SUM($H57:$M57)) | AD57: =IF($A57="","",MAX(0,$AB57-$AC57)) | AE57: =IF($A57="","",IFERROR($Q57/$O57,"")) | AF57: =IF($A57="","",IFERROR($AD57/$AB57,"")) | AG57: =IF($A57="","",IFERROR(($P57/$O57)/$AD57,"")) | AH57: =IF($A57="","",IFERROR($Q57/$P57,"")) | AI57: =IF($A57="","",IFERROR($AF57*$AG57*$AH57,"")) | AJ57: =IF($A57="","",IFERROR($AE57/$F57,"")) | AK57: =IF($A57="","",IFERROR($AD57/$N57,"")) | AL57: =IF($A57="","",IFERROR($H57/$N57,"")) | AM57: =IF($A57="","",IFERROR(($P57-$Q57)/$P57*1000000,"")) | AN57: =IF($A57="","",IFERROR(($Q57+$R57)/$T57,"")) | AO57: =IF($A57="","",IFERROR($V57/$U57,"")) | AP57: =IF($A57="","",IFERROR(MAX(0,$AD57-$P57/$O57),"")) | AQ57: =IF($A57="","",IFERROR(($P57-$Q57)/$O57,"")) | AR57: =IF($A57="","",IF($F57="","Temps d'ouverture manquant",IF($O57="","Cadence produit inconnue",IF($G57>$F57,"Arrêts planifiés > temps d'ouverture",IF($AC57>$AB57,"Arrêts subis > temps requis",IF($P57<>$Q57+$R57+$S57,"Produite ≠ conforme + retouchée + rebutée",IF($Q57>$P57,"Conforme > produite",IF($V57>$U57,"Présents > prévus","OK")))))))) | AS57: =IF($A57="",0,IF(AND(OR(COCKPIT!$H$4="Toutes",$C57=COCKPIT!$H$4),OR(COCKPIT!$K$4="Toutes",$B57=COCKPIT!$K$4)),1,0))
O58: =IF($E58="","",IFERROR(INDEX(PARAMETRES!$O$7:$O$36,MATCH($E58,PARAMETRES!$M$7:$M$36,0)),"")) | AB58: =IF($A58="","",MAX(0,$F58-$G58)) | AC58: =IF($A58="","",SUM($H58:$M58)) | AD58: =IF($A58="","",MAX(0,$AB58-$AC58)) | AE58: =IF($A58="","",IFERROR($Q58/$O58,"")) | AF58: =IF($A58="","",IFERROR($AD58/$AB58,"")) | AG58: =IF($A58="","",IFERROR(($P58/$O58)/$AD58,"")) | AH58: =IF($A58="","",IFERROR($Q58/$P58,"")) | AI58: =IF($A58="","",IFERROR($AF58*$AG58*$AH58,"")) | AJ58: =IF($A58="","",IFERROR($AE58/$F58,"")) | AK58: =IF($A58="","",IFERROR($AD58/$N58,"")) | AL58: =IF($A58="","",IFERROR($H58/$N58,"")) | AM58: =IF($A58="","",IFERROR(($P58-$Q58)/$P58*1000000,"")) | AN58: =IF($A58="","",IFERROR(($Q58+$R58)/$T58,"")) | AO58: =IF($A58="","",IFERROR($V58/$U58,"")) | AP58: =IF($A58="","",IFERROR(MAX(0,$AD58-$P58/$O58),"")) | AQ58: =IF($A58="","",IFERROR(($P58-$Q58)/$O58,"")) | AR58: =IF($A58="","",IF($F58="","Temps d'ouverture manquant",IF($O58="","Cadence produit inconnue",IF($G58>$F58,"Arrêts planifiés > temps d'ouverture",IF($AC58>$AB58,"Arrêts subis > temps requis",IF($P58<>$Q58+$R58+$S58,"Produite ≠ conforme + retouchée + rebutée",IF($Q58>$P58,"Conforme > produite",IF($V58>$U58,"Présents > prévus","OK")))))))) | AS58: =IF($A58="",0,IF(AND(OR(COCKPIT!$H$4="Toutes",$C58=COCKPIT!$H$4),OR(COCKPIT!$K$4="Toutes",$B58=COCKPIT!$K$4)),1,0))
... O204: =IF($E204="","",IFERROR(INDEX(PARAMETRES!$O$7:$O$36,MATCH($E204,PARAMETRES!$M$7:$M$36,0)),"")) | AB204: =IF($A204="","",MAX(0,$F204-$G204)) | AC204: =IF($A204="","",SUM($H204:$M204)) | AD204: =IF($A204="","",MAX(0,$AB204-$AC204)) | AE204: =IF($A204="","",IFERROR($Q204/$O204,"")) | AF204: =IF($A204="","",IFERROR($AD204/$AB204,"")) | AG204: =IF($A204="","",IFERROR(($P204/$O204)/$AD204,"")) | AH204: =IF($A204="","",IFERROR($Q204/$P204,"")) | AI204: =IF($A204="","",IFERROR($AF204*$AG204*$AH204,"")) | AJ204: =IF($A204="","",IFERROR($AE204/$F204,"")) | AK204: =IF($A204="","",IFERROR($AD204/$N204,"")) | AL204: =IF($A204="","",IFERROR($H204/$N204,"")) | AM204: =IF($A204="","",IFERROR(($P204-$Q204)/$P204*1000000,"")) | AN204: =IF($A204="","",IFERROR(($Q204+$R204)/$T204,"")) | AO204: =IF($A204="","",IFERROR($V204/$U204,"")) | AP204: =IF($A204="","",IFERROR(MAX(0,$AD204-$P204/$O204),"")) | AQ204: =IF($A204="","",IFERROR(($P204-$Q204)/$O204,"")) | AR204: =IF($A204="","",IF($F204="","Temps d'ouverture manquant",IF($O204="","Cadence produit inconnue",IF($G204>$F204,"Arrêts planifiés > temps d'ouverture",IF($AC204>$AB204,"Arrêts subis > temps requis",IF($P204<>$Q204+$R204+$S204,"Produite ≠ conforme + retouchée + rebutée",IF($Q204>$P204,"Conforme > produite",IF($V204>$U204,"Présents > prévus","OK")))))))) | AS204: =IF($A204="",0,IF(AND(OR(COCKPIT!$H$4="Toutes",$C204=COCKPIT!$H$4),OR(COCKPIT!$K$4="Toutes",$B204=COCKPIT!$K$4)),1,0))

Sheet ARRETS
A1: JOURNAL DES ARRÊTS — niveau événementiel
A2: Un enregistrement par arrêt. Ce niveau de détail alimente l'analyse de Pareto par cause et par famille 5M. Les colonnes bleues sont renseignées automatiquement à partir du code cause.
A4: Date | B4: Équipe | C4: Ligne / ressource | D4: Machine / poste | E4: Heure de début | F4: Heure de fin | G4: Durée (min) | H4: Code cause | I4: Libellé de la cause | J4: Famille 5M | K4: Type | L4: Rubrique de perte | M4: Constat terrain | N4: Action immédiate appliquée | O4: N° d'action liée | P4: Niveau d'alerte | Q4: Filtre cockpit
A5: 46024 | B5: Équipe A (matin) | C5: Ligne 1 - Assemblage | D5: Ligne 1 | E5: 0.29097222 | F5: 0.31875 | G5: =IF(OR($E5="",$F5=""),"",ROUND(($F5-$E5+IF($F5<$E5,1,0))*1440,0)) | H5: PLA-01 | I5: =IF($H5="","",IFERROR(INDEX(PARAMETRES!$S$7:$S$46,MATCH($H5,PARAMETRES!$R$7:$R$46,0)),"Code inconnu")) | J5: =IF($H5="","",IFERROR(INDEX(PARAMETRES!$T$7:$T$46,MATCH($H5,PARAMETRES!$R$7:$R$46,0)),"")) | K5: =IF($H5="","",IFERROR(INDEX(PARAMETRES!$U$7:$U$46,MATCH($H5,PARAMETRES!$R$7:$R$46,0)),"")) | L5: =IF($H5="","",IFERROR(INDEX(PARAMETRES!$V$7:$V$46,MATCH($H5,PARAMETRES!$R$7:$R$46,0)),"")) | P5: =IF($G5="","",IF($G5>=60,"Arrêt majeur — analyse 5 pourquoi",IF($G5>=30,"À analyser en revue quotidienne",IF($K5="Planifié","Arrêt planifié","Aléa courant")))) | Q5: =IF($A5="",0,IF(AND(OR(COCKPIT!$H$4="Toutes",$C5=COCKPIT!$H$4),OR(COCKPIT!$K$4="Toutes",$B5=COCKPIT!$K$4)),1,0))
A6: 46024 | B6: Équipe A (matin) | C6: Ligne 1 - Assemblage | D6: Ligne 1 | E6: 0.33402778 | F6: 0.36805556 | G6: =IF(OR($E6="",$F6=""),"",ROUND(($F6-$E6+IF($F6<$E6,1,0))*1440,0)) | H6: PAN-01 | I6: =IF($H6="","",IFERROR(INDEX(PARAMETRES!$S$7:$S$46,MATCH($H6,PARAMETRES!$R$7:$R$46,0)),"Code inconnu")) | J6: =IF($H6="","",IFERROR(INDEX(PARAMETRES!$T$7:$T$46,MATCH($H6,PARAMETRES!$R$7:$R$46,0)),"")) | K6: =IF($H6="","",IFERROR(INDEX(PARAMETRES!$U$7:$U$46,MATCH($H6,PARAMETRES!$R$7:$R$46,0)),"")) | L6: =IF($H6="","",IFERROR(INDEX(PARAMETRES!$V$7:$V$46,MATCH($H6,PARAMETRES!$R$7:$R$46,0)),"")) | P6: =IF($G6="","",IF($G6>=60,"Arrêt majeur — analyse 5 pourquoi",IF($G6>=30,"À analyser en revue quotidienne",IF($K6="Planifié","Arrêt planifié","Aléa courant")))) | Q6: =IF($A6="",0,IF(AND(OR(COCKPIT!$H$4="Toutes",$C6=COCKPIT!$H$4),OR(COCKPIT!$K$4="Toutes",$B6=COCKPIT!$K$4)),1,0))
A7: 46024 | B7: Équipe A (matin) | C7: Ligne 1 - Assemblage | D7: Ligne 1 | E7: 0.39513889 | F7: 0.41736111 | G7: =IF(OR($E7="",$F7=""),"",ROUND(($F7-$E7+IF($F7<$E7,1,0))*1440,0)) | H7: CDS-01 | I7: =IF($H7="","",IFERROR(INDEX(PARAMETRES!$S$7:$S$46,MATCH($H7,PARAMETRES!$R$7:$R$46,0)),"Code inconnu")) | J7: =IF($H7="","",IFERROR(INDEX(PARAMETRES!$T$7:$T$46,MATCH($H7,PARAMETRES!$R$7:$R$46,0)),"")) | K7: =IF($H7="","",IFERROR(INDEX(PARAMETRES!$U$7:$U$46,MATCH($H7,PARAMETRES!$R$7:$R$46,0)),"")) | L7: =IF($H7="","",IFERROR(INDEX(PARAMETRES!$V$7:$V$46,MATCH($H7,PARAMETRES!$R$7:$R$46,0)),"")) | P7: =IF($G7="","",IF($G7>=60,"Arrêt majeur — analyse 5 pourquoi",IF($G7>=30,"À analyser en revue quotidienne",IF($K7="Planifié","Arrêt planifié","Aléa courant")))) | Q7: =IF($A7="",0,IF(AND(OR(COCKPIT!$H$4="Toutes",$C7=COCKPIT!$H$4),OR(COCKPIT!$K$4="Toutes",$B7=COCKPIT!$K$4)),1,0))
A8: 46024 | B8: Équipe B (après-midi) | C8: Ligne 2 - Usinage | D8: Ligne 2 | E8: 0.28333333 | F8: 0.31111111 | G8: =IF(OR($E8="",$F8=""),"",ROUND(($F8-$E8+IF($F8<$E8,1,0))*1440,0)) | H8: PLA-01 | I8: =IF($H8="","",IFERROR(INDEX(PARAMETRES!$S$7:$S$46,MATCH($H8,PARAMETRES!$R$7:$R$46,0)),"Code inconnu")) | J8: =IF($H8="","",IFERROR(INDEX(PARAMETRES!$T$7:$T$46,MATCH($H8,PARAMETRES!$R$7:$R$46,0)),"")) | K8: =IF($H8="","",IFERROR(INDEX(PARAMETRES!$U$7:$U$46,MATCH($H8,PARAMETRES!$R$7:$R$46,0)),"")) | L8: =IF($H8="","",IFERROR(INDEX(PARAMETRES!$V$7:$V$46,MATCH($H8,PARAMETRES!$R$7:$R$46,0)),"")) | P8: =IF($G8="","",IF($G8>=60,"Arrêt majeur — analyse 5 pourquoi",IF($G8>=30,"À analyser en revue quotidienne",IF($K8="Planifié","Arrêt planifié","Aléa courant")))) | Q8: =IF($A8="",0,IF(AND(OR(COCKPIT!$H$4="Toutes",$C8=COCKPIT!$H$4),OR(COCKPIT!$K$4="Toutes",$B8=COCKPIT!$K$4)),1,0))
A9: 46024 | B9: Équipe B (après-midi) | C9: Ligne 2 - Usinage | D9: Ligne 2 | E9: 0.34166667 | F9: 0.35138889 | G9: =IF(OR($E9="",$F9=""),"",ROUND(($F9-$E9+IF($F9<$E9,1,0))*1440,0)) | H9: REG-01 | I9: =IF($H9="","",IFERROR(INDEX(PARAMETRES!$S$7:$S$46,MATCH($H9,PARAMETRES!$R$7:$R$46,0)),"Code inconnu")) | J9: =IF($H9="","",IFERROR(INDEX(PARAMETRES!$T$7:$T$46,MATCH($H9,PARAMETRES!$R$7:$R$46,0)),"")) | K9: =IF($H9="","",IFERROR(INDEX(PARAMETRES!$U$7:$U$46,MATCH($H9,PARAMETRES!$R$7:$R$46,0)),"")) | L9: =IF($H9="","",IFERROR(INDEX(PARAMETRES!$V$7:$V$46,MATCH($H9,PARAMETRES!$R$7:$R$46,0)),"")) | P9: =IF($G9="","",IF($G9>=60,"Arrêt majeur — analyse 5 pourquoi",IF($G9>=30,"À analyser en revue quotidienne",IF($K9="Planifié","Arrêt planifié","Aléa courant")))) | Q9: =IF($A9="",0,IF(AND(OR(COCKPIT!$H$4="Toutes",$C9=COCKPIT!$H$4),OR(COCKPIT!$K$4="Toutes",$B9=COCKPIT!$K$4)),1,0))
A10: 46024 | B10: Équipe B (après-midi) | C10: Ligne 2 - Usinage | D10: Ligne 2 | E10: 0.36597222 | F10: 0.37291667 | G10: =IF(OR($E10="",$F10=""),"",ROUND(($F10-$E10+IF($F10<$E10,1,0))*1440,0)) | H10: MAT-02 | I10: =IF($H10="","",IFERROR(INDEX(PARAMETRES!$S$7:$S$46,MATCH($H10,PARAMETRES!$R$7:$R$46,0)),"Code inconnu")) | J10: =IF($H10="","",IFERROR(INDEX(PARAMETRES!$T$7:$T$46,MATCH($H10,PARAMETRES!$R$7:$R$46,0)),"")) | K10: =IF($H10="","",IFERROR(INDEX(PARAMETRES!$U$7:$U$46,MATCH($H10,PARAMETRES!$R$7:$R$46,0)),"")) | L10: =IF($H10="","",IFERROR(INDEX(PARAMETRES!$V$7:$V$46,MATCH($H10,PARAMETRES!$R$7:$R$46,0)),"")) | P10: =IF($G10="","",IF($G10>=60,"Arrêt majeur — analyse 5 pourquoi",IF($G10>=30,"À analyser en revue quotidienne",IF($K10="Planifié","Arrêt planifié","Aléa courant")))) | Q10: =IF($A10="",0,IF(AND(OR(COCKPIT!$H$4="Toutes",$C10=COCKPIT!$H$4),OR(COCKPIT!$K$4="Toutes",$B10=COCKPIT!$K$4)),1,0))
A11: 46024 | B11: Équipe B (après-midi) | C11: Ligne 2 - Usinage | D11: Ligne 2 | E11: 0.38263889 | F11: 0.39444444 | G11: =IF(OR($E11="",$F11=""),"",ROUND(($F11-$E11+IF($F11<$E11,1,0))*1440,0)) | H11: LOG-01 | I11: =IF($H11="","",IFERROR(INDEX(PARAMETRES!$S$7:$S$46,MATCH($H11,PARAMETRES!$R$7:$R$46,0)),"Code inconnu")) | J11: =IF($H11="","",IFERROR(INDEX(PARAMETRES!$T$7:$T$46,MATCH($H11,PARAMETRES!$R$7:$R$46,0)),"")) | K11: =IF($H11="","",IFERROR(INDEX(PARAMETRES!$U$7:$U$46,MATCH($H11,PARAMETRES!$R$7:$R$46,0)),"")) | L11: =IF($H11="","",IFERROR(INDEX(PARAMETRES!$V$7:$V$46,MATCH($H11,PARAMETRES!$R$7:$R$46,0)),"")) | P11: =IF($G11="","",IF($G11>=60,"Arrêt majeur — analyse 5 pourquoi",IF($G11>=30,"À analyser en revue quotidienne",IF($K11="Planifié","Arrêt planifié","Aléa courant")))) | Q11: =IF($A11="",0,IF(AND(OR(COCKPIT!$H$4="Toutes",$C11=COCKPIT!$H$4),OR(COCKPIT!$K$4="Toutes",$B11=COCKPIT!$K$4)),1,0))
A12: 46027 | B12: Équipe B (après-midi) | C12: Ligne 1 - Assemblage | D12: Ligne 1 | E12: 0.27777778 | F12: 0.30555556 | G12: =IF(OR($E12="",$F12=""),"",ROUND(($F12-$E12+IF($F12<$E12,1,0))*1440,0)) | H12: PLA-01 | I12: =IF($H12="","",IFERROR(INDEX(PARAMETRES!$S$7:$S$46,MATCH($H12,PARAMETRES!$R$7:$R$46,0)),"Code inconnu")) | J12: =IF($H12="","",IFERROR(INDEX(PARAMETRES!$T$7:$T$46,MATCH($H12,PARAMETRES!$R$7:$R$46,0)),"")) | K12: =IF($H12="","",IFERROR(INDEX(PARAMETRES!$U$7:$U$46,MATCH($H12,PARAMETRES!$R$7:$R$46,0)),"")) | L12: =IF($H12="","",IFERROR(INDEX(PARAMETRES!$V$7:$V$46,MATCH($H12,PARAMETRES!$R$7:$R$46,0)),"")) | P12: =IF($G12="","",IF($G12>=60,"Arrêt majeur — analyse 5 pourquoi",IF($G12>=30,"À analyser en revue quotidienne",IF($K12="Planifié","Arrêt planifié","Aléa courant")))) | Q12: =IF($A12="",0,IF(AND(OR(COCKPIT!$H$4="Toutes",$C12=COCKPIT!$H$4),OR(COCKPIT!$K$4="Toutes",$B12=COCKPIT!$K$4)),1,0))
A13: 46027 | B13: Équipe B (après-midi) | C13: Ligne 1 - Assemblage | D13: Ligne 1 | E13: 0.31388889 | F13: 0.32708333 | G13: =IF(OR($E13="",$F13=""),"",ROUND(($F13-$E13+IF($F13<$E13,1,0))*1440,0)) | H13: MAT-01 | I13: =IF($H13="","",IFERROR(INDEX(PARAMETRES!$S$7:$S$46,MATCH($H13,PARAMETRES!$R$7:$R$46,0)),"Code inconnu")) | J13: =IF($H13="","",IFERROR(INDEX(PARAMETRES!$T$7:$T$46,MATCH($H13,PARAMETRES!$R$7:$R$46,0)),"")) | K13: =IF($H13="","",IFERROR(INDEX(PARAMETRES!$U$7:$U$46,MATCH($H13,PARAMETRES!$R$7:$R$46,0)),"")) | L13: =IF($H13="","",IFERROR(INDEX(PARAMETRES!$V$7:$V$46,MATCH($H13,PARAMETRES!$R$7:$R$46,0)),"")) | P13: =IF($G13="","",IF($G13>=60,"Arrêt majeur — analyse 5 pourquoi",IF($G13>=30,"À analyser en revue quotidienne",IF($K13="Planifié","Arrêt planifié","Aléa courant")))) | Q13: =IF($A13="",0,IF(AND(OR(COCKPIT!$H$4="Toutes",$C13=COCKPIT!$H$4),OR(COCKPIT!$K$4="Toutes",$B13=COCKPIT!$K$4)),1,0))
A14: 46027 | B14: Équipe B (après-midi) | C14: Ligne 1 - Assemblage | D14: Ligne 1 | E14: 0.35416667 | F14: 0.37430556 | G14: =IF(OR($E14="",$F14=""),"",ROUND(($F14-$E14+IF($F14<$E14,1,0))*1440,0)) | H14: PER-02 | I14: =IF($H14="","",IFERROR(INDEX(PARAMETRES!$S$7:$S$46,MATCH($H14,PARAMETRES!$R$7:$R$46,0)),"Code inconnu")) | J14: =IF($H14="","",IFERROR(INDEX(PARAMETRES!$T$7:$T$46,MATCH($H14,PARAMETRES!$R$7:$R$46,0)),"")) | K14: =IF($H14="","",IFERROR(INDEX(PARAMETRES!$U$7:$U$46,MATCH($H14,PARAMETRES!$R$7:$R$46,0)),"")) | L14: =IF($H14="","",IFERROR(INDEX(PARAMETRES!$V$7:$V$46,MATCH($H14,PARAMETRES!$R$7:$R$46,0)),"")) | P14: =IF($G14="","",IF($G14>=60,"Arrêt majeur — analyse 5 pourquoi",IF($G14>=30,"À analyser en revue quotidienne",IF($K14="Planifié","Arrêt planifié","Aléa courant")))) | Q14: =IF($A14="",0,IF(AND(OR(COCKPIT!$H$4="Toutes",$C14=COCKPIT!$H$4),OR(COCKPIT!$K$4="Toutes",$B14=COCKPIT!$K$4)),1,0))
A15: 46027 | B15: Équipe B (après-midi) | C15: Ligne 1 - Assemblage | D15: Ligne 1 | E15: 0.39027778 | F15: 0.40069444 | G15: =IF(OR($E15="",$F15=""),"",ROUND(($F15-$E15+IF($F15<$E15,1,0))*1440,0)) | H15: ESS-01 | I15: =IF($H15="","",IFERROR(INDEX(PARAMETRES!$S$7:$S$46,MATCH($H15,PARAMETRES!$R$7:$R$46,0)),"Code inconnu")) | J15: =IF($H15="","",IFERROR(INDEX(PARAMETRES!$T$7:$T$46,MATCH($H15,PARAMETRES!$R$7:$R$46,0)),"")) | K15: =IF($H15="","",IFERROR(INDEX(PARAMETRES!$U$7:$U$46,MATCH($H15,PARAMETRES!$R$7:$R$46,0)),"")) | L15: =IF($H15="","",IFERROR(INDEX(PARAMETRES!$V$7:$V$46,MATCH($H15,PARAMETRES!$R$7:$R$46,0)),"")) | P15: =IF($G15="","",IF($G15>=60,"Arrêt majeur — analyse 5 pourquoi",IF($G15>=30,"À analyser en revue quotidienne",IF($K15="Planifié","Arrêt planifié","Aléa courant")))) | Q15: =IF($A15="",0,IF(AND(OR(COCKPIT!$H$4="Toutes",$C15=COCKPIT!$H$4),OR(COCKPIT!$K$4="Toutes",$B15=COCKPIT!$K$4)),1,0))
A16: 46027 | B16: Équipe B (après-midi) | C16: Ligne 1 - Assemblage | D16: Ligne 1 | E16: 0.42708333 | F16: 0.46388889 | G16: =IF(OR($E16="",$F16=""),"",ROUND(($F16-$E16+IF($F16<$E16,1,0))*1440,0)) | H16: PAN-03 | I16: =IF($H16="","",IFERROR(INDEX(PARAMETRES!$S$7:$S$46,MATCH($H16,PARAMETRES!$R$7:$R$46,0)),"Code inconnu")) | J16: =IF($H16="","",IFERROR(INDEX(PARAMETRES!$T$7:$T$46,MATCH($H16,PARAMETRES!$R$7:$R$46,0)),"")) | K16: =IF($H16="","",IFERROR(INDEX(PARAMETRES!$U$7:$U$46,MATCH($H16,PARAMETRES!$R$7:$R$46,0)),"")) | L16: =IF($H16="","",IFERROR(INDEX(PARAMETRES!$V$7:$V$46,MATCH($H16,PARAMETRES!$R$7:$R$46,0)),"")) | P16: =IF($G16="","",IF($G16>=60,"Arrêt majeur — analyse 5 pourquoi",IF($G16>=30,"À analyser en revue quotidienne",IF($K16="Planifié","Arrêt planifié","Aléa courant")))) | Q16: =IF($A16="",0,IF(AND(OR(COCKPIT!$H$4="Toutes",$C16=COCKPIT!$H$4),OR(COCKPIT!$K$4="Toutes",$B16=COCKPIT!$K$4)),1,0))
... A203: 46052 | B203: Équipe B (après-midi) | C203: Ligne 2 - Usinage | D203: Ligne 2 | E203: 0.36736111 | F203: 0.375 | G203: =IF(OR($E203="",$F203=""),"",ROUND(($F203-$E203+IF($F203<$E203,1,0))*1440,0)) | H203: LOG-01 | I203: =IF($H203="","",IFERROR(INDEX(PARAMETRES!$S$7:$S$46,MATCH($H203,PARAMETRES!$R$7:$R$46,0)),"Code inconnu")) | J203: =IF($H203="","",IFERROR(INDEX(PARAMETRES!$T$7:$T$46,MATCH($H203,PARAMETRES!$R$7:$R$46,0)),"")) | K203: =IF($H203="","",IFERROR(INDEX(PARAMETRES!$U$7:$U$46,MATCH($H203,PARAMETRES!$R$7:$R$46,0)),"")) | L203: =IF($H203="","",IFERROR(INDEX(PARAMETRES!$V$7:$V$46,MATCH($H203,PARAMETRES!$R$7:$R$46,0)),"")) | P203: =IF($G203="","",IF($G203>=60,"Arrêt majeur — analyse 5 pourquoi",IF($G203>=30,"À analyser en revue quotidienne",IF($K203="Planifié","Arrêt planifié","Aléa courant")))) | Q203: =IF($A203="",0,IF(AND(OR(COCKPIT!$H$4="Toutes",$C203=COCKPIT!$H$4),OR(COCKPIT!$K$4="Toutes",$B203=COCKPIT!$K$4)),1,0))
G204: =IF(OR($E204="",$F204=""),"",ROUND(($F204-$E204+IF($F204<$E204,1,0))*1440,0)) | I204: =IF($H204="","",IFERROR(INDEX(PARAMETRES!$S$7:$S$46,MATCH($H204,PARAMETRES!$R$7:$R$46,0)),"Code inconnu")) | J204: =IF($H204="","",IFERROR(INDEX(PARAMETRES!$T$7:$T$46,MATCH($H204,PARAMETRES!$R$7:$R$46,0)),"")) | K204: =IF($H204="","",IFERROR(INDEX(PARAMETRES!$U$7:$U$46,MATCH($H204,PARAMETRES!$R$7:$R$46,0)),"")) | L204: =IF($H204="","",IFERROR(INDEX(PARAMETRES!$V$7:$V$46,MATCH($H204,PARAMETRES!$R$7:$R$46,0)),"")) | P204: =IF($G204="","",IF($G204>=60,"Arrêt majeur — analyse 5 pourquoi",IF($G204>=30,"À analyser en revue quotidienne",IF($K204="Planifié","Arrêt planifié","Aléa courant")))) | Q204: =IF($A204="",0,IF(AND(OR(COCKPIT!$H$4="Toutes",$C204=COCKPIT!$H$4),OR(COCKPIT!$K$4="Toutes",$B204=COCKPIT!$K$4)),1,0))
G205: =IF(OR($E205="",$F205=""),"",ROUND(($F205-$E205+IF($F205<$E205,1,0))*1440,0)) | I205: =IF($H205="","",IFERROR(INDEX(PARAMETRES!$S$7:$S$46,MATCH($H205,PARAMETRES!$R$7:$R$46,0)),"Code inconnu")) | J205: =IF($H205="","",IFERROR(INDEX(PARAMETRES!$T$7:$T$46,MATCH($H205,PARAMETRES!$R$7:$R$46,0)),"")) | K205: =IF($H205="","",IFERROR(INDEX(PARAMETRES!$U$7:$U$46,MATCH($H205,PARAMETRES!$R$7:$R$46,0)),"")) | L205: =IF($H205="","",IFERROR(INDEX(PARAMETRES!$V$7:$V$46,MATCH($H205,PARAMETRES!$R$7:$R$46,0)),"")) | P205: =IF($G205="","",IF($G205>=60,"Arrêt majeur — analyse 5 pourquoi",IF($G205>=30,"À analyser en revue quotidienne",IF($K205="Planifié","Arrêt planifié","Aléa courant")))) | Q205: =IF($A205="",0,IF(AND(OR(COCKPIT!$H$4="Toutes",$C205=COCKPIT!$H$4),OR(COCKPIT!$K$4="Toutes",$B205=COCKPIT!$K$4)),1,0))
G206: =IF(OR($E206="",$F206=""),"",ROUND(($F206-$E206+IF($F206<$E206,1,0))*1440,0)) | I206: =IF($H206="","",IFERROR(INDEX(PARAMETRES!$S$7:$S$46,MATCH($H206,PARAMETRES!$R$7:$R$46,0)),"Code inconnu")) | J206: =IF($H206="","",IFERROR(INDEX(PARAMETRES!$T$7:$T$46,MATCH($H206,PARAMETRES!$R$7:$R$46,0)),"")) | K206: =IF($H206="","",IFERROR(INDEX(PARAMETRES!$U$7:$U$46,MATCH($H206,PARAMETRES!$R$7:$R$46,0)),"")) | L206: =IF($H206="","",IFERROR(INDEX(PARAMETRES!$V$7:$V$46,MATCH($H206,PARAMETRES!$R$7:$R$46,0)),"")) | P206: =IF($G206="","",IF($G206>=60,"Arrêt majeur — analyse 5 pourquoi",IF($G206>=30,"À analyser en revue quotidienne",IF($K206="Planifié","Arrêt planifié","Aléa courant")))) | Q206: =IF($A206="",0,IF(AND(OR(COCKPIT!$H$4="Toutes",$C206=COCKPIT!$H$4),OR(COCKPIT!$K$4="Toutes",$B206=COCKPIT!$K$4)),1,0))
G207: =IF(OR($E207="",$F207=""),"",ROUND(($F207-$E207+IF($F207<$E207,1,0))*1440,0)) | I207: =IF($H207="","",IFERROR(INDEX(PARAMETRES!$S$7:$S$46,MATCH($H207,PARAMETRES!$R$7:$R$46,0)),"Code inconnu")) | J207: =IF($H207="","",IFERROR(INDEX(PARAMETRES!$T$7:$T$46,MATCH($H207,PARAMETRES!$R$7:$R$46,0)),"")) | K207: =IF($H207="","",IFERROR(INDEX(PARAMETRES!$U$7:$U$46,MATCH($H207,PARAMETRES!$R$7:$R$46,0)),"")) | L207: =IF($H207="","",IFERROR(INDEX(PARAMETRES!$V$7:$V$46,MATCH($H207,PARAMETRES!$R$7:$R$46,0)),"")) | P207: =IF($G207="","",IF($G207>=60,"Arrêt majeur — analyse 5 pourquoi",IF($G207>=30,"À analyser en revue quotidienne",IF($K207="Planifié","Arrêt planifié","Aléa courant")))) | Q207: =IF($A207="",0,IF(AND(OR(COCKPIT!$H$4="Toutes",$C207=COCKPIT!$H$4),OR(COCKPIT!$K$4="Toutes",$B207=COCKPIT!$K$4)),1,0))
G208: =IF(OR($E208="",$F208=""),"",ROUND(($F208-$E208+IF($F208<$E208,1,0))*1440,0)) | I208: =IF($H208="","",IFERROR(INDEX(PARAMETRES!$S$7:$S$46,MATCH($H208,PARAMETRES!$R$7:$R$46,0)),"Code inconnu")) | J208: =IF($H208="","",IFERROR(INDEX(PARAMETRES!$T$7:$T$46,MATCH($H208,PARAMETRES!$R$7:$R$46,0)),"")) | K208: =IF($H208="","",IFERROR(INDEX(PARAMETRES!$U$7:$U$46,MATCH($H208,PARAMETRES!$R$7:$R$46,0)),"")) | L208: =IF($H208="","",IFERROR(INDEX(PARAMETRES!$V$7:$V$46,MATCH($H208,PARAMETRES!$R$7:$R$46,0)),"")) | P208: =IF($G208="","",IF($G208>=60,"Arrêt majeur — analyse 5 pourquoi",IF($G208>=30,"À analyser en revue quotidienne",IF($K208="Planifié","Arrêt planifié","Aléa courant")))) | Q208: =IF($A208="",0,IF(AND(OR(COCKPIT!$H$4="Toutes",$C208=COCKPIT!$H$4),OR(COCKPIT!$K$4="Toutes",$B208=COCKPIT!$K$4)),1,0))
G209: =IF(OR($E209="",$F209=""),"",ROUND(($F209-$E209+IF($F209<$E209,1,0))*1440,0)) | I209: =IF($H209="","",IFERROR(INDEX(PARAMETRES!$S$7:$S$46,MATCH($H209,PARAMETRES!$R$7:$R$46,0)),"Code inconnu")) | J209: =IF($H209="","",IFERROR(INDEX(PARAMETRES!$T$7:$T$46,MATCH($H209,PARAMETRES!$R$7:$R$46,0)),"")) | K209: =IF($H209="","",IFERROR(INDEX(PARAMETRES!$U$7:$U$46,MATCH($H209,PARAMETRES!$R$7:$R$46,0)),"")) | L209: =IF($H209="","",IFERROR(INDEX(PARAMETRES!$V$7:$V$46,MATCH($H209,PARAMETRES!$R$7:$R$46,0)),"")) | P209: =IF($G209="","",IF($G209>=60,"Arrêt majeur — analyse 5 pourquoi",IF($G209>=30,"À analyser en revue quotidienne",IF($K209="Planifié","Arrêt planifié","Aléa courant")))) | Q209: =IF($A209="",0,IF(AND(OR(COCKPIT!$H$4="Toutes",$C209=COCKPIT!$H$4),OR(COCKPIT!$K$4="Toutes",$B209=COCKPIT!$K$4)),1,0))
G210: =IF(OR($E210="",$F210=""),"",ROUND(($F210-$E210+IF($F210<$E210,1,0))*1440,0)) | I210: =IF($H210="","",IFERROR(INDEX(PARAMETRES!$S$7:$S$46,MATCH($H210,PARAMETRES!$R$7:$R$46,0)),"Code inconnu")) | J210: =IF($H210="","",IFERROR(INDEX(PARAMETRES!$T$7:$T$46,MATCH($H210,PARAMETRES!$R$7:$R$46,0)),"")) | K210: =IF($H210="","",IFERROR(INDEX(PARAMETRES!$U$7:$U$46,MATCH($H210,PARAMETRES!$R$7:$R$46,0)),"")) | L210: =IF($H210="","",IFERROR(INDEX(PARAMETRES!$V$7:$V$46,MATCH($H210,PARAMETRES!$R$7:$R$46,0)),"")) | P210: =IF($G210="","",IF($G210>=60,"Arrêt majeur — analyse 5 pourquoi",IF($G210>=30,"À analyser en revue quotidienne",IF($K210="Planifié","Arrêt planifié","Aléa courant")))) | Q210: =IF($A210="",0,IF(AND(OR(COCKPIT!$H$4="Toutes",$C210=COCKPIT!$H$4),OR(COCKPIT!$K$4="Toutes",$B210=COCKPIT!$K$4)),1,0))
G211: =IF(OR($E211="",$F211=""),"",ROUND(($F211-$E211+IF($F211<$E211,1,0))*1440,0)) | I211: =IF($H211="","",IFERROR(INDEX(PARAMETRES!$S$7:$S$46,MATCH($H211,PARAMETRES!$R$7:$R$46,0)),"Code inconnu")) | J211: =IF($H211="","",IFERROR(INDEX(PARAMETRES!$T$7:$T$46,MATCH($H211,PARAMETRES!$R$7:$R$46,0)),"")) | K211: =IF($H211="","",IFERROR(INDEX(PARAMETRES!$U$7:$U$46,MATCH($H211,PARAMETRES!$R$7:$R$46,0)),"")) | L211: =IF($H211="","",IFERROR(INDEX(PARAMETRES!$V$7:$V$46,MATCH($H211,PARAMETRES!$R$7:$R$46,0)),"")) | P211: =IF($G211="","",IF($G211>=60,"Arrêt majeur — analyse 5 pourquoi",IF($G211>=30,"À analyser en revue quotidienne",IF($K211="Planifié","Arrêt planifié","Aléa courant")))) | Q211: =IF($A211="",0,IF(AND(OR(COCKPIT!$H$4="Toutes",$C211=COCKPIT!$H$4),OR(COCKPIT!$K$4="Toutes",$B211=COCKPIT!$K$4)),1,0))
G212: =IF(OR($E212="",$F212=""),"",ROUND(($F212-$E212+IF($F212<$E212,1,0))*1440,0)) | I212: =IF($H212="","",IFERROR(INDEX(PARAMETRES!$S$7:$S$46,MATCH($H212,PARAMETRES!$R$7:$R$46,0)),"Code inconnu")) | J212: =IF($H212="","",IFERROR(INDEX(PARAMETRES!$T$7:$T$46,MATCH($H212,PARAMETRES!$R$7:$R$46,0)),"")) | K212: =IF($H212="","",IFERROR(INDEX(PARAMETRES!$U$7:$U$46,MATCH($H212,PARAMETRES!$R$7:$R$46,0)),"")) | L212: =IF($H212="","",IFERROR(INDEX(PARAMETRES!$V$7:$V$46,MATCH($H212,PARAMETRES!$R$7:$R$46,0)),"")) | P212: =IF($G212="","",IF($G212>=60,"Arrêt majeur — analyse 5 pourquoi",IF($G212>=30,"À analyser en revue quotidienne",IF($K212="Planifié","Arrêt planifié","Aléa courant")))) | Q212: =IF($A212="",0,IF(AND(OR(COCKPIT!$H$4="Toutes",$C212=COCKPIT!$H$4),OR(COCKPIT!$K$4="Toutes",$B212=COCKPIT!$K$4)),1,0))
G213: =IF(OR($E213="",$F213=""),"",ROUND(($F213-$E213+IF($F213<$E213,1,0))*1440,0)) | I213: =IF($H213="","",IFERROR(INDEX(PARAMETRES!$S$7:$S$46,MATCH($H213,PARAMETRES!$R$7:$R$46,0)),"Code inconnu")) | J213: =IF($H213="","",IFERROR(INDEX(PARAMETRES!$T$7:$T$46,MATCH($H213,PARAMETRES!$R$7:$R$46,0)),"")) | K213: =IF($H213="","",IFERROR(INDEX(PARAMETRES!$U$7:$U$46,MATCH($H213,PARAMETRES!$R$7:$R$46,0)),"")) | L213: =IF($H213="","",IFERROR(INDEX(PARAMETRES!$V$7:$V$46,MATCH($H213,PARAMETRES!$R$7:$R$46,0)),"")) | P213: =IF($G213="","",IF($G213>=60,"Arrêt majeur — analyse 5 pourquoi",IF($G213>=30,"À analyser en revue quotidienne",IF($K213="Planifié","Arrêt planifié","Aléa courant")))) | Q213: =IF($A213="",0,IF(AND(OR(COCKPIT!$H$4="Toutes",$C213=COCKPIT!$H$4),OR(COCKPIT!$K$4="Toutes",$B213=COCKPIT!$K$4)),1,0))
G214: =IF(OR($E214="",$F214=""),"",ROUND(($F214-$E214+IF($F214<$E214,1,0))*1440,0)) | I214: =IF($H214="","",IFERROR(INDEX(PARAMETRES!$S$7:$S$46,MATCH($H214,PARAMETRES!$R$7:$R$46,0)),"Code inconnu")) | J214: =IF($H214="","",IFERROR(INDEX(PARAMETRES!$T$7:$T$46,MATCH($H214,PARAMETRES!$R$7:$R$46,0)),"")) | K214: =IF($H214="","",IFERROR(INDEX(PARAMETRES!$U$7:$U$46,MATCH($H214,PARAMETRES!$R$7:$R$46,0)),"")) | L214: =IF($H214="","",IFERROR(INDEX(PARAMETRES!$V$7:$V$46,MATCH($H214,PARAMETRES!$R$7:$R$46,0)),"")) | P214: =IF($G214="","",IF($G214>=60,"Arrêt majeur — analyse 5 pourquoi",IF($G214>=30,"À analyser en revue quotidienne",IF($K214="Planifié","Arrêt planifié","Aléa courant")))) | Q214: =IF($A214="",0,IF(AND(OR(COCKPIT!$H$4="Toutes",$C214=COCKPIT!$H$4),OR(COCKPIT!$K$4="Toutes",$B214=COCKPIT!$K$4)),1,0))
G215: =IF(OR($E215="",$F215=""),"",ROUND(($F215-$E215+IF($F215<$E215,1,0))*1440,0)) | I215: =IF($H215="","",IFERROR(INDEX(PARAMETRES!$S$7:$S$46,MATCH($H215,PARAMETRES!$R$7:$R$46,0)),"Code inconnu")) | J215: =IF($H215="","",IFERROR(INDEX(PARAMETRES!$T$7:$T$46,MATCH($H215,PARAMETRES!$R$7:$R$46,0)),"")) | K215: =IF($H215="","",IFERROR(INDEX(PARAMETRES!$U$7:$U$46,MATCH($H215,PARAMETRES!$R$7:$R$46,0)),"")) | L215: =IF($H215="","",IFERROR(INDEX(PARAMETRES!$V$7:$V$46,MATCH($H215,PARAMETRES!$R$7:$R$46,0)),"")) | P215: =IF($G215="","",IF($G215>=60,"Arrêt majeur — analyse 5 pourquoi",IF($G215>=30,"À analyser en revue quotidienne",IF($K215="Planifié","Arrêt planifié","Aléa courant")))) | Q215: =IF($A215="",0,IF(AND(OR(COCKPIT!$H$4="Toutes",$C215=COCKPIT!$H$4),OR(COCKPIT!$K$4="Toutes",$B215=COCKPIT!$K$4)),1,0))
... G404: =IF(OR($E404="",$F404=""),"",ROUND(($F404-$E404+IF($F404<$E404,1,0))*1440,0)) | I404: =IF($H404="","",IFERROR(INDEX(PARAMETRES!$S$7:$S$46,MATCH($H404,PARAMETRES!$R$7:$R$46,0)),"Code inconnu")) | J404: =IF($H404="","",IFERROR(INDEX(PARAMETRES!$T$7:$T$46,MATCH($H404,PARAMETRES!$R$7:$R$46,0)),"")) | K404: =IF($H404="","",IFERROR(INDEX(PARAMETRES!$U$7:$U$46,MATCH($H404,PARAMETRES!$R$7:$R$46,0)),"")) | L404: =IF($H404="","",IFERROR(INDEX(PARAMETRES!$V$7:$V$46,MATCH($H404,PARAMETRES!$R$7:$R$46,0)),"")) | P404: =IF($G404="","",IF($G404>=60,"Arrêt majeur — analyse 5 pourquoi",IF($G404>=30,"À analyser en revue quotidienne",IF($K404="Planifié","Arrêt planifié","Aléa courant")))) | Q404: =IF($A404="",0,IF(AND(OR(COCKPIT!$H$4="Toutes",$C404=COCKPIT!$H$4),OR(COCKPIT!$K$4="Toutes",$B404=COCKPIT!$K$4)),1,0))

Sheet PLAN_ACTIONS
A1: PLAN D'ACTIONS — résolution de problème structurée
A2: Règle d'animation : aucun problème sans fait mesuré, sans cause racine validée, sans pilote nommé et sans date cible. Trois chantiers de fond ouverts au maximum. Criticité IPR = Gravité × Fréquence × Détection (échelle 1 à 5).
A4: SYNTHÈSE DU PLAN D'ACTIONS — calculée automatiquement
A5: Actions ouvertes | D5: Dont en retard | G5: Respect des délais | J5: Délai moyen de traitement | M5: Criticité moyenne (IPR) | P5: Actions critiques (IPR ≥ 30) | S5: Efficacité confirmée | V5: Gains sécurisés (€/an)
A6: =COUNTIF($Q$9:$Q$128,"À lancer")+COUNTIF($Q$9:$Q$128,"En cours")+COUNTIF($Q$9:$Q$128,"En attente") | D6: =SUMPRODUCT(($S$9:$S$128<>"")*($S$9:$S$128>0)*($Q$9:$Q$128<>"Terminée")*($Q$9:$Q$128<>"Abandonnée")) | G6: =IFERROR(COUNTIFS($Q$9:$Q$128,"Terminée",$S$9:$S$128,0)/COUNTIF($Q$9:$Q$128,"Terminée"),"") | J6: =IFERROR(AVERAGE($T$9:$T$128),"") | M6: =IFERROR(AVERAGE($I$9:$I$128),"") | P6: =COUNTIF($I$9:$I$128,">=30") | S6: =IFERROR(COUNTIF($U$9:$U$128,"Oui")/(COUNTIF($U$9:$U$128,"Oui")+COUNTIF($U$9:$U$128,"Non")),"") | V6: =SUMIF($Q$9:$Q$128,"Terminée",$X$9:$X$128)
A8: N° | B8: Date de détection | C8: Source | D8: Ligne / zone | E8: Problème constaté (fait mesuré) | F8: G | G8: F | H8: D | I8: Criticité (IPR) | J8: Famille 5M | K8: Cause racine validée (5 pourquoi) | L8: Action décidée | M8: Nature | N8: Pilote | O8: Date cible | P8: Avanc. | Q8: Statut | R8: Date de clôture | S8: Retard (j) | T8: Délai de traitement (j) | U8: Efficacité vérifiée | V8: Date de vérification | W8: Standard mis à jour | X8: Gain estimé (€/an) | Y8: Commentaire de suivi
A9: =IF($E9="","","A-"&TEXT(ROW()-8,"000")) | B9: 46030 | C9: Analyse Pareto TRS | D9: Ligne 1 - Assemblage | E9: Arrêts répétés du convoyeur d'alimentation : 185 min perdues sur la semaine 2 | F9: 3 | G9: 4 | H9: 3 | I9: =IF(OR($F9="",$G9="",$H9=""),"",$F9*$G9*$H9) | J9: Machine | K9: Capteur de position encrassé par les copeaux ; nettoyage absent du plan de maintenance préventive | L9: Ajouter le nettoyage hebdomadaire du capteur au plan préventif et former les deux équipes | M9: Préventive (D7) | N9: DURAND M. | O9: 46044 | P9: 0.6 | Q9: En cours | S9: =IF($O9="","",IF(OR($Q9="Terminée",$Q9="Abandonnée"),IF($R9="","",MAX(0,$R9-$O9)),MAX(0,TODAY()-$O9))) | T9: =IF(OR($R9="",$B9=""),"",$R9-$B9) | U9: En attente | W9: Oui | X9: 14000 | Y9: Vérifier l'absence de récidive sur 4 semaines glissantes
A10: =IF($E10="","","A-"&TEXT(ROW()-8,"000")) | B10: 46031 | C10: Qualité client | D10: Ligne 2 - Usinage | E10: Réclamation client : cote de perçage hors tolérance sur le lot OF-01018 (12 pièces) | F10: 5 | G10: 2 | H10: 4 | I10: =IF(OR($F10="",$G10="",$H10=""),"",$F10*$G10*$H10) | J10: Méthode | K10: Absence de contrôle de la première pièce après changement d'outil coupant | L10: Rendre bloquante la validation première pièce après tout changement d'outil (autocontrôle + visa) | M10: Corrective (D5) | N10: LEROY S. | O10: 46038 | P10: 1 | Q10: Terminée | R10: 46037 | S10: =IF($O10="","",IF(OR($Q10="Terminée",$Q10="Abandonnée"),IF($R10="","",MAX(0,$R10-$O10)),MAX(0,TODAY()-$O10))) | T10: =IF(OR($R10="",$B10=""),"",$R10-$B10) | U10: Oui | V10: 46066 | W10: Oui | X10: 22000 | Y10: Standard de poste et gamme de contrôle mis à jour
A11: =IF($E11="","","A-"&TEXT(ROW()-8,"000")) | B11: 46035 | C11: Sécurité | D11: Ligne 1 - Assemblage | E11: Accident avec arrêt : coupure à la main lors de l'évacuation des chutes | F11: 5 | G11: 1 | H11: 3 | I11: =IF(OR($F11="",$G11="",$H11=""),"",$F11*$G11*$H11) | J11: Milieu | K11: Bac d'évacuation des chutes sans protection, gants inadaptés au risque de coupure | L11: Installer un bac fermé et déployer des gants anti-coupure niveau C sur les deux lignes | M11: Corrective (D5) | N11: BAKARI F. | O11: 46042 | P11: 1 | Q11: Terminée | R11: 46041 | S11: =IF($O11="","",IF(OR($Q11="Terminée",$Q11="Abandonnée"),IF($R11="","",MAX(0,$R11-$O11)),MAX(0,TODAY()-$O11))) | T11: =IF(OR($R11="",$B11=""),"",$R11-$B11) | U11: Oui | V11: 46072 | W11: Oui | X11: 0 | Y11: Analyse d'accident diffusée aux trois équipes
A12: =IF($E12="","","A-"&TEXT(ROW()-8,"000")) | B12: 46036 | C12: Écart quotidien | D12: Ligne 2 - Usinage | E12: Temps de changement de série moyen de 38 min contre 25 min au standard | F12: 3 | G12: 5 | H12: 2 | I12: =IF(OR($F12="",$G12="",$H12=""),"",$F12*$G12*$H12) | J12: Méthode | K12: Outillage et moyens de contrôle non préparés avant l'arrêt machine (pas de séparation interne/externe) | L12: Déployer un chantier SMED : préparation externe systématique et chariot de changement dédié | M12: Amélioration | N12: MARCHAND J. | O12: 46066 | P12: 0.35 | Q12: En cours | S12: =IF($O12="","",IF(OR($Q12="Terminée",$Q12="Abandonnée"),IF($R12="","",MAX(0,$R12-$O12)),MAX(0,TODAY()-$O12))) | T12: =IF(OR($R12="",$B12=""),"",$R12-$B12) | U12: En attente | W12: Non | X12: 31000 | Y12: Chantier de fond n°1 — objectif 20 min
A13: =IF($E13="","","A-"&TEXT(ROW()-8,"000")) | B13: 46038 | C13: Audit 5S | D13: Ligne 3 - Conditionnement | E13: Zone de conditionnement notée 2,1/4 : allées encombrées par les en-cours | F13: 2 | G13: 4 | H13: 1 | I13: =IF(OR($F13="",$G13="",$H13=""),"",$F13*$G13*$H13) | J13: Milieu | K13: Limite d'en-cours non définie et non matérialisée au sol | L13: Définir un plafond d'en-cours, marquer les emplacements au sol et afficher la règle | M13: Corrective (D5) | N13: SOW I. | O13: 46052 | P13: 0.5 | Q13: En cours | S13: =IF($O13="","",IF(OR($Q13="Terminée",$Q13="Abandonnée"),IF($R13="","",MAX(0,$R13-$O13)),MAX(0,TODAY()-$O13))) | T13: =IF(OR($R13="",$B13=""),"",$R13-$B13) | U13: En attente | W13: Non | X13: 0 | Y13: Recontrôle au prochain audit 5S
A14: =IF($E14="","","A-"&TEXT(ROW()-8,"000")) | B14: 46041 | C14: Idée opérateur | D14: Ligne 1 - Assemblage | E14: Recherche d'outillage au poste d'assemblage : 5 à 8 min perdues par poste | F14: 1 | G14: 5 | H14: 2 | I14: =IF(OR($F14="",$G14="",$H14=""),"",$F14*$G14*$H14) | J14: Milieu | K14: Aucun emplacement dédié aux outils de réglage | L14: Réaliser un panneau d'ombres (shadow board) au poste d'assemblage | M14: Amélioration | N14: PETIT C. | O14: 46059 | P14: 0.2 | Q14: En cours | S14: =IF($O14="","",IF(OR($Q14="Terminée",$Q14="Abandonnée"),IF($R14="","",MAX(0,$R14-$O14)),MAX(0,TODAY()-$O14))) | T14: =IF(OR($R14="",$B14=""),"",$R14-$B14) | U14: En attente | W14: Non | X14: 6000 | Y14: Proposée par l'équipe A lors du point 5 minutes
A15: =IF($E15="","","A-"&TEXT(ROW()-8,"000")) | B15: 46042 | C15: Écart quotidien | D15: Ligne 2 - Usinage | E15: Rupture matière sur REF-2002 : 55 min d'arrêt le 20/01 | F15: 3 | G15: 3 | H15: 3 | I15: =IF(OR($F15="",$G15="",$H15=""),"",$F15*$G15*$H15) | J15: Matière | K15: Seuil de réapprovisionnement calculé sans tenir compte du délai fournisseur réel (8 j au lieu de 5 j) | L15: Recalculer les points de commande sur la base des délais réels et alerter à J-3 | M15: Préventive (D7) | N15: NGOM A. | O15: 46056 | P15: 0 | Q15: À lancer | S15: =IF($O15="","",IF(OR($Q15="Terminée",$Q15="Abandonnée"),IF($R15="","",MAX(0,$R15-$O15)),MAX(0,TODAY()-$O15))) | T15: =IF(OR($R15="",$B15=""),"",$R15-$B15) | U15: En attente | W15: Non | X15: 9000 | Y15: À traiter avec le service approvisionnement
A16: =IF($E16="","","A-"&TEXT(ROW()-8,"000")) | B16: 46044 | C16: Analyse Pareto TRS | D16: Ligne 1 - Assemblage | E16: Micro-arrêts récurrents en fin de poste (bourrage évacuation) | F16: 2 | G16: 4 | H16: 4 | I16: =IF(OR($F16="",$G16="",$H16=""),"",$F16*$G16*$H16) | J16: Machine | K16: Guide d'évacuation déréglé, aucun standard de contrôle en fin de poste | L16: Régler le guide et ajouter le point au standard de fin de poste | M16: Corrective (D5) | N16: GARNIER L. | O16: 46050 | P16: 0.8 | Q16: En cours | S16: =IF($O16="","",IF(OR($Q16="Terminée",$Q16="Abandonnée"),IF($R16="","",MAX(0,$R16-$O16)),MAX(0,TODAY()-$O16))) | T16: =IF(OR($R16="",$B16=""),"",$R16-$B16) | U16: En attente | W16: Oui | X16: 7500 | Y16: Suivi quotidien du nombre de micro-arrêts
A17: =IF($E17="","","A-"&TEXT(ROW()-8,"000")) | I17: =IF(OR($F17="",$G17="",$H17=""),"",$F17*$G17*$H17) | S17: =IF($O17="","",IF(OR($Q17="Terminée",$Q17="Abandonnée"),IF($R17="","",MAX(0,$R17-$O17)),MAX(0,TODAY()-$O17))) | T17: =IF(OR($R17="",$B17=""),"",$R17-$B17)
A18: =IF($E18="","","A-"&TEXT(ROW()-8,"000")) | I18: =IF(OR($F18="",$G18="",$H18=""),"",$F18*$G18*$H18) | S18: =IF($O18="","",IF(OR($Q18="Terminée",$Q18="Abandonnée"),IF($R18="","",MAX(0,$R18-$O18)),MAX(0,TODAY()-$O18))) | T18: =IF(OR($R18="",$B18=""),"",$R18-$B18)
A19: =IF($E19="","","A-"&TEXT(ROW()-8,"000")) | I19: =IF(OR($F19="",$G19="",$H19=""),"",$F19*$G19*$H19) | S19: =IF($O19="","",IF(OR($Q19="Terminée",$Q19="Abandonnée"),IF($R19="","",MAX(0,$R19-$O19)),MAX(0,TODAY()-$O19))) | T19: =IF(OR($R19="",$B19=""),"",$R19-$B19)
A20: =IF($E20="","","A-"&TEXT(ROW()-8,"000")) | I20: =IF(OR($F20="",$G20="",$H20=""),"",$F20*$G20*$H20) | S20: =IF($O20="","",IF(OR($Q20="Terminée",$Q20="Abandonnée"),IF($R20="","",MAX(0,$R20-$O20)),MAX(0,TODAY()-$O20))) | T20: =IF(OR($R20="",$B20=""),"",$R20-$B20)
A21: =IF($E21="","","A-"&TEXT(ROW()-8,"000")) | I21: =IF(OR($F21="",$G21="",$H21=""),"",$F21*$G21*$H21) | S21: =IF($O21="","",IF(OR($Q21="Terminée",$Q21="Abandonnée"),IF($R21="","",MAX(0,$R21-$O21)),MAX(0,TODAY()-$O21))) | T21: =IF(OR($R21="",$B21=""),"",$R21-$B21)
A22: =IF($E22="","","A-"&TEXT(ROW()-8,"000")) | I22: =IF(OR($F22="",$G22="",$H22=""),"",$F22*$G22*$H22) | S22: =IF($O22="","",IF(OR($Q22="Terminée",$Q22="Abandonnée"),IF($R22="","",MAX(0,$R22-$O22)),MAX(0,TODAY()-$O22))) | T22: =IF(OR($R22="",$B22=""),"",$R22-$B22)
A23: =IF($E23="","","A-"&TEXT(ROW()-8,"000")) | I23: =IF(OR($F23="",$G23="",$H23=""),"",$F23*$G23*$H23) | S23: =IF($O23="","",IF(OR($Q23="Terminée",$Q23="Abandonnée"),IF($R23="","",MAX(0,$R23-$O23)),MAX(0,TODAY()-$O23))) | T23: =IF(OR($R23="",$B23=""),"",$R23-$B23)
A24: =IF($E24="","","A-"&TEXT(ROW()-8,"000")) | I24: =IF(OR($F24="",$G24="",$H24=""),"",$F24*$G24*$H24) | S24: =IF($O24="","",IF(OR($Q24="Terminée",$Q24="Abandonnée"),IF($R24="","",MAX(0,$R24-$O24)),MAX(0,TODAY()-$O24))) | T24: =IF(OR($R24="",$B24=""),"",$R24-$B24)
A25: =IF($E25="","","A-"&TEXT(ROW()-8,"000")) | I25: =IF(OR($F25="",$G25="",$H25=""),"",$F25*$G25*$H25) | S25: =IF($O25="","",IF(OR($Q25="Terminée",$Q25="Abandonnée"),IF($R25="","",MAX(0,$R25-$O25)),MAX(0,TODAY()-$O25))) | T25: =IF(OR($R25="",$B25=""),"",$R25-$B25)
A26: =IF($E26="","","A-"&TEXT(ROW()-8,"000")) | I26: =IF(OR($F26="",$G26="",$H26=""),"",$F26*$G26*$H26) | S26: =IF($O26="","",IF(OR($Q26="Terminée",$Q26="Abandonnée"),IF($R26="","",MAX(0,$R26-$O26)),MAX(0,TODAY()-$O26))) | T26: =IF(OR($R26="",$B26=""),"",$R26-$B26)
A27: =IF($E27="","","A-"&TEXT(ROW()-8,"000")) | I27: =IF(OR($F27="",$G27="",$H27=""),"",$F27*$G27*$H27) | S27: =IF($O27="","",IF(OR($Q27="Terminée",$Q27="Abandonnée"),IF($R27="","",MAX(0,$R27-$O27)),MAX(0,TODAY()-$O27))) | T27: =IF(OR($R27="",$B27=""),"",$R27-$B27)
A28: =IF($E28="","","A-"&TEXT(ROW()-8,"000")) | I28: =IF(OR($F28="",$G28="",$H28=""),"",$F28*$G28*$H28) | S28: =IF($O28="","",IF(OR($Q28="Terminée",$Q28="Abandonnée"),IF($R28="","",MAX(0,$R28-$O28)),MAX(0,TODAY()-$O28))) | T28: =IF(OR($R28="",$B28=""),"",$R28-$B28)
... A128: =IF($E128="","","A-"&TEXT(ROW()-8,"000")) | I128: =IF(OR($F128="",$G128="",$H128=""),"",$F128*$G128*$H128) | S128: =IF($O128="","",IF(OR($Q128="Terminée",$Q128="Abandonnée"),IF($R128="","",MAX(0,$R128-$O128)),MAX(0,TODAY()-$O128))) | T128: =IF(OR($R128="",$B128=""),"",$R128-$B128)
A130: Cotation de la criticité (IPR) : Gravité — 1 gêne interne … 5 arrêt client ou accident • Fréquence — 1 exceptionnel … 5 quotidien • Détection — 1 détecté immédiatement … 5 détecté par le client. Une action de criticité ≥ 30 doit être traitée en priorité et faire l'objet d'une vérification d'efficacité tracée.

Sheet POLYVALENCE
A1: MATRICE DE POLYVALENCE — couverture des postes de travail
A2: Échelle ILUO : 0 non formé • 1 en formation • 2 autonome avec appui • 3 autonome • 4 autonome et formateur. Un poste est considéré couvert lorsque l'effectif autonome (niveau ≥ 3) atteint la cible définie dans PARAMETRES.
A4: INDICATEURS DE COMPÉTENCE — calculés automatiquement
A5: Effectif suivi | D5: Taux de polyvalence global | G5: Postes sous la cible | J5: Postes en mono-compétence | M5: Niveau moyen de maîtrise | Q5: Postes critiques couverts
A6: =COUNTA($B$12:$B$51) | D6: =IFERROR(SUM($E$12:$P$51)/(4*COUNTIF($E$9:$P$9,"?*")*COUNTA($B$12:$B$51)),"") | G6: =COUNTIF($E$56:$P$56,"<0") | J6: =COUNTIF($E$58:$P$58,"OUI") | M6: =IFERROR(AVERAGE($E$12:$P$51),"") | Q6: =SUMPRODUCT(($E$10:$P$10=3)*($E$53:$P$53>=$E$11:$P$11))
A8: MATRICE DES COMPÉTENCES
A9: Matricule | B9: Collaborateur | C9: Équipe | D9: Statut | E9: =IF(INDEX(PARAMETRES!$X$7:$X$26,COLUMN()-4)="","",INDEX(PARAMETRES!$X$7:$X$26,COLUMN()-4)) | F9: =IF(INDEX(PARAMETRES!$X$7:$X$26,COLUMN()-4)="","",INDEX(PARAMETRES!$X$7:$X$26,COLUMN()-4)) | G9: =IF(INDEX(PARAMETRES!$X$7:$X$26,COLUMN()-4)="","",INDEX(PARAMETRES!$X$7:$X$26,COLUMN()-4)) | H9: =IF(INDEX(PARAMETRES!$X$7:$X$26,COLUMN()-4)="","",INDEX(PARAMETRES!$X$7:$X$26,COLUMN()-4)) | I9: =IF(INDEX(PARAMETRES!$X$7:$X$26,COLUMN()-4)="","",INDEX(PARAMETRES!$X$7:$X$26,COLUMN()-4)) | J9: =IF(INDEX(PARAMETRES!$X$7:$X$26,COLUMN()-4)="","",INDEX(PARAMETRES!$X$7:$X$26,COLUMN()-4)) | K9: =IF(INDEX(PARAMETRES!$X$7:$X$26,COLUMN()-4)="","",INDEX(PARAMETRES!$X$7:$X$26,COLUMN()-4)) | L9: =IF(INDEX(PARAMETRES!$X$7:$X$26,COLUMN()-4)="","",INDEX(PARAMETRES!$X$7:$X$26,COLUMN()-4)) | ... P9: =IF(INDEX(PARAMETRES!$X$7:$X$26,COLUMN()-4)="","",INDEX(PARAMETRES!$X$7:$X$26,COLUMN()-4)) | Q9: Postes autonomes | R9: Taux de maîtrise | S9: Postes critiques maîtrisés | T9: Prochaine étape de formation
A10: Criticité du poste (1 à 3) | E10: =IF(INDEX(PARAMETRES!$X$7:$X$26,COLUMN()-4)="","",INDEX(PARAMETRES!$Y$7:$Y$26,COLUMN()-4)) | F10: =IF(INDEX(PARAMETRES!$X$7:$X$26,COLUMN()-4)="","",INDEX(PARAMETRES!$Y$7:$Y$26,COLUMN()-4)) | G10: =IF(INDEX(PARAMETRES!$X$7:$X$26,COLUMN()-4)="","",INDEX(PARAMETRES!$Y$7:$Y$26,COLUMN()-4)) | H10: =IF(INDEX(PARAMETRES!$X$7:$X$26,COLUMN()-4)="","",INDEX(PARAMETRES!$Y$7:$Y$26,COLUMN()-4)) | I10: =IF(INDEX(PARAMETRES!$X$7:$X$26,COLUMN()-4)="","",INDEX(PARAMETRES!$Y$7:$Y$26,COLUMN()-4)) | J10: =IF(INDEX(PARAMETRES!$X$7:$X$26,COLUMN()-4)="","",INDEX(PARAMETRES!$Y$7:$Y$26,COLUMN()-4)) | K10: =IF(INDEX(PARAMETRES!$X$7:$X$26,COLUMN()-4)="","",INDEX(PARAMETRES!$Y$7:$Y$26,COLUMN()-4)) | L10: =IF(INDEX(PARAMETRES!$X$7:$X$26,COLUMN()-4)="","",INDEX(PARAMETRES!$Y$7:$Y$26,COLUMN()-4)) | ... P10: =IF(INDEX(PARAMETRES!$X$7:$X$26,COLUMN()-4)="","",INDEX(PARAMETRES!$Y$7:$Y$26,COLUMN()-4))
A11: Effectif autonome cible | E11: =IF(INDEX(PARAMETRES!$X$7:$X$26,COLUMN()-4)="","",INDEX(PARAMETRES!$Z$7:$Z$26,COLUMN()-4)) | F11: =IF(INDEX(PARAMETRES!$X$7:$X$26,COLUMN()-4)="","",INDEX(PARAMETRES!$Z$7:$Z$26,COLUMN()-4)) | G11: =IF(INDEX(PARAMETRES!$X$7:$X$26,COLUMN()-4)="","",INDEX(PARAMETRES!$Z$7:$Z$26,COLUMN()-4)) | H11: =IF(INDEX(PARAMETRES!$X$7:$X$26,COLUMN()-4)="","",INDEX(PARAMETRES!$Z$7:$Z$26,COLUMN()-4)) | I11: =IF(INDEX(PARAMETRES!$X$7:$X$26,COLUMN()-4)="","",INDEX(PARAMETRES!$Z$7:$Z$26,COLUMN()-4)) | J11: =IF(INDEX(PARAMETRES!$X$7:$X$26,COLUMN()-4)="","",INDEX(PARAMETRES!$Z$7:$Z$26,COLUMN()-4)) | K11: =IF(INDEX(PARAMETRES!$X$7:$X$26,COLUMN()-4)="","",INDEX(PARAMETRES!$Z$7:$Z$26,COLUMN()-4)) | L11: =IF(INDEX(PARAMETRES!$X$7:$X$26,COLUMN()-4)="","",INDEX(PARAMETRES!$Z$7:$Z$26,COLUMN()-4)) | ... P11: =IF(INDEX(PARAMETRES!$X$7:$X$26,COLUMN()-4)="","",INDEX(PARAMETRES!$Z$7:$Z$26,COLUMN()-4))
A12: M-1042 | B12: DUPONT Marie | C12: Équipe A (matin) | D12: CDI | E12: 4 | F12: 3 | G12: 2 | H12: 4 | I12: 3 | J12: 2 | K12: 3 | L12: 1 | M12: 3 | N12: 3 | O12: 4 | P12: 3 | Q12: =IF($B12="","",COUNTIF($E12:$P12,">=3")) | R12: =IF($B12="","",IFERROR(SUM($E12:$P12)/(4*COUNTIF($E$9:$P$9,"?*")),"")) | S12: =IF($B12="","",SUMPRODUCT(($E$10:$P$10=3)*($E12:$P12>=3)))
A13: M-1078 | B13: NGOM Abdoulaye | C13: Équipe A (matin) | D13: CDI | E13: 3 | F13: 4 | G13: 2 | H13: 3 | I13: 2 | J13: 1 | K13: 4 | L13: 2 | M13: 2 | N13: 1 | O13: 2 | P13: 1 | Q13: =IF($B13="","",COUNTIF($E13:$P13,">=3")) | R13: =IF($B13="","",IFERROR(SUM($E13:$P13)/(4*COUNTIF($E$9:$P$9,"?*")),"")) | S13: =IF($B13="","",SUMPRODUCT(($E$10:$P$10=3)*($E13:$P13>=3)))
A14: M-1103 | B14: LEROY Sophie | C14: Équipe A (matin) | D14: CDI | E14: 2 | F14: 3 | G14: 3 | H14: 2 | I14: 4 | J14: 3 | K14: 1 | L14: 1 | M14: 3 | N14: 4 | O14: 3 | P14: 2 | Q14: =IF($B14="","",COUNTIF($E14:$P14,">=3")) | R14: =IF($B14="","",IFERROR(SUM($E14:$P14)/(4*COUNTIF($E$9:$P$9,"?*")),"")) | S14: =IF($B14="","",SUMPRODUCT(($E$10:$P$10=3)*($E14:$P14>=3)))
A15: M-1156 | B15: BAKARI Fatou | C15: Équipe A (matin) | D15: CDI | E15: 3 | F15: 2 | G15: 1 | H15: 3 | I15: 3 | J15: 4 | K15: 2 | L15: 3 | M15: 2 | N15: 1 | O15: 1 | P15: 0 | Q15: =IF($B15="","",COUNTIF($E15:$P15,">=3")) | R15: =IF($B15="","",IFERROR(SUM($E15:$P15)/(4*COUNTIF($E$9:$P$9,"?*")),"")) | S15: =IF($B15="","",SUMPRODUCT(($E$10:$P$10=3)*($E15:$P15>=3)))
A16: M-1201 | B16: PETIT Camille | C16: Équipe A (matin) | D16: Intérim | E16: 1 | F16: 1 | G16: 2 | H16: 0 | I16: 2 | J16: 2 | K16: 0 | L16: 3 | M16: 3 | N16: 0 | O16: 0 | P16: 0 | Q16: =IF($B16="","",COUNTIF($E16:$P16,">=3")) | R16: =IF($B16="","",IFERROR(SUM($E16:$P16)/(4*COUNTIF($E$9:$P$9,"?*")),"")) | S16: =IF($B16="","",SUMPRODUCT(($E$10:$P$10=3)*($E16:$P16>=3)))
A17: M-1233 | B17: MARCHAND Julien | C17: Équipe B (après-midi) | D17: CDI | E17: 4 | F17: 3 | G17: 3 | H17: 4 | I17: 2 | J17: 2 | K17: 3 | L17: 2 | M17: 3 | N17: 3 | O17: 3 | P17: 2 | Q17: =IF($B17="","",COUNTIF($E17:$P17,">=3")) | R17: =IF($B17="","",IFERROR(SUM($E17:$P17)/(4*COUNTIF($E$9:$P$9,"?*")),"")) | S17: =IF($B17="","",SUMPRODUCT(($E$10:$P$10=3)*($E17:$P17>=3)))
A18: M-1245 | B18: SOW Ibrahima | C18: Équipe B (après-midi) | D18: CDI | E18: 2 | F18: 4 | G18: 2 | H18: 3 | I18: 3 | J18: 1 | K18: 2 | L18: 4 | M18: 2 | N18: 1 | O18: 1 | P18: 1 | Q18: =IF($B18="","",COUNTIF($E18:$P18,">=3")) | R18: =IF($B18="","",IFERROR(SUM($E18:$P18)/(4*COUNTIF($E$9:$P$9,"?*")),"")) | S18: =IF($B18="","",SUMPRODUCT(($E$10:$P$10=3)*($E18:$P18>=3)))
A19: M-1290 | B19: GARNIER Louis | C19: Équipe B (après-midi) | D19: CDI | E19: 3 | F19: 2 | G19: 3 | H19: 2 | I19: 3 | J19: 3 | K19: 1 | L19: 2 | M19: 4 | N19: 2 | O19: 2 | P19: 1 | Q19: =IF($B19="","",COUNTIF($E19:$P19,">=3")) | R19: =IF($B19="","",IFERROR(SUM($E19:$P19)/(4*COUNTIF($E$9:$P$9,"?*")),"")) | S19: =IF($B19="","",SUMPRODUCT(($E$10:$P$10=3)*($E19:$P19>=3)))
A20: M-1312 | B20: ROUX Émilie | C20: Équipe B (après-midi) | D20: CDD | E20: 1 | F20: 2 | G20: 1 | H20: 1 | I20: 2 | J20: 3 | K20: 0 | L20: 1 | M20: 3 | N20: 0 | O20: 0 | P20: 0 | Q20: =IF($B20="","",COUNTIF($E20:$P20,">=3")) | R20: =IF($B20="","",IFERROR(SUM($E20:$P20)/(4*COUNTIF($E$9:$P$9,"?*")),"")) | S20: =IF($B20="","",SUMPRODUCT(($E$10:$P$10=3)*($E20:$P20>=3)))
A21: M-1355 | B21: FAYE Moussa | C21: Équipe B (après-midi) | D21: CDI | E21: 3 | F21: 3 | G21: 2 | H21: 3 | I21: 1 | J21: 2 | K21: 3 | L21: 3 | M21: 2 | N21: 2 | O21: 2 | P21: 1 | Q21: =IF($B21="","",COUNTIF($E21:$P21,">=3")) | R21: =IF($B21="","",IFERROR(SUM($E21:$P21)/(4*COUNTIF($E$9:$P$9,"?*")),"")) | S21: =IF($B21="","",SUMPRODUCT(($E$10:$P$10=3)*($E21:$P21>=3)))
A22: M-1401 | B22: BERNARD Alice | C22: Équipe C (nuit) | D22: CDI | E22: 2 | F22: 2 | G22: 4 | H22: 2 | I22: 3 | J22: 2 | K22: 2 | L22: 2 | M22: 3 | N22: 3 | O22: 1 | P22: 1 | Q22: =IF($B22="","",COUNTIF($E22:$P22,">=3")) | R22: =IF($B22="","",IFERROR(SUM($E22:$P22)/(4*COUNTIF($E$9:$P$9,"?*")),"")) | S22: =IF($B22="","",SUMPRODUCT(($E$10:$P$10=3)*($E22:$P22>=3)))
A23: M-1433 | B23: DIALLO Aminata | C23: Équipe C (nuit) | D23: CDI | E23: 1 | F23: 1 | G23: 3 | H23: 1 | I23: 2 | J23: 3 | K23: 1 | L23: 2 | M23: 2 | N23: 1 | O23: 0 | P23: 0 | Q23: =IF($B23="","",COUNTIF($E23:$P23,">=3")) | R23: =IF($B23="","",IFERROR(SUM($E23:$P23)/(4*COUNTIF($E$9:$P$9,"?*")),"")) | S23: =IF($B23="","",SUMPRODUCT(($E$10:$P$10=3)*($E23:$P23>=3)))
Q24: =IF($B24="","",COUNTIF($E24:$P24,">=3")) | R24: =IF($B24="","",IFERROR(SUM($E24:$P24)/(4*COUNTIF($E$9:$P$9,"?*")),"")) | S24: =IF($B24="","",SUMPRODUCT(($E$10:$P$10=3)*($E24:$P24>=3)))
Q25: =IF($B25="","",COUNTIF($E25:$P25,">=3")) | R25: =IF($B25="","",IFERROR(SUM($E25:$P25)/(4*COUNTIF($E$9:$P$9,"?*")),"")) | S25: =IF($B25="","",SUMPRODUCT(($E$10:$P$10=3)*($E25:$P25>=3)))
Q26: =IF($B26="","",COUNTIF($E26:$P26,">=3")) | R26: =IF($B26="","",IFERROR(SUM($E26:$P26)/(4*COUNTIF($E$9:$P$9,"?*")),"")) | S26: =IF($B26="","",SUMPRODUCT(($E$10:$P$10=3)*($E26:$P26>=3)))
Q27: =IF($B27="","",COUNTIF($E27:$P27,">=3")) | R27: =IF($B27="","",IFERROR(SUM($E27:$P27)/(4*COUNTIF($E$9:$P$9,"?*")),"")) | S27: =IF($B27="","",SUMPRODUCT(($E$10:$P$10=3)*($E27:$P27>=3)))
Q28: =IF($B28="","",COUNTIF($E28:$P28,">=3")) | R28: =IF($B28="","",IFERROR(SUM($E28:$P28)/(4*COUNTIF($E$9:$P$9,"?*")),"")) | S28: =IF($B28="","",SUMPRODUCT(($E$10:$P$10=3)*($E28:$P28>=3)))
Q29: =IF($B29="","",COUNTIF($E29:$P29,">=3")) | R29: =IF($B29="","",IFERROR(SUM($E29:$P29)/(4*COUNTIF($E$9:$P$9,"?*")),"")) | S29: =IF($B29="","",SUMPRODUCT(($E$10:$P$10=3)*($E29:$P29>=3)))
Q30: =IF($B30="","",COUNTIF($E30:$P30,">=3")) | R30: =IF($B30="","",IFERROR(SUM($E30:$P30)/(4*COUNTIF($E$9:$P$9,"?*")),"")) | S30: =IF($B30="","",SUMPRODUCT(($E$10:$P$10=3)*($E30:$P30>=3)))
Q31: =IF($B31="","",COUNTIF($E31:$P31,">=3")) | R31: =IF($B31="","",IFERROR(SUM($E31:$P31)/(4*COUNTIF($E$9:$P$9,"?*")),"")) | S31: =IF($B31="","",SUMPRODUCT(($E$10:$P$10=3)*($E31:$P31>=3)))
Q32: =IF($B32="","",COUNTIF($E32:$P32,">=3")) | R32: =IF($B32="","",IFERROR(SUM($E32:$P32)/(4*COUNTIF($E$9:$P$9,"?*")),"")) | S32: =IF($B32="","",SUMPRODUCT(($E$10:$P$10=3)*($E32:$P32>=3)))
Q33: =IF($B33="","",COUNTIF($E33:$P33,">=3")) | R33: =IF($B33="","",IFERROR(SUM($E33:$P33)/(4*COUNTIF($E$9:$P$9,"?*")),"")) | S33: =IF($B33="","",SUMPRODUCT(($E$10:$P$10=3)*($E33:$P33>=3)))
Q34: =IF($B34="","",COUNTIF($E34:$P34,">=3")) | R34: =IF($B34="","",IFERROR(SUM($E34:$P34)/(4*COUNTIF($E$9:$P$9,"?*")),"")) | S34: =IF($B34="","",SUMPRODUCT(($E$10:$P$10=3)*($E34:$P34>=3)))
Q35: =IF($B35="","",COUNTIF($E35:$P35,">=3")) | R35: =IF($B35="","",IFERROR(SUM($E35:$P35)/(4*COUNTIF($E$9:$P$9,"?*")),"")) | S35: =IF($B35="","",SUMPRODUCT(($E$10:$P$10=3)*($E35:$P35>=3)))
... Q51: =IF($B51="","",COUNTIF($E51:$P51,">=3")) | R51: =IF($B51="","",IFERROR(SUM($E51:$P51)/(4*COUNTIF($E$9:$P$9,"?*")),"")) | S51: =IF($B51="","",SUMPRODUCT(($E$10:$P$10=3)*($E51:$P51>=3)))
A52: COUVERTURE DES POSTES — lecture du risque de compétence
A53: Effectif autonome (niveau ≥ 3) | E53: =COUNTIF($E$12:$E$51,">=3") | F53: =COUNTIF($F$12:$F$51,">=3") | G53: =COUNTIF($G$12:$G$51,">=3") | H53: =COUNTIF($H$12:$H$51,">=3") | I53: =COUNTIF($I$12:$I$51,">=3") | J53: =COUNTIF($J$12:$J$51,">=3") | K53: =COUNTIF($K$12:$K$51,">=3") | L53: =COUNTIF($L$12:$L$51,">=3") | M53: =COUNTIF($M$12:$M$51,">=3") | N53: =COUNTIF($N$12:$N$51,">=3") | O53: =COUNTIF($O$12:$O$51,">=3") | P53: =COUNTIF($P$12:$P$51,">=3")
A54: Effectif en formation (niveaux 1 et 2) | E54: =COUNTIFS($E$12:$E$51,">=1",$E$12:$E$51,"<3") | F54: =COUNTIFS($F$12:$F$51,">=1",$F$12:$F$51,"<3") | G54: =COUNTIFS($G$12:$G$51,">=1",$G$12:$G$51,"<3") | H54: =COUNTIFS($H$12:$H$51,">=1",$H$12:$H$51,"<3") | I54: =COUNTIFS($I$12:$I$51,">=1",$I$12:$I$51,"<3") | J54: =COUNTIFS($J$12:$J$51,">=1",$J$12:$J$51,"<3") | K54: =COUNTIFS($K$12:$K$51,">=1",$K$12:$K$51,"<3") | L54: =COUNTIFS($L$12:$L$51,">=1",$L$12:$L$51,"<3") | M54: =COUNTIFS($M$12:$M$51,">=1",$M$12:$M$51,"<3") | N54: =COUNTIFS($N$12:$N$51,">=1",$N$12:$N$51,"<3") | O54: =COUNTIFS($O$12:$O$51,">=1",$O$12:$O$51,"<3") | P54: =COUNTIFS($P$12:$P$51,">=1",$P$12:$P$51,"<3")
A55: Effectif autonome cible | E55: =$E$11 | F55: =$F$11 | G55: =$G$11 | H55: =$H$11 | I55: =$I$11 | J55: =$J$11 | K55: =$K$11 | L55: =$L$11 | M55: =$M$11 | N55: =$N$11 | O55: =$O$11 | P55: =$P$11
A56: Écart à la cible | E56: =IF($E$11="","",$E$53-$E$11) | F56: =IF($F$11="","",$F$53-$F$11) | G56: =IF($G$11="","",$G$53-$G$11) | H56: =IF($H$11="","",$H$53-$H$11) | I56: =IF($I$11="","",$I$53-$I$11) | J56: =IF($J$11="","",$J$53-$J$11) | K56: =IF($K$11="","",$K$53-$K$11) | L56: =IF($L$11="","",$L$53-$L$11) | M56: =IF($M$11="","",$M$53-$M$11) | N56: =IF($N$11="","",$N$53-$N$11) | O56: =IF($O$11="","",$O$53-$O$11) | P56: =IF($P$11="","",$P$53-$P$11)
A57: Taux de couverture | E57: =IFERROR($E$53/$E$11,"") | F57: =IFERROR($F$53/$F$11,"") | G57: =IFERROR($G$53/$G$11,"") | H57: =IFERROR($H$53/$H$11,"") | I57: =IFERROR($I$53/$I$11,"") | J57: =IFERROR($J$53/$J$11,"") | K57: =IFERROR($K$53/$K$11,"") | L57: =IFERROR($L$53/$L$11,"") | M57: =IFERROR($M$53/$M$11,"") | N57: =IFERROR($N$53/$N$11,"") | O57: =IFERROR($O$53/$O$11,"") | P57: =IFERROR($P$53/$P$11,"")
A58: Risque de mono-compétence | E58: =IF($E$9="","",IF($E$53<=1,"OUI","non")) | F58: =IF($F$9="","",IF($F$53<=1,"OUI","non")) | G58: =IF($G$9="","",IF($G$53<=1,"OUI","non")) | H58: =IF($H$9="","",IF($H$53<=1,"OUI","non")) | I58: =IF($I$9="","",IF($I$53<=1,"OUI","non")) | J58: =IF($J$9="","",IF($J$53<=1,"OUI","non")) | K58: =IF($K$9="","",IF($K$53<=1,"OUI","non")) | L58: =IF($L$9="","",IF($L$53<=1,"OUI","non")) | M58: =IF($M$9="","",IF($M$53<=1,"OUI","non")) | N58: =IF($N$9="","",IF($N$53<=1,"OUI","non")) | O58: =IF($O$9="","",IF($O$53<=1,"OUI","non")) | P58: =IF($P$9="","",IF($P$53<=1,"OUI","non"))
A59: Statut du poste | E59: =IF($E$9="","",IF($E$53>=$E$11,"Couvert",IF($E$53>=$E$11-1,"Vigilance","Critique"))) | F59: =IF($F$9="","",IF($F$53>=$F$11,"Couvert",IF($F$53>=$F$11-1,"Vigilance","Critique"))) | G59: =IF($G$9="","",IF($G$53>=$G$11,"Couvert",IF($G$53>=$G$11-1,"Vigilance","Critique"))) | H59: =IF($H$9="","",IF($H$53>=$H$11,"Couvert",IF($H$53>=$H$11-1,"Vigilance","Critique"))) | I59: =IF($I$9="","",IF($I$53>=$I$11,"Couvert",IF($I$53>=$I$11-1,"Vigilance","Critique"))) | J59: =IF($J$9="","",IF($J$53>=$J$11,"Couvert",IF($J$53>=$J$11-1,"Vigilance","Critique"))) | K59: =IF($K$9="","",IF($K$53>=$K$11,"Couvert",IF($K$53>=$K$11-1,"Vigilance","Critique"))) | L59: =IF($L$9="","",IF($L$53>=$L$11,"Couvert",IF($L$53>=$L$11-1,"Vigilance","Critique"))) | M59: =IF($M$9="","",IF($M$53>=$M$11,"Couvert",IF($M$53>=$M$11-1,"Vigilance","Critique"))) | N59: =IF($N$9="","",IF($N$53>=$N$11,"Couvert",IF($N$53>=$N$11-1,"Vigilance","Critique"))) | O59: =IF($O$9="","",IF($O$53>=$O$11,"Couvert",IF($O$53>=$O$11-1,"Vigilance","Critique"))) | P59: =IF($P$9="","",IF($P$53>=$P$11,"Couvert",IF($P$53>=$P$11-1,"Vigilance","Critique")))

Sheet AUDIT_5S
A1: AUDIT 5S — grille terrain pondérée
A2: Notation de chaque critère de 0 à 4 : 0 non fait • 1 amorcé • 2 partiel • 3 conforme • 4 exemplaire et tenu dans la durée. La pondération traduit l'importance du critère pour la zone auditée (1 = utile, 2 = important, 3 = majeur).
A4: IDENTIFICATION DE L'AUDIT
A5: Zone auditée : | C5: Ligne 1 - Assemblage | E5: Date de l'audit : | F5: 46052 | H5: Auditeur : | I5: LEROY S.
A6: Zone de référence : | C6: UAP Assemblage-Usinage | E6: Audit précédent : | F6: 46010 | H6: Accompagné de : | I6: Équipe A (matin)
A7: Domaine | B7: N° | C7: Critère observé sur le terrain | D7: Pondération | E7: Note (0 à 4) | F7: Note pondérée | G7: Note audit N-1 | H7: Écart | I7: Constat terrain | J7: Action corrective décidée | K7: Pilote | L7: Délai
A8: 1S Débarrasser | B8: 1 | C8: Aucun objet, pièce ou en-cours inutile dans la zone | D8: 2 | E8: 3 | F8: =IF($E8="","",$D8*$E8) | G8: 2 | H8: =IF(OR($E8="",$G8=""),"",$E8-$G8)
A9: 1S Débarrasser | B9: 2 | C9: Les en-cours ne dépassent pas la limite définie et affichée | D9: 3 | E9: 2 | F9: =IF($E9="","",$D9*$E9) | G9: 2 | H9: =IF(OR($E9="",$G9=""),"",$E9-$G9)
A10: 1S Débarrasser | B10: 3 | C10: Aucun document obsolète affiché (version et date visibles) | D10: 1 | E10: 3 | F10: =IF($E10="","",$D10*$E10) | G10: 3 | H10: =IF(OR($E10="",$G10=""),"",$E10-$G10)
A11: 1S Débarrasser | B11: 4 | C11: Les objets sans propriétaire sont identifiés et traités (zone rouge) | D11: 1 | E11: 2 | F11: =IF($E11="","",$D11*$E11) | G11: 1 | H11: =IF(OR($E11="",$G11=""),"",$E11-$G11)
A12: 1S Débarrasser | B12: 5 | C12: Allées, accès machines et issues de secours totalement dégagés | D12: 3 | E12: 3 | F12: =IF($E12="","",$D12*$E12) | G12: 3 | H12: =IF(OR($E12="",$G12=""),"",$E12-$G12)
A13: 2S Ranger | B13: 1 | C13: Chaque outil dispose d'un emplacement unique et identifié | D13: 3 | E13: 2 | F13: =IF($E13="","",$D13*$E13) | G13: 2 | H13: =IF(OR($E13="",$G13=""),"",$E13-$G13)
A14: 2S Ranger | B14: 2 | C14: Marquage au sol présent, lisible et respecté | D14: 2 | E14: 3 | F14: =IF($E14="","",$D14*$E14) | G14: 2 | H14: =IF(OR($E14="",$G14=""),"",$E14-$G14)
A15: 2S Ranger | B15: 3 | C15: EPI rangés, disponibles et à portée immédiate | D15: 3 | E15: 4 | F15: =IF($E15="","",$D15*$E15) | G15: 3 | H15: =IF(OR($E15="",$G15=""),"",$E15-$G15)
A16: 2S Ranger | B16: 4 | C16: Stock au poste borné visuellement (mini / maxi) | D16: 2 | E16: 2 | F16: =IF($E16="","",$D16*$E16) | G16: 1 | H16: =IF(OR($E16="",$G16=""),"",$E16-$G16)
A17: 2S Ranger | B17: 5 | C17: Un nouvel arrivant trouve un outil en moins de 30 secondes | D17: 2 | E17: 2 | F17: =IF($E17="","",$D17*$E17) | G17: 2 | H17: =IF(OR($E17="",$G17=""),"",$E17-$G17)
A18: 3S Nettoyer | B18: 1 | C18: Sols, machines et postes propres en fin de poste | D18: 2 | E18: 3 | F18: =IF($E18="","",$D18*$E18) | G18: 3 | H18: =IF(OR($E18="",$G18=""),"",$E18-$G18)
A19: 3S Nettoyer | B19: 2 | C19: Aucune fuite (huile, air, fluide) non traitée ou non signalée | D19: 3 | E19: 3 | F19: =IF($E19="","",$D19*$E19) | G19: 2 | H19: =IF(OR($E19="",$G19=""),"",$E19-$G19)
... A32: 5S Progresser | B32: 5 | C32: Le management reconnaît les progrès sur le terrain | D32: 1 | E32: 3 | F32: =IF($E32="","",$D32*$E32) | G32: 3 | H32: =IF(OR($E32="",$G32=""),"",$E32-$G32)
A33: RÉSULTAT DE L'AUDIT — score pondéré par domaine
A34: Domaine 5S | B34: Note pondérée obtenue | C34: Note pondérée maximale | D34: Score | E34: Cible | F34: Écart | G34: Statut | H34: Score audit N-1 | I34: Tendance
A35: 1S Débarrasser | B35: =SUMIF($A$8:$A$32,$A35,$F$8:$F$32) | C35: =SUMIF($A$8:$A$32,$A35,$D$8:$D$32)*4 | D35: =IFERROR($B35/$C35,"") | E35: =INDEX(PARAMETRES!$D$16:$D$29,MATCH("AUDIT5S",PARAMETRES!$A$16:$A$29,0)) | F35: =IF($D35="","",$D35-$E35) | G35: =IF($D35="","",IF($D35>=$E35,"Conforme",IF($D35>=$E35-0.1,"À consolider","Non conforme"))) | H35: =IFERROR(SUMPRODUCT(($A$8:$A$32=$A35)*$D$8:$D$32*$G$8:$G$32)/$C35,"") | I35: =IF(OR($D35="",$H35=""),"",IF($D35>$H35+0.02,"En progrès",IF($D35<$H35-0.02,"En recul","Stable")))
A36: 2S Ranger | B36: =SUMIF($A$8:$A$32,$A36,$F$8:$F$32) | C36: =SUMIF($A$8:$A$32,$A36,$D$8:$D$32)*4 | D36: =IFERROR($B36/$C36,"") | E36: =INDEX(PARAMETRES!$D$16:$D$29,MATCH("AUDIT5S",PARAMETRES!$A$16:$A$29,0)) | F36: =IF($D36="","",$D36-$E36) | G36: =IF($D36="","",IF($D36>=$E36,"Conforme",IF($D36>=$E36-0.1,"À consolider","Non conforme"))) | H36: =IFERROR(SUMPRODUCT(($A$8:$A$32=$A36)*$D$8:$D$32*$G$8:$G$32)/$C36,"") | I36: =IF(OR($D36="",$H36=""),"",IF($D36>$H36+0.02,"En progrès",IF($D36<$H36-0.02,"En recul","Stable")))
A37: 3S Nettoyer | B37: =SUMIF($A$8:$A$32,$A37,$F$8:$F$32) | C37: =SUMIF($A$8:$A$32,$A37,$D$8:$D$32)*4 | D37: =IFERROR($B37/$C37,"") | E37: =INDEX(PARAMETRES!$D$16:$D$29,MATCH("AUDIT5S",PARAMETRES!$A$16:$A$29,0)) | F37: =IF($D37="","",$D37-$E37) | G37: =IF($D37="","",IF($D37>=$E37,"Conforme",IF($D37>=$E37-0.1,"À consolider","Non conforme"))) | H37: =IFERROR(SUMPRODUCT(($A$8:$A$32=$A37)*$D$8:$D$32*$G$8:$G$32)/$C37,"") | I37: =IF(OR($D37="",$H37=""),"",IF($D37>$H37+0.02,"En progrès",IF($D37<$H37-0.02,"En recul","Stable")))
A38: 4S Standardiser | B38: =SUMIF($A$8:$A$32,$A38,$F$8:$F$32) | C38: =SUMIF($A$8:$A$32,$A38,$D$8:$D$32)*4 | D38: =IFERROR($B38/$C38,"") | E38: =INDEX(PARAMETRES!$D$16:$D$29,MATCH("AUDIT5S",PARAMETRES!$A$16:$A$29,0)) | F38: =IF($D38="","",$D38-$E38) | G38: =IF($D38="","",IF($D38>=$E38,"Conforme",IF($D38>=$E38-0.1,"À consolider","Non conforme"))) | H38: =IFERROR(SUMPRODUCT(($A$8:$A$32=$A38)*$D$8:$D$32*$G$8:$G$32)/$C38,"") | I38: =IF(OR($D38="",$H38=""),"",IF($D38>$H38+0.02,"En progrès",IF($D38<$H38-0.02,"En recul","Stable")))
A39: 5S Progresser | B39: =SUMIF($A$8:$A$32,$A39,$F$8:$F$32) | C39: =SUMIF($A$8:$A$32,$A39,$D$8:$D$32)*4 | D39: =IFERROR($B39/$C39,"") | E39: =INDEX(PARAMETRES!$D$16:$D$29,MATCH("AUDIT5S",PARAMETRES!$A$16:$A$29,0)) | F39: =IF($D39="","",$D39-$E39) | G39: =IF($D39="","",IF($D39>=$E39,"Conforme",IF($D39>=$E39-0.1,"À consolider","Non conforme"))) | H39: =IFERROR(SUMPRODUCT(($A$8:$A$32=$A39)*$D$8:$D$32*$G$8:$G$32)/$C39,"") | I39: =IF(OR($D39="",$H39=""),"",IF($D39>$H39+0.02,"En progrès",IF($D39<$H39-0.02,"En recul","Stable")))
A40: SCORE GLOBAL | B40: =SUM($B$35:$B$39) | C40: =SUM($C$35:$C$39) | D40: =IFERROR($B40/$C40,"") | E40: =INDEX(PARAMETRES!$D$16:$D$29,MATCH("AUDIT5S",PARAMETRES!$A$16:$A$29,0)) | F40: =IF($D40="","",$D40-$E40) | G40: =IF($D40="","",IF($D40>=$E40,"Conforme",IF($D40>=$E40-0.1,"À consolider","Non conforme"))) | H40: =IFERROR(SUMPRODUCT($D$8:$D$32,$G$8:$G$32)/($C40),"") | I40: =IF(OR($D40="",$H40=""),"",IF($D40>$H40+0.02,"En progrès",IF($D40<$H40-0.02,"En recul","Stable")))
A43: HISTORIQUE DES AUDITS DE LA ZONE — à compléter à chaque passage
A44: Date de l'audit | B44: Zone | C44: Score global | D44: Actions ouvertes | E44: Actions soldées | F44: Auditeur
A45: 45926 | B45: Ligne 1 - Assemblage | C45: 0.52 | D45: 8 | E45: 5 | F45: LEROY S.
A46: 45954 | B46: Ligne 1 - Assemblage | C46: 0.58 | D46: 7 | E46: 6 | F46: LEROY S.
A47: 45982 | B47: Ligne 1 - Assemblage | C47: 0.61 | D47: 6 | E47: 5 | F47: DURAND M.
A48: 46010 | B48: Ligne 1 - Assemblage | C48: 0.63 | D48: 6 | E48: 4 | F48: LEROY S.
A49: =$F$5 | B49: =$C$5 | C49: =$D$40

Sheet PRISE_DE_POSTE
A1: STANDARD DE PRISE DE POSTE ET DE PASSATION
A2: Document à imprimer et à tenir à chaque changement d'équipe. Les points bloquants doivent être soldés avant le lancement de la série. Structure SQCDP : Sécurité, Qualité, Coût, Délai, Personnel.
A4: IDENTIFICATION DU POSTE
A5: Date : | B5: 46052 | C5: Ligne / zone : | D5: Ligne 1 - Assemblage | F5: Équipe sortante : | G5: Équipe A (matin) | I5: Superviseur sortant : | J5: DURAND M.
A6: Heure : | B6: 0.5625 | C6: Effectif présent / prévu : | D6: 11 / 12 | F6: Équipe entrante : | G6: Équipe B (après-midi) | I6: Superviseur entrant : | J6: MARCHAND J.
A7: Séquence | B7: Jalon | C7: Axe SQCDP | D7: Point de contrôle | E7: Bloquant | F7: Statut | G7: Constat / observation | H7: Action immédiate | I7: Pilote | J7: Délai
A8: 1. Avant la prise de poste | B8: T-20 min | C8: Délai | D8: Lire la passation écrite du poste précédent et le carnet de consignes | E8: Oui
A9: 1. Avant la prise de poste | B9: T-20 min | C9: Délai | D9: Vérifier le programme du jour, les priorités clients et les urgences | E9: Oui
A10: 1. Avant la prise de poste | B10: T-15 min | C10: Personnel | D10: Contrôler l'effectif présent et couvrir les absences (matrice de polyvalence) | E10: Oui
A11: 1. Avant la prise de poste | B11: T-15 min | C11: Qualité | D11: Vérifier la disponibilité matière, outillage et moyens de contrôle | E11: Oui
A12: 1. Avant la prise de poste | B12: T-10 min | C12: Délai | D12: Vérifier les interventions de maintenance planifiées sur le poste | E12: Non
A13: 2. Passation croisée | B13: T-10 min | C13: Sécurité | D13: Passation orale avec le superviseur sortant (5 min, sur le terrain) | E13: Oui
A14: 2. Passation croisée | B14: T-5 min | C14: Qualité | D14: Faire le point sur les aléas non résolus et les dérogations en cours | E14: Oui
A15: 3. Animation 5 minutes | B15: T0 | C15: Sécurité | D15: Point sécurité : accident, presqu'accident, situation dangereuse de la veille | E15: Oui
A16: 3. Animation 5 minutes | B16: T0 | C16: Qualité | D16: Résultat de la veille : TRS, qualité, service — écart et cause principale | E16: Oui
A17: 3. Animation 5 minutes | B17: T0 | C17: Délai | D17: Objectif du jour chiffré et affectation nominative aux postes | E17: Oui
A18: 3. Animation 5 minutes | B18: T0 | C18: Personnel | D18: Annoncer les aléas connus et les besoins d'entraide | E18: Non
A19: 4. Démarrage | B19: T+10 min | C19: Sécurité | D19: Contrôler le port des EPI et l'état des protections machines | E19: Oui
... A32: 6. Fin de poste | B32: T-10 min | C32: Délai | D32: Rédiger la passation écrite ci-dessous et la faire viser | E32: Oui
A33: BILAN DE LA PRISE DE POSTE
A34: Taux de conformité du standard | E34: =IFERROR(COUNTIF($F$8:$F$32,"OK")/(COUNTIF($F$8:$F$32,"OK")+COUNTIF($F$8:$F$32,"NOK")),"")
A35: Points de contrôle non conformes | E35: =COUNTIF($F$8:$F$32,"NOK")
A36: Dont points bloquants non soldés | E36: =COUNTIFS($E$8:$E$32,"Oui",$F$8:$F$32,"NOK")
A37: Décision de lancement | E37: =IF(COUNTIF($F$8:$F$32,"OK")+COUNTIF($F$8:$F$32,"NOK")+COUNTIF($F$8:$F$32,"S.O.")=0,"Contrôles non réalisés",IF(COUNTIFS($E$8:$E$32,"Oui",$F$8:$F$32,"NOK")>0,"LANCEMENT INTERDIT — solder les points bloquants","Lancement autorisé"))
A40: PASSATION ÉCRITE À L'ÉQUIPE SUIVANTE
A41: En-cours, état des lignes et avancement des OF
A42: Aléas non résolus et actions engagées
A43: Consignes particulières (client, qualité, sécurité, dérogation)
A44: Points de vigilance pour le poste suivant
A45: Interventions de maintenance en cours ou attendues
A48: MATRICE D'ESCALADE — qui alerter, dans quel délai
A49: Niveau | B49: Situation déclenchante | C49: Délai de réaction | D49: Interlocuteur | E49: Moyen d'alerte | F49: Trace obligatoire
A50: Niveau 1 | B50: Arrêt ou écart traité par l'équipe au poste | C50: Immédiat | D50: Opérateur et chef d'équipe | E50: Face à face au poste | F50: Onglet ARRÊTS
A51: Niveau 2 | B51: Arrêt supérieur à 15 min ou écart qualité interne | C51: Sous 15 min | D51: Superviseur de production | E51: Appel radio / téléphone | F51: Onglet ARRÊTS + PLAN_ACTIONS
A52: Niveau 3 | B52: Arrêt supérieur à 60 min, non-conformité client, risque de rupture | C52: Sous 30 min | D52: Responsable de production et qualité | E52: Appel + message écrit | F52: PLAN_ACTIONS (criticité ≥ 30)
A53: Niveau 4 | B53: Accident avec arrêt, arrêt de ligne supérieur à 4 h, arrêt client | C53: Immédiat | D53: Direction de site et HSE | E53: Appel direct | F53: Analyse d'accident / 8D
A55: VISA DE PASSATION
A56: Superviseur sortant (nom et visa) | F56: Superviseur entrant (nom et visa)

Sheet PARAMETRES
A1: PARAMÈTRES ET RÉFÉRENTIELS DU SITE
A2: Source unique de vérité du classeur : objectifs, listes de choix et données de référence. Toute modification se répercute automatiquement sur les onglets de saisie et le cockpit.
A4: 1. IDENTIFICATION DE L'ENTITÉ PILOTÉE | I4: 3. RÉFÉRENTIELS DE SAISIE — alimentent les listes déroulantes de tous les onglets
A5: Site / usine | C5: Site de démonstration | F5: Texte libre — figure dans l'en-tête du cockpit | I5: Organisation | M5: Produits et cadences nominales | R5: Causes d'arrêt normalisées | X5: Postes de travail (polyvalence) | AB5: Listes de choix normalisées
A6: Atelier / UAP | C6: UAP Assemblage-Usinage | F6: Périmètre couvert par ce classeur | I6: Lignes / ressources | J6: Équipes (postes) | K6: Pilotes et animateurs | M6: Référence | N6: Désignation | O6: Cadence nominale (pcs/min) | P6: PPM cible | R6: Code | S6: Libellé | T6: Famille 5M | U6: Type | V6: Rubrique de saisie | X6: Poste de travail | Y6: Criticité (1 à 3) | Z6: Effectif autonome cible | AB6: Familles 5M | AC6: Sources d'écart | AD6: Nature d'action | AE6: Statut d'action | AF6: Efficacité | AG6: Oui / Non | AH6: Contrôle terrain | AI6: Axes SQCDP | AJ6: Filtre lignes | AK6: Filtre équipes | AL6: Rubriques de perte | AM6: Mois
A7: Responsable de production | C7: À compléter | I7: Ligne 1 - Assemblage | J7: Équipe A (matin) | K7: DURAND M. | M7: REF-1001 | N7: Carter aluminium A20 | O7: 15 | P7: 2000 | R7: PLA-01 | S7: Pause légale et relève de poste | T7: Milieu | U7: Planifié | V7: Arrêts planifiés | X7: Conduite ligne 1 | Y7: 3 | Z7: 3 | AB7: Machine | AC7: Écart quotidien | AD7: Curative (D3) | AE7: À lancer | AF7: Oui | AG7: Oui | AH7: OK | AI7: Sécurité | AJ7: Toutes | AK7: Toutes | AL7: Arrêts planifiés | AM7: Janvier
A8: Superviseur référent | C8: À compléter | I8: Ligne 2 - Usinage | J8: Équipe B (après-midi) | K8: NGOM A. | M8: REF-1002 | N8: Carter aluminium A30 | O8: 12.5 | P8: 2000 | R8: PLA-02 | S8: Maintenance préventive planifiée | T8: Machine | U8: Planifié | V8: Arrêts planifiés | X8: Conduite ligne 2 | Y8: 3 | Z8: 3 | AB8: Main d'œuvre | AC8: Sécurité | AD8: Corrective (D5) | AE8: En cours | AF8: Non | AG8: Non | AH8: NOK | AI8: Qualité | AJ8: Ligne 1 - Assemblage | AK8: Équipe A (matin) | AL8: Pannes | AM8: Février
A9: Nombre d'équipes par jour | C9: 2 | F9: Sert au dimensionnement des ressources | I9: Ligne 3 - Conditionnement | J9: Équipe C (nuit) | K9: LEROY S. | M9: REF-2001 | N9: Support moteur S12 | O9: 9 | P9: 1500 | R9: PLA-03 | S9: Réunion, formation ou audit planifié | T9: Main d'œuvre | U9: Planifié | V9: Arrêts planifiés | X9: Conduite ligne 3 | Y9: 2 | Z9: 2 | AB9: Matière | AC9: Qualité client | AD9: Préventive (D7) | AE9: En attente | AF9: En attente | AG9: S.O. | AH9: S.O. | AI9: Coût | AJ9: Ligne 2 - Usinage | AK9: Équipe B (après-midi) | AL9: Changement de série | AM9: Mars
A10: Temps d'ouverture théorique par poste (min) | C10: 480 | F10: Valeur par défaut proposée à la saisie | K10: BAKARI F. | M10: REF-2002 | N10: Support moteur S18 | O10: 7.5 | P10: 1500 | R10: PAN-01 | S10: Panne mécanique | T10: Machine | U10: Subi | V10: Pannes | X10: Changement de série | Y10: 3 | Z10: 3 | AB10: Méthode | AC10: Analyse Pareto TRS | AD10: Amélioration | AE10: Terminée | AI10: Délai | AJ10: Ligne 3 - Conditionnement | AK10: Équipe C (nuit) | AL10: Réglages et micro-arrêts | AM10: Avril
A11: Jours ouvrés de référence par mois | C11: 21 | F11: Base de calcul des ratios mensuels | K11: PETIT C. | M11: REF-3001 | N11: Kit conditionné K4 | O11: 22 | P11: 3000 | R11: PAN-02 | S11: Panne électrique ou capteur | T11: Machine | U11: Subi | V11: Pannes | X11: Contrôle qualité | Y11: 3 | Z11: 3 | AB11: Milieu | AC11: Audit 5S | AE11: Abandonnée | AI11: Personnel | AL11: Manque matière | AM11: Mai
A12: Devise de valorisation | C12: EUR | F12: Gains du plan d'actions | K12: MARCHAND J. | R12: PAN-03 | S12: Défaut automatisme / supervision | T12: Machine | U12: Subi | V12: Pannes | X12: Retouche | Y12: 2 | Z12: 2 | AC12: Idée opérateur | AL12: Manque personnel | AM12: Juin
K13: SOW I. | R13: CDS-01 | S13: Changement de série (outillage) | T13: Méthode | U13: Subi | V13: Changement de série | X13: Maintenance 1er niveau | Y13: 3 | Z13: 2 | AC13: Réclamation client | AL13: Autres arrêts subis | AM13: Juillet
A14: 2. OBJECTIFS ET SEUILS D'ALERTE — contrat de performance | K14: GARNIER L. | R14: CDS-02 | S14: Attente outillage ou moyen de contrôle | T14: Méthode | U14: Subi | V14: Changement de série | X14: Cariste / appro | Y14: 2 | Z14: 2 | AC14: Audit interne | AM14: Août
A15: Code | B15: Indicateur | C15: Unité | D15: Cible | E15: Seuil d'alerte | F15: Sens | G15: Origine de l'objectif | R15: REG-01 | S15: Réglage qualité en cours de série | T15: Méthode | U15: Subi | V15: Réglages et micro-arrêts | X15: Emballage | Y15: 1 | Z15: 2 | AM15: Septembre
A16: TRS | B16: Taux de rendement synthétique (TRS / OEE) | C16: % | D16: 0.75 | E16: 0.7 | F16: 1 | G16: Objectif budget 2026 — direction industrielle | R16: REG-02 | S16: Micro-arrêts, bourrage, purge | T16: Machine | U16: Subi | V16: Réglages et micro-arrêts | X16: Saisie et reporting | Y16: 2 | Z16: 2 | AM16: Octobre
A17: DISPO | B17: Taux de disponibilité | C17: % | D17: 0.9 | E17: 0.85 | F17: 1 | G17: Dérivé de l'objectif TRS | R17: MAT-01 | S17: Rupture d'approvisionnement matière | T17: Matière | U17: Subi | V17: Manque matière | X17: Animation 5 min | Y17: 2 | Z17: 2 | AM17: Novembre
A18: PERF | B18: Taux de performance (cadence) | C18: % | D18: 0.95 | E18: 0.9 | F18: 1 | G18: Dérivé de l'objectif TRS | R18: MAT-02 | S18: Matière non conforme (rebut fournisseur) | T18: Matière | U18: Subi | V18: Manque matière | X18: Formation nouveaux | Y18: 1 | Z18: 2 | AM18: Décembre
A19: QUAL | B19: Taux de qualité au premier passage (RFT) | C19: % | D19: 0.99 | E19: 0.98 | F19: 1 | G19: Engagement client / plan qualité | R19: PER-01 | S19: Absence non remplacée | T19: Main d'œuvre | U19: Subi | V19: Manque personnel
A20: TRG | B20: Taux de rendement global (TRG) | C20: % | D20: 0.6 | E20: 0.55 | F20: 1 | G20: Suivi capacitaire | R20: PER-02 | S20: Accompagnement / montée en compétence | T20: Main d'œuvre | U20: Subi | V20: Manque personnel
A21: SERVICE | B21: Taux de service (quantité programmée) | C21: % | D21: 0.95 | E21: 0.9 | F21: 1 | G21: Contrat de service logistique | R21: LOG-01 | S21: Attente cariste / évacuation en-cours | T21: Milieu | U21: Subi | V21: Autres arrêts subis
A22: PPM | B22: Non-conformités internes | C22: ppm | D22: 2000 | E22: 5000 | F22: -1 | G22: Plan qualité 2026 | R22: LOG-02 | S22: Saturation aval / stock plein | T22: Milieu | U22: Subi | V22: Autres arrêts subis
A23: PRESENCE | B23: Taux de présence | C23: % | D23: 0.95 | E23: 0.92 | F23: 1 | G23: Ressources humaines | R23: ESS-01 | S23: Essai, prototype, série pilote | T23: Méthode | U23: Subi | V23: Autres arrêts subis
A24: ACCIDENT | B24: Accidents avec arrêt (cumul mois) | C24: nb | D24: 0 | E24: 0 | F24: -1 | G24: Politique santé-sécurité
A25: RETARD | B25: Actions correctives en retard | C25: nb | D25: 0 | E25: 2 | F25: -1 | G25: Règle d'animation QRQC
A26: MTTR | B26: Temps moyen de réparation (MTTR) | C26: min | D26: 30 | E26: 45 | F26: -1 | G26: Contrat de maintenance
A27: MTBF | B27: Temps moyen entre pannes (MTBF) | C27: min | D27: 240 | E27: 180 | F27: 1 | G27: Contrat de maintenance
A28: AUDIT5S | B28: Score d'audit 5S | C28: % | D28: 0.8 | E28: 0.7 | F28: 1 | G28: Standard 5S du site
A29: POLYV | B29: Taux de polyvalence de l'équipe | C29: % | D29: 0.7 | E29: 0.6 | F29: 1 | G29: Plan de compétences
A31: Sens de lecture : 1 = la performance s'améliore quand la valeur augmente • -1 = la performance s'améliore quand la valeur diminue. Le cockpit compare automatiquement la valeur du mois à la cible (vert), au seuil d'alerte (orange) puis au-delà (rouge).

Sheet GLOSSAIRE
A1: GLOSSAIRE DES INDICATEURS ET RÈGLES DE GESTION
A2: Définition, formule appliquée et interprétation de chaque indicateur produit par le classeur. Document de référence pour l'harmonisation des calculs entre ateliers.
A4: 1. INDICATEURS DE PERFORMANCE
A5: Indicateur | B5: Intitulé complet | C5: Formule appliquée | D5: Unité | E5: Données sources | F5: Interprétation et limites | G5: Référence
A6: TRS | B6: Taux de rendement synthétique (OEE) | C6: Disponibilité × Performance × Qualité, soit Temps utile ÷ Temps requis | D6: % | E6: SAISIE_PROD colonnes AB, AE | F6: Part du temps requis réellement transformée en production bonne. Indicateur de synthèse de la performance d'un moyen. | G6: NF E60-182
A7: Disponibilité | B7: Taux de disponibilité opérationnelle | C7: Temps de marche ÷ Temps requis | D7: % | E7: SAISIE_PROD colonnes AD, AB | F7: Mesure les arrêts subis. Un écart signale des pannes, des changements de série longs ou des ruptures d'approvisionnement. | G7: NF E60-182
A8: Performance | B8: Taux de performance ou tenue de cadence | C8: (Quantité produite ÷ Cadence nominale) ÷ Temps de marche | D8: % | E8: SAISIE_PROD colonnes P, O, AD | F8: Mesure les pertes de vitesse et les micro-arrêts non déclarés. Dépend de la fiabilité de la cadence nominale du référentiel. | G8: NF E60-182
A9: Qualité RFT | B9: Taux de qualité au premier passage (Right First Time) | C9: Quantité conforme au premier passage ÷ Quantité produite | D9: % | E9: SAISIE_PROD colonnes Q, P | F9: Exclut volontairement les pièces retouchées : une retouche consomme du temps et masque un défaut de procédé. | G9: IATF 16949 §9.1
A10: TRG | B10: Taux de rendement global | C10: Temps utile ÷ Temps d'ouverture | D10: % | E10: SAISIE_PROD colonnes AE, F | F10: Intègre les arrêts planifiés. Indicateur de capacité : il répond à la question « que puis-je encore charger ? ». | G10: NF E60-182
A11: Taux de service | B11: Respect du programme de production | C11: (Conforme + Retouché) ÷ Quantité demandée | D11: % | E11: SAISIE_PROD colonnes Q, R, T | F11: Mesure la tenue de l'engagement logistique. À distinguer du TRS : une ligne peut être performante et servir en retard. | G11: Contrat de service interne
A12: PPM | B12: Non-conformités internes en parties par million | C12: (Produite − Conforme) ÷ Produite × 1 000 000 | D12: ppm | E12: SAISIE_PROD colonnes P, Q | F12: Unité de référence des plans qualité. Permet de comparer des volumes de production hétérogènes. | G12: IATF 16949
A13: MTBF | B13: Temps moyen de bon fonctionnement entre deux pannes | C13: Temps de marche ÷ Nombre de pannes | D13: min | E13: SAISIE_PROD colonnes AD, N | F13: Mesure la fiabilité du moyen. Un MTBF qui se dégrade annonce une défaillance de fond avant qu'elle ne devienne bloquante. | G13: NF EN 13306
A14: MTTR | B14: Temps moyen de réparation | C14: Minutes de panne ÷ Nombre de pannes | D14: min | E14: SAISIE_PROD colonnes H, N | F14: Mesure la maintenabilité et la réactivité de la maintenance : diagnostic, pièces de rechange, procédure d'intervention. | G14: NF EN 13306
A15: Taux de présence | B15: Présentéisme de l'effectif de production | C15: Effectif présent ÷ Effectif prévu | D15: % | E15: SAISIE_PROD colonnes V, U | F15: Contextualise les pertes de temps liées au manque de personnel et le recours aux heures supplémentaires. | G15: Suivi RH
A16: Criticité (IPR) | B16: Indice de priorité du risque d'une action | C16: Gravité × Fréquence × Détection (échelle 1 à 5) | D16: sans unité | E16: PLAN_ACTIONS colonnes F, G, H | F16: Hiérarchise les actions. Un IPR ≥ 30 impose un traitement prioritaire et une vérification d'efficacité tracée. | G16: Méthode AMDEC
... A21: Limites de contrôle | B21: Bornes de variation courante du procédé | C21: Moyenne des TRS journaliers ± 2 écarts-types | D21: % | E21: CALC colonnes V4 à V7 | F21: Un point hors limite signale une cause spéciale à investiguer ; à l'intérieur, la variation est courante et ne justifie pas de réaction ponctuelle. | G21: Maîtrise statistique des procédés
A23: 2. CASCADE DES TEMPS — décomposition normalisée
A24: Temps d'ouverture (TO) | C24: Temps pendant lequel le moyen est mis à disposition de la production.
A25: − Arrêts planifiés | C25: Pauses légales, maintenance préventive planifiée, réunions et formations programmées.
A26: = Temps requis (TR) | C26: Temps pendant lequel la production est attendue. Dénominateur du TRS.
A27: − Arrêts subis | C27: Pannes, changements de série, réglages et micro-arrêts, manque matière, manque personnel, autres aléas.
A28: = Temps de marche (TF) | C28: Temps pendant lequel le moyen produit effectivement. TF ÷ TR = disponibilité.
A29: − Perte de cadence | C29: Écart entre la production réelle et la production théorique à la cadence nominale.
A30: − Pertes de non-qualité | C30: Temps consommé à produire les pièces non conformes au premier passage.
A31: = Temps utile (TU) | C31: Temps équivalent de production bonne à cadence nominale. TU ÷ TR = TRS.
A33: 3. RÈGLES DE GESTION DU CLASSEUR
A34: Unité de temps | C34: Toutes les durées sont saisies en minutes entières. Le classeur ne convertit pas les heures.
A35: Granularité | C35: Une ligne de SAISIE_PROD par couple (jour, ligne, équipe). Un enregistrement de ARRETS par arrêt élémentaire.
A36: Cohérence des quantités | C36: Quantité produite = conforme au premier passage + retouchée + rebutée. La colonne de contrôle de SAISIE_PROD signale tout écart.
A37: Cohérence des temps | C37: Temps d'ouverture = arrêts planifiés + arrêts subis + temps de marche. La somme des arrêts ne peut pas dépasser le temps requis.
A38: Arrêts planifiés | C38: Pauses, maintenance préventive et réunions planifiées sont exclues du temps requis : elles n'affectent pas le TRS mais pèsent sur le TRG.
A39: Cadence nominale | C39: Elle provient du référentiel produits et non d'une saisie de poste : c'est la référence contractuelle qui rend les taux de performance comparables entre eux.
A40: Arrêt de nuit | C40: Un arrêt dont l'heure de fin est antérieure à l'heure de début est traité comme un franchissement de minuit.
A41: Périmètre du cockpit | C41: Les filtres Ligne et Équipe s'appliquent aux cartes d'indicateurs, au suivi journalier, au Pareto, à la cascade des pertes et à l'historique. Les graphiques de comparaison « TRS par ligne » et « TRS par équipe » restent volontairement hors filtre pour permettre la comparaison ; le plan d'actions et l'audit 5S sont suivis globalement.
A42: Historique | C42: Le classeur conserve 200 lignes de saisie et 400 arrêts, soit environ 5 mois d'exploitation sur deux lignes. Au-delà, archiver une copie du fichier par exercice.
A43: Confidentialité | C43: La matrice de polyvalence contient des données nominatives : en restreindre la diffusion au responsable de production et à la fonction RH.

Sheet CALC
A1: MOTEUR DE CALCUL — feuille technique, ne pas modifier
A2: Cette feuille agrège les données de saisie selon les filtres du cockpit et alimente l'ensemble des graphiques. Toute modification manuelle fausse le tableau de bord. | U2: REPÈRES STATISTIQUES (colonne V)
A3: Année | B3: =COCKPIT!$B$4 | U3: Cible TRS | V3: =INDEX(PARAMETRES!$D$16:$D$29,MATCH("TRS",PARAMETRES!$A$16:$A$29,0))
A4: Mois | B4: =COCKPIT!$D$4 | U4: Moyenne des TRS journaliers | V4: =IFERROR(AVERAGE($M$12:$M$42),"")
A5: Ligne | B5: =COCKPIT!$H$4 | U5: Écart-type des TRS journaliers | V5: =IFERROR(STDEV($M$12:$M$42),"")
A6: Équipe | B6: =COCKPIT!$K$4 | U6: Limite de contrôle supérieure (moy. + 2σ) | V6: =IFERROR(MIN(1,$V$4+2*$V$5),"")
A7: Début de période | B7: =DATE($B$3,$B$4,1) | U7: Limite de contrôle inférieure (moy. - 2σ) | V7: =IFERROR(MAX(0,$V$4-2*$V$5),"")
A8: Fin de période | B8: =EOMONTH($B$7,0) | U8: Temps d'ouverture TO (min) | V8: =SUMIFS(SAISIE_PROD!$F$5:$F$204,SAISIE_PROD!$A$5:$A$204,">="&$B$7,SAISIE_PROD!$A$5:$A$204,"<="&$B$8,SAISIE_PROD!$AS$5:$AS$204,1)
A9: Jours de production saisis | B9: =COUNT($M$12:$M$42) | U9: Arrêts planifiés (min) | V9: =SUMIFS(SAISIE_PROD!$G$5:$G$204,SAISIE_PROD!$A$5:$A$204,">="&$B$7,SAISIE_PROD!$A$5:$A$204,"<="&$B$8,SAISIE_PROD!$AS$5:$AS$204,1)
A10: SÉRIE JOURNALIÈRE DU MOIS SÉLECTIONNÉ | U10: Pannes (min) | V10: =SUMIFS(SAISIE_PROD!$H$5:$H$204,SAISIE_PROD!$A$5:$A$204,">="&$B$7,SAISIE_PROD!$A$5:$A$204,"<="&$B$8,SAISIE_PROD!$AS$5:$AS$204,1)
A11: Jour | B11: Date | C11: Temps utile | D11: Temps requis | E11: Temps de marche | F11: Temps d'ouverture | G11: Qté produite | H11: Qté conforme | I11: Qté retouchée | J11: Qté demandée | K11: Accidents | L11: Arrêts subis | M11: TRS | N11: Cible | O11: Moyenne mobile 7 j | P11: LCS | Q11: LCI | R11: TRS (graphique) | S11: Moyenne mobile (graphique) | U11: Changement de série (min) | V11: =SUMIFS(SAISIE_PROD!$I$5:$I$204,SAISIE_PROD!$A$5:$A$204,">="&$B$7,SAISIE_PROD!$A$5:$A$204,"<="&$B$8,SAISIE_PROD!$AS$5:$AS$204,1)
A12: 1 | B12: =IF($A12>DAY($B$8),"",DATE($B$3,$B$4,$A12)) | C12: =IF($B12="","",SUMIFS(SAISIE_PROD!$AE$5:$AE$204,SAISIE_PROD!$A$5:$A$204,$B12,SAISIE_PROD!$AS$5:$AS$204,1)) | D12: =IF($B12="","",SUMIFS(SAISIE_PROD!$AB$5:$AB$204,SAISIE_PROD!$A$5:$A$204,$B12,SAISIE_PROD!$AS$5:$AS$204,1)) | E12: =IF($B12="","",SUMIFS(SAISIE_PROD!$AD$5:$AD$204,SAISIE_PROD!$A$5:$A$204,$B12,SAISIE_PROD!$AS$5:$AS$204,1)) | F12: =IF($B12="","",SUMIFS(SAISIE_PROD!$F$5:$F$204,SAISIE_PROD!$A$5:$A$204,$B12,SAISIE_PROD!$AS$5:$AS$204,1)) | G12: =IF($B12="","",SUMIFS(SAISIE_PROD!$P$5:$P$204,SAISIE_PROD!$A$5:$A$204,$B12,SAISIE_PROD!$AS$5:$AS$204,1)) | H12: =IF($B12="","",SUMIFS(SAISIE_PROD!$Q$5:$Q$204,SAISIE_PROD!$A$5:$A$204,$B12,SAISIE_PROD!$AS$5:$AS$204,1)) | I12: =IF($B12="","",SUMIFS(SAISIE_PROD!$R$5:$R$204,SAISIE_PROD!$A$5:$A$204,$B12,SAISIE_PROD!$AS$5:$AS$204,1)) | J12: =IF($B12="","",SUMIFS(SAISIE_PROD!$T$5:$T$204,SAISIE_PROD!$A$5:$A$204,$B12,SAISIE_PROD!$AS$5:$AS$204,1)) | K12: =IF($B12="","",SUMIFS(SAISIE_PROD!$X$5:$X$204,SAISIE_PROD!$A$5:$A$204,$B12,SAISIE_PROD!$AS$5:$AS$204,1)) | L12: =IF($B12="","",SUMIFS(SAISIE_PROD!$AC$5:$AC$204,SAISIE_PROD!$A$5:$A$204,$B12,SAISIE_PROD!$AS$5:$AS$204,1)) | M12: =IF(OR($B12="",$D12=0),"",$C12/$D12) | N12: =IF($B12="",NA(),$V$3) | O12: =IF(COUNT($M12:$M12)<3,"",AVERAGE($M12:$M12)) | P12: =IF(OR($B12="",$V$5=""),NA(),$V$6) | Q12: =IF(OR($B12="",$V$5=""),NA(),$V$7) | R12: =IF($M12="",NA(),$M12) | S12: =IF($O12="",NA(),$O12) | U12: Réglages et micro-arrêts (min) | V12: =SUMIFS(SAISIE_PROD!$J$5:$J$204,SAISIE_PROD!$A$5:$A$204,">="&$B$7,SAISIE_PROD!$A$5:$A$204,"<="&$B$8,SAISIE_PROD!$AS$5:$AS$204,1)
A13: 2 | B13: =IF($A13>DAY($B$8),"",DATE($B$3,$B$4,$A13)) | C13: =IF($B13="","",SUMIFS(SAISIE_PROD!$AE$5:$AE$204,SAISIE_PROD!$A$5:$A$204,$B13,SAISIE_PROD!$AS$5:$AS$204,1)) | D13: =IF($B13="","",SUMIFS(SAISIE_PROD!$AB$5:$AB$204,SAISIE_PROD!$A$5:$A$204,$B13,SAISIE_PROD!$AS$5:$AS$204,1)) | E13: =IF($B13="","",SUMIFS(SAISIE_PROD!$AD$5:$AD$204,SAISIE_PROD!$A$5:$A$204,$B13,SAISIE_PROD!$AS$5:$AS$204,1)) | F13: =IF($B13="","",SUMIFS(SAISIE_PROD!$F$5:$F$204,SAISIE_PROD!$A$5:$A$204,$B13,SAISIE_PROD!$AS$5:$AS$204,1)) | G13: =IF($B13="","",SUMIFS(SAISIE_PROD!$P$5:$P$204,SAISIE_PROD!$A$5:$A$204,$B13,SAISIE_PROD!$AS$5:$AS$204,1)) | H13: =IF($B13="","",SUMIFS(SAISIE_PROD!$Q$5:$Q$204,SAISIE_PROD!$A$5:$A$204,$B13,SAISIE_PROD!$AS$5:$AS$204,1)) | I13: =IF($B13="","",SUMIFS(SAISIE_PROD!$R$5:$R$204,SAISIE_PROD!$A$5:$A$204,$B13,SAISIE_PROD!$AS$5:$AS$204,1)) | J13: =IF($B13="","",SUMIFS(SAISIE_PROD!$T$5:$T$204,SAISIE_PROD!$A$5:$A$204,$B13,SAISIE_PROD!$AS$5:$AS$204,1)) | K13: =IF($B13="","",SUMIFS(SAISIE_PROD!$X$5:$X$204,SAISIE_PROD!$A$5:$A$204,$B13,SAISIE_PROD!$AS$5:$AS$204,1)) | L13: =IF($B13="","",SUMIFS(SAISIE_PROD!$AC$5:$AC$204,SAISIE_PROD!$A$5:$A$204,$B13,SAISIE_PROD!$AS$5:$AS$204,1)) | M13: =IF(OR($B13="",$D13=0),"",$C13/$D13) | N13: =IF($B13="",NA(),$V$3) | O13: =IF(COUNT($M12:$M13)<3,"",AVERAGE($M12:$M13)) | P13: =IF(OR($B13="",$V$5=""),NA(),$V$6) | Q13: =IF(OR($B13="",$V$5=""),NA(),$V$7) | R13: =IF($M13="",NA(),$M13) | S13: =IF($O13="",NA(),$O13) | U13: Manque matière (min) | V13: =SUMIFS(SAISIE_PROD!$K$5:$K$204,SAISIE_PROD!$A$5:$A$204,">="&$B$7,SAISIE_PROD!$A$5:$A$204,"<="&$B$8,SAISIE_PROD!$AS$5:$AS$204,1)
A14: 3 | B14: =IF($A14>DAY($B$8),"",DATE($B$3,$B$4,$A14)) | C14: =IF($B14="","",SUMIFS(SAISIE_PROD!$AE$5:$AE$204,SAISIE_PROD!$A$5:$A$204,$B14,SAISIE_PROD!$AS$5:$AS$204,1)) | D14: =IF($B14="","",SUMIFS(SAISIE_PROD!$AB$5:$AB$204,SAISIE_PROD!$A$5:$A$204,$B14,SAISIE_PROD!$AS$5:$AS$204,1)) | E14: =IF($B14="","",SUMIFS(SAISIE_PROD!$AD$5:$AD$204,SAISIE_PROD!$A$5:$A$204,$B14,SAISIE_PROD!$AS$5:$AS$204,1)) | F14: =IF($B14="","",SUMIFS(SAISIE_PROD!$F$5:$F$204,SAISIE_PROD!$A$5:$A$204,$B14,SAISIE_PROD!$AS$5:$AS$204,1)) | G14: =IF($B14="","",SUMIFS(SAISIE_PROD!$P$5:$P$204,SAISIE_PROD!$A$5:$A$204,$B14,SAISIE_PROD!$AS$5:$AS$204,1)) | H14: =IF($B14="","",SUMIFS(SAISIE_PROD!$Q$5:$Q$204,SAISIE_PROD!$A$5:$A$204,$B14,SAISIE_PROD!$AS$5:$AS$204,1)) | I14: =IF($B14="","",SUMIFS(SAISIE_PROD!$R$5:$R$204,SAISIE_PROD!$A$5:$A$204,$B14,SAISIE_PROD!$AS$5:$AS$204,1)) | J14: =IF($B14="","",SUMIFS(SAISIE_PROD!$T$5:$T$204,SAISIE_PROD!$A$5:$A$204,$B14,SAISIE_PROD!$AS$5:$AS$204,1)) | K14: =IF($B14="","",SUMIFS(SAISIE_PROD!$X$5:$X$204,SAISIE_PROD!$A$5:$A$204,$B14,SAISIE_PROD!$AS$5:$AS$204,1)) | L14: =IF($B14="","",SUMIFS(SAISIE_PROD!$AC$5:$AC$204,SAISIE_PROD!$A$5:$A$204,$B14,SAISIE_PROD!$AS$5:$AS$204,1)) | M14: =IF(OR($B14="",$D14=0),"",$C14/$D14) | N14: =IF($B14="",NA(),$V$3) | O14: =IF(COUNT($M12:$M14)<3,"",AVERAGE($M12:$M14)) | P14: =IF(OR($B14="",$V$5=""),NA(),$V$6) | Q14: =IF(OR($B14="",$V$5=""),NA(),$V$7) | R14: =IF($M14="",NA(),$M14) | S14: =IF($O14="",NA(),$O14) | U14: Manque personnel (min) | V14: =SUMIFS(SAISIE_PROD!$L$5:$L$204,SAISIE_PROD!$A$5:$A$204,">="&$B$7,SAISIE_PROD!$A$5:$A$204,"<="&$B$8,SAISIE_PROD!$AS$5:$AS$204,1)
A15: 4 | B15: =IF($A15>DAY($B$8),"",DATE($B$3,$B$4,$A15)) | C15: =IF($B15="","",SUMIFS(SAISIE_PROD!$AE$5:$AE$204,SAISIE_PROD!$A$5:$A$204,$B15,SAISIE_PROD!$AS$5:$AS$204,1)) | D15: =IF($B15="","",SUMIFS(SAISIE_PROD!$AB$5:$AB$204,SAISIE_PROD!$A$5:$A$204,$B15,SAISIE_PROD!$AS$5:$AS$204,1)) | E15: =IF($B15="","",SUMIFS(SAISIE_PROD!$AD$5:$AD$204,SAISIE_PROD!$A$5:$A$204,$B15,SAISIE_PROD!$AS$5:$AS$204,1)) | F15: =IF($B15="","",SUMIFS(SAISIE_PROD!$F$5:$F$204,SAISIE_PROD!$A$5:$A$204,$B15,SAISIE_PROD!$AS$5:$AS$204,1)) | G15: =IF($B15="","",SUMIFS(SAISIE_PROD!$P$5:$P$204,SAISIE_PROD!$A$5:$A$204,$B15,SAISIE_PROD!$AS$5:$AS$204,1)) | H15: =IF($B15="","",SUMIFS(SAISIE_PROD!$Q$5:$Q$204,SAISIE_PROD!$A$5:$A$204,$B15,SAISIE_PROD!$AS$5:$AS$204,1)) | I15: =IF($B15="","",SUMIFS(SAISIE_PROD!$R$5:$R$204,SAISIE_PROD!$A$5:$A$204,$B15,SAISIE_PROD!$AS$5:$AS$204,1)) | J15: =IF($B15="","",SUMIFS(SAISIE_PROD!$T$5:$T$204,SAISIE_PROD!$A$5:$A$204,$B15,SAISIE_PROD!$AS$5:$AS$204,1)) | K15: =IF($B15="","",SUMIFS(SAISIE_PROD!$X$5:$X$204,SAISIE_PROD!$A$5:$A$204,$B15,SAISIE_PROD!$AS$5:$AS$204,1)) | L15: =IF($B15="","",SUMIFS(SAISIE_PROD!$AC$5:$AC$204,SAISIE_PROD!$A$5:$A$204,$B15,SAISIE_PROD!$AS$5:$AS$204,1)) | M15: =IF(OR($B15="",$D15=0),"",$C15/$D15) | N15: =IF($B15="",NA(),$V$3) | O15: =IF(COUNT($M12:$M15)<3,"",AVERAGE($M12:$M15)) | P15: =IF(OR($B15="",$V$5=""),NA(),$V$6) | Q15: =IF(OR($B15="",$V$5=""),NA(),$V$7) | R15: =IF($M15="",NA(),$M15) | S15: =IF($O15="",NA(),$O15) | U15: Autres arrêts subis (min) | V15: =SUMIFS(SAISIE_PROD!$M$5:$M$204,SAISIE_PROD!$A$5:$A$204,">="&$B$7,SAISIE_PROD!$A$5:$A$204,"<="&$B$8,SAISIE_PROD!$AS$5:$AS$204,1)
A16: 5 | B16: =IF($A16>DAY($B$8),"",DATE($B$3,$B$4,$A16)) | C16: =IF($B16="","",SUMIFS(SAISIE_PROD!$AE$5:$AE$204,SAISIE_PROD!$A$5:$A$204,$B16,SAISIE_PROD!$AS$5:$AS$204,1)) | D16: =IF($B16="","",SUMIFS(SAISIE_PROD!$AB$5:$AB$204,SAISIE_PROD!$A$5:$A$204,$B16,SAISIE_PROD!$AS$5:$AS$204,1)) | E16: =IF($B16="","",SUMIFS(SAISIE_PROD!$AD$5:$AD$204,SAISIE_PROD!$A$5:$A$204,$B16,SAISIE_PROD!$AS$5:$AS$204,1)) | F16: =IF($B16="","",SUMIFS(SAISIE_PROD!$F$5:$F$204,SAISIE_PROD!$A$5:$A$204,$B16,SAISIE_PROD!$AS$5:$AS$204,1)) | G16: =IF($B16="","",SUMIFS(SAISIE_PROD!$P$5:$P$204,SAISIE_PROD!$A$5:$A$204,$B16,SAISIE_PROD!$AS$5:$AS$204,1)) | H16: =IF($B16="","",SUMIFS(SAISIE_PROD!$Q$5:$Q$204,SAISIE_PROD!$A$5:$A$204,$B16,SAISIE_PROD!$AS$5:$AS$204,1)) | I16: =IF($B16="","",SUMIFS(SAISIE_PROD!$R$5:$R$204,SAISIE_PROD!$A$5:$A$204,$B16,SAISIE_PROD!$AS$5:$AS$204,1)) | J16: =IF($B16="","",SUMIFS(SAISIE_PROD!$T$5:$T$204,SAISIE_PROD!$A$5:$A$204,$B16,SAISIE_PROD!$AS$5:$AS$204,1)) | K16: =IF($B16="","",SUMIFS(SAISIE_PROD!$X$5:$X$204,SAISIE_PROD!$A$5:$A$204,$B16,SAISIE_PROD!$AS$5:$AS$204,1)) | L16: =IF($B16="","",SUMIFS(SAISIE_PROD!$AC$5:$AC$204,SAISIE_PROD!$A$5:$A$204,$B16,SAISIE_PROD!$AS$5:$AS$204,1)) | M16: =IF(OR($B16="",$D16=0),"",$C16/$D16) | N16: =IF($B16="",NA(),$V$3) | O16: =IF(COUNT($M12:$M16)<3,"",AVERAGE($M12:$M16)) | P16: =IF(OR($B16="",$V$5=""),NA(),$V$6) | Q16: =IF(OR($B16="",$V$5=""),NA(),$V$7) | R16: =IF($M16="",NA(),$M16) | S16: =IF($O16="",NA(),$O16) | U16: Perte de cadence (min) | V16: =SUMIFS(SAISIE_PROD!$AP$5:$AP$204,SAISIE_PROD!$A$5:$A$204,">="&$B$7,SAISIE_PROD!$A$5:$A$204,"<="&$B$8,SAISIE_PROD!$AS$5:$AS$204,1)
A17: 6 | B17: =IF($A17>DAY($B$8),"",DATE($B$3,$B$4,$A17)) | C17: =IF($B17="","",SUMIFS(SAISIE_PROD!$AE$5:$AE$204,SAISIE_PROD!$A$5:$A$204,$B17,SAISIE_PROD!$AS$5:$AS$204,1)) | D17: =IF($B17="","",SUMIFS(SAISIE_PROD!$AB$5:$AB$204,SAISIE_PROD!$A$5:$A$204,$B17,SAISIE_PROD!$AS$5:$AS$204,1)) | E17: =IF($B17="","",SUMIFS(SAISIE_PROD!$AD$5:$AD$204,SAISIE_PROD!$A$5:$A$204,$B17,SAISIE_PROD!$AS$5:$AS$204,1)) | F17: =IF($B17="","",SUMIFS(SAISIE_PROD!$F$5:$F$204,SAISIE_PROD!$A$5:$A$204,$B17,SAISIE_PROD!$AS$5:$AS$204,1)) | G17: =IF($B17="","",SUMIFS(SAISIE_PROD!$P$5:$P$204,SAISIE_PROD!$A$5:$A$204,$B17,SAISIE_PROD!$AS$5:$AS$204,1)) | H17: =IF($B17="","",SUMIFS(SAISIE_PROD!$Q$5:$Q$204,SAISIE_PROD!$A$5:$A$204,$B17,SAISIE_PROD!$AS$5:$AS$204,1)) | I17: =IF($B17="","",SUMIFS(SAISIE_PROD!$R$5:$R$204,SAISIE_PROD!$A$5:$A$204,$B17,SAISIE_PROD!$AS$5:$AS$204,1)) | J17: =IF($B17="","",SUMIFS(SAISIE_PROD!$T$5:$T$204,SAISIE_PROD!$A$5:$A$204,$B17,SAISIE_PROD!$AS$5:$AS$204,1)) | K17: =IF($B17="","",SUMIFS(SAISIE_PROD!$X$5:$X$204,SAISIE_PROD!$A$5:$A$204,$B17,SAISIE_PROD!$AS$5:$AS$204,1)) | L17: =IF($B17="","",SUMIFS(SAISIE_PROD!$AC$5:$AC$204,SAISIE_PROD!$A$5:$A$204,$B17,SAISIE_PROD!$AS$5:$AS$204,1)) | M17: =IF(OR($B17="",$D17=0),"",$C17/$D17) | N17: =IF($B17="",NA(),$V$3) | O17: =IF(COUNT($M12:$M17)<3,"",AVERAGE($M12:$M17)) | P17: =IF(OR($B17="",$V$5=""),NA(),$V$6) | Q17: =IF(OR($B17="",$V$5=""),NA(),$V$7) | R17: =IF($M17="",NA(),$M17) | S17: =IF($O17="",NA(),$O17) | U17: Pertes non-qualité (min) | V17: =SUMIFS(SAISIE_PROD!$AQ$5:$AQ$204,SAISIE_PROD!$A$5:$A$204,">="&$B$7,SAISIE_PROD!$A$5:$A$204,"<="&$B$8,SAISIE_PROD!$AS$5:$AS$204,1)
A18: 7 | B18: =IF($A18>DAY($B$8),"",DATE($B$3,$B$4,$A18)) | C18: =IF($B18="","",SUMIFS(SAISIE_PROD!$AE$5:$AE$204,SAISIE_PROD!$A$5:$A$204,$B18,SAISIE_PROD!$AS$5:$AS$204,1)) | D18: =IF($B18="","",SUMIFS(SAISIE_PROD!$AB$5:$AB$204,SAISIE_PROD!$A$5:$A$204,$B18,SAISIE_PROD!$AS$5:$AS$204,1)) | E18: =IF($B18="","",SUMIFS(SAISIE_PROD!$AD$5:$AD$204,SAISIE_PROD!$A$5:$A$204,$B18,SAISIE_PROD!$AS$5:$AS$204,1)) | F18: =IF($B18="","",SUMIFS(SAISIE_PROD!$F$5:$F$204,SAISIE_PROD!$A$5:$A$204,$B18,SAISIE_PROD!$AS$5:$AS$204,1)) | G18: =IF($B18="","",SUMIFS(SAISIE_PROD!$P$5:$P$204,SAISIE_PROD!$A$5:$A$204,$B18,SAISIE_PROD!$AS$5:$AS$204,1)) | H18: =IF($B18="","",SUMIFS(SAISIE_PROD!$Q$5:$Q$204,SAISIE_PROD!$A$5:$A$204,$B18,SAISIE_PROD!$AS$5:$AS$204,1)) | I18: =IF($B18="","",SUMIFS(SAISIE_PROD!$R$5:$R$204,SAISIE_PROD!$A$5:$A$204,$B18,SAISIE_PROD!$AS$5:$AS$204,1)) | J18: =IF($B18="","",SUMIFS(SAISIE_PROD!$T$5:$T$204,SAISIE_PROD!$A$5:$A$204,$B18,SAISIE_PROD!$AS$5:$AS$204,1)) | K18: =IF($B18="","",SUMIFS(SAISIE_PROD!$X$5:$X$204,SAISIE_PROD!$A$5:$A$204,$B18,SAISIE_PROD!$AS$5:$AS$204,1)) | L18: =IF($B18="","",SUMIFS(SAISIE_PROD!$AC$5:$AC$204,SAISIE_PROD!$A$5:$A$204,$B18,SAISIE_PROD!$AS$5:$AS$204,1)) | M18: =IF(OR($B18="",$D18=0),"",$C18/$D18) | N18: =IF($B18="",NA(),$V$3) | O18: =IF(COUNT($M12:$M18)<3,"",AVERAGE($M12:$M18)) | P18: =IF(OR($B18="",$V$5=""),NA(),$V$6) | Q18: =IF(OR($B18="",$V$5=""),NA(),$V$7) | R18: =IF($M18="",NA(),$M18) | S18: =IF($O18="",NA(),$O18) | U18: Temps requis TR (min) | V18: =SUMIFS(SAISIE_PROD!$AB$5:$AB$204,SAISIE_PROD!$A$5:$A$204,">="&$B$7,SAISIE_PROD!$A$5:$A$204,"<="&$B$8,SAISIE_PROD!$AS$5:$AS$204,1)
A19: 8 | B19: =IF($A19>DAY($B$8),"",DATE($B$3,$B$4,$A19)) | C19: =IF($B19="","",SUMIFS(SAISIE_PROD!$AE$5:$AE$204,SAISIE_PROD!$A$5:$A$204,$B19,SAISIE_PROD!$AS$5:$AS$204,1)) | D19: =IF($B19="","",SUMIFS(SAISIE_PROD!$AB$5:$AB$204,SAISIE_PROD!$A$5:$A$204,$B19,SAISIE_PROD!$AS$5:$AS$204,1)) | E19: =IF($B19="","",SUMIFS(SAISIE_PROD!$AD$5:$AD$204,SAISIE_PROD!$A$5:$A$204,$B19,SAISIE_PROD!$AS$5:$AS$204,1)) | F19: =IF($B19="","",SUMIFS(SAISIE_PROD!$F$5:$F$204,SAISIE_PROD!$A$5:$A$204,$B19,SAISIE_PROD!$AS$5:$AS$204,1)) | G19: =IF($B19="","",SUMIFS(SAISIE_PROD!$P$5:$P$204,SAISIE_PROD!$A$5:$A$204,$B19,SAISIE_PROD!$AS$5:$AS$204,1)) | H19: =IF($B19="","",SUMIFS(SAISIE_PROD!$Q$5:$Q$204,SAISIE_PROD!$A$5:$A$204,$B19,SAISIE_PROD!$AS$5:$AS$204,1)) | I19: =IF($B19="","",SUMIFS(SAISIE_PROD!$R$5:$R$204,SAISIE_PROD!$A$5:$A$204,$B19,SAISIE_PROD!$AS$5:$AS$204,1)) | J19: =IF($B19="","",SUMIFS(SAISIE_PROD!$T$5:$T$204,SAISIE_PROD!$A$5:$A$204,$B19,SAISIE_PROD!$AS$5:$AS$204,1)) | K19: =IF($B19="","",SUMIFS(SAISIE_PROD!$X$5:$X$204,SAISIE_PROD!$A$5:$A$204,$B19,SAISIE_PROD!$AS$5:$AS$204,1)) | L19: =IF($B19="","",SUMIFS(SAISIE_PROD!$AC$5:$AC$204,SAISIE_PROD!$A$5:$A$204,$B19,SAISIE_PROD!$AS$5:$AS$204,1)) | M19: =IF(OR($B19="",$D19=0),"",$C19/$D19) | N19: =IF($B19="",NA(),$V$3) | O19: =IF(COUNT($M13:$M19)<3,"",AVERAGE($M13:$M19)) | P19: =IF(OR($B19="",$V$5=""),NA(),$V$6) | Q19: =IF(OR($B19="",$V$5=""),NA(),$V$7) | R19: =IF($M19="",NA(),$M19) | S19: =IF($O19="",NA(),$O19) | U19: Temps de marche TF (min) | V19: =SUMIFS(SAISIE_PROD!$AD$5:$AD$204,SAISIE_PROD!$A$5:$A$204,">="&$B$7,SAISIE_PROD!$A$5:$A$204,"<="&$B$8,SAISIE_PROD!$AS$5:$AS$204,1)
A20: 9 | B20: =IF($A20>DAY($B$8),"",DATE($B$3,$B$4,$A20)) | C20: =IF($B20="","",SUMIFS(SAISIE_PROD!$AE$5:$AE$204,SAISIE_PROD!$A$5:$A$204,$B20,SAISIE_PROD!$AS$5:$AS$204,1)) | D20: =IF($B20="","",SUMIFS(SAISIE_PROD!$AB$5:$AB$204,SAISIE_PROD!$A$5:$A$204,$B20,SAISIE_PROD!$AS$5:$AS$204,1)) | E20: =IF($B20="","",SUMIFS(SAISIE_PROD!$AD$5:$AD$204,SAISIE_PROD!$A$5:$A$204,$B20,SAISIE_PROD!$AS$5:$AS$204,1)) | F20: =IF($B20="","",SUMIFS(SAISIE_PROD!$F$5:$F$204,SAISIE_PROD!$A$5:$A$204,$B20,SAISIE_PROD!$AS$5:$AS$204,1)) | G20: =IF($B20="","",SUMIFS(SAISIE_PROD!$P$5:$P$204,SAISIE_PROD!$A$5:$A$204,$B20,SAISIE_PROD!$AS$5:$AS$204,1)) | H20: =IF($B20="","",SUMIFS(SAISIE_PROD!$Q$5:$Q$204,SAISIE_PROD!$A$5:$A$204,$B20,SAISIE_PROD!$AS$5:$AS$204,1)) | I20: =IF($B20="","",SUMIFS(SAISIE_PROD!$R$5:$R$204,SAISIE_PROD!$A$5:$A$204,$B20,SAISIE_PROD!$AS$5:$AS$204,1)) | J20: =IF($B20="","",SUMIFS(SAISIE_PROD!$T$5:$T$204,SAISIE_PROD!$A$5:$A$204,$B20,SAISIE_PROD!$AS$5:$AS$204,1)) | K20: =IF($B20="","",SUMIFS(SAISIE_PROD!$X$5:$X$204,SAISIE_PROD!$A$5:$A$204,$B20,SAISIE_PROD!$AS$5:$AS$204,1)) | L20: =IF($B20="","",SUMIFS(SAISIE_PROD!$AC$5:$AC$204,SAISIE_PROD!$A$5:$A$204,$B20,SAISIE_PROD!$AS$5:$AS$204,1)) | M20: =IF(OR($B20="",$D20=0),"",$C20/$D20) | N20: =IF($B20="",NA(),$V$3) | O20: =IF(COUNT($M14:$M20)<3,"",AVERAGE($M14:$M20)) | P20: =IF(OR($B20="",$V$5=""),NA(),$V$6) | Q20: =IF(OR($B20="",$V$5=""),NA(),$V$7) | R20: =IF($M20="",NA(),$M20) | S20: =IF($O20="",NA(),$O20) | U20: Temps utile TU (min) | V20: =SUMIFS(SAISIE_PROD!$AE$5:$AE$204,SAISIE_PROD!$A$5:$A$204,">="&$B$7,SAISIE_PROD!$A$5:$A$204,"<="&$B$8,SAISIE_PROD!$AS$5:$AS$204,1)
A21: 10 | B21: =IF($A21>DAY($B$8),"",DATE($B$3,$B$4,$A21)) | C21: =IF($B21="","",SUMIFS(SAISIE_PROD!$AE$5:$AE$204,SAISIE_PROD!$A$5:$A$204,$B21,SAISIE_PROD!$AS$5:$AS$204,1)) | D21: =IF($B21="","",SUMIFS(SAISIE_PROD!$AB$5:$AB$204,SAISIE_PROD!$A$5:$A$204,$B21,SAISIE_PROD!$AS$5:$AS$204,1)) | E21: =IF($B21="","",SUMIFS(SAISIE_PROD!$AD$5:$AD$204,SAISIE_PROD!$A$5:$A$204,$B21,SAISIE_PROD!$AS$5:$AS$204,1)) | F21: =IF($B21="","",SUMIFS(SAISIE_PROD!$F$5:$F$204,SAISIE_PROD!$A$5:$A$204,$B21,SAISIE_PROD!$AS$5:$AS$204,1)) | G21: =IF($B21="","",SUMIFS(SAISIE_PROD!$P$5:$P$204,SAISIE_PROD!$A$5:$A$204,$B21,SAISIE_PROD!$AS$5:$AS$204,1)) | H21: =IF($B21="","",SUMIFS(SAISIE_PROD!$Q$5:$Q$204,SAISIE_PROD!$A$5:$A$204,$B21,SAISIE_PROD!$AS$5:$AS$204,1)) | I21: =IF($B21="","",SUMIFS(SAISIE_PROD!$R$5:$R$204,SAISIE_PROD!$A$5:$A$204,$B21,SAISIE_PROD!$AS$5:$AS$204,1)) | J21: =IF($B21="","",SUMIFS(SAISIE_PROD!$T$5:$T$204,SAISIE_PROD!$A$5:$A$204,$B21,SAISIE_PROD!$AS$5:$AS$204,1)) | K21: =IF($B21="","",SUMIFS(SAISIE_PROD!$X$5:$X$204,SAISIE_PROD!$A$5:$A$204,$B21,SAISIE_PROD!$AS$5:$AS$204,1)) | L21: =IF($B21="","",SUMIFS(SAISIE_PROD!$AC$5:$AC$204,SAISIE_PROD!$A$5:$A$204,$B21,SAISIE_PROD!$AS$5:$AS$204,1)) | M21: =IF(OR($B21="",$D21=0),"",$C21/$D21) | N21: =IF($B21="",NA(),$V$3) | O21: =IF(COUNT($M15:$M21)<3,"",AVERAGE($M15:$M21)) | P21: =IF(OR($B21="",$V$5=""),NA(),$V$6) | Q21: =IF(OR($B21="",$V$5=""),NA(),$V$7) | R21: =IF($M21="",NA(),$M21) | S21: =IF($O21="",NA(),$O21) | U21: — (réservé) —
A22: 11 | B22: =IF($A22>DAY($B$8),"",DATE($B$3,$B$4,$A22)) | C22: =IF($B22="","",SUMIFS(SAISIE_PROD!$AE$5:$AE$204,SAISIE_PROD!$A$5:$A$204,$B22,SAISIE_PROD!$AS$5:$AS$204,1)) | D22: =IF($B22="","",SUMIFS(SAISIE_PROD!$AB$5:$AB$204,SAISIE_PROD!$A$5:$A$204,$B22,SAISIE_PROD!$AS$5:$AS$204,1)) | E22: =IF($B22="","",SUMIFS(SAISIE_PROD!$AD$5:$AD$204,SAISIE_PROD!$A$5:$A$204,$B22,SAISIE_PROD!$AS$5:$AS$204,1)) | F22: =IF($B22="","",SUMIFS(SAISIE_PROD!$F$5:$F$204,SAISIE_PROD!$A$5:$A$204,$B22,SAISIE_PROD!$AS$5:$AS$204,1)) | G22: =IF($B22="","",SUMIFS(SAISIE_PROD!$P$5:$P$204,SAISIE_PROD!$A$5:$A$204,$B22,SAISIE_PROD!$AS$5:$AS$204,1)) | H22: =IF($B22="","",SUMIFS(SAISIE_PROD!$Q$5:$Q$204,SAISIE_PROD!$A$5:$A$204,$B22,SAISIE_PROD!$AS$5:$AS$204,1)) | I22: =IF($B22="","",SUMIFS(SAISIE_PROD!$R$5:$R$204,SAISIE_PROD!$A$5:$A$204,$B22,SAISIE_PROD!$AS$5:$AS$204,1)) | J22: =IF($B22="","",SUMIFS(SAISIE_PROD!$T$5:$T$204,SAISIE_PROD!$A$5:$A$204,$B22,SAISIE_PROD!$AS$5:$AS$204,1)) | K22: =IF($B22="","",SUMIFS(SAISIE_PROD!$X$5:$X$204,SAISIE_PROD!$A$5:$A$204,$B22,SAISIE_PROD!$AS$5:$AS$204,1)) | L22: =IF($B22="","",SUMIFS(SAISIE_PROD!$AC$5:$AC$204,SAISIE_PROD!$A$5:$A$204,$B22,SAISIE_PROD!$AS$5:$AS$204,1)) | M22: =IF(OR($B22="",$D22=0),"",$C22/$D22) | N22: =IF($B22="",NA(),$V$3) | O22: =IF(COUNT($M16:$M22)<3,"",AVERAGE($M16:$M22)) | P22: =IF(OR($B22="",$V$5=""),NA(),$V$6) | Q22: =IF(OR($B22="",$V$5=""),NA(),$V$7) | R22: =IF($M22="",NA(),$M22) | S22: =IF($O22="",NA(),$O22) | U22: Quantité produite | V22: =SUMIFS(SAISIE_PROD!$P$5:$P$204,SAISIE_PROD!$A$5:$A$204,">="&$B$7,SAISIE_PROD!$A$5:$A$204,"<="&$B$8,SAISIE_PROD!$AS$5:$AS$204,1)
A23: 12 | B23: =IF($A23>DAY($B$8),"",DATE($B$3,$B$4,$A23)) | C23: =IF($B23="","",SUMIFS(SAISIE_PROD!$AE$5:$AE$204,SAISIE_PROD!$A$5:$A$204,$B23,SAISIE_PROD!$AS$5:$AS$204,1)) | D23: =IF($B23="","",SUMIFS(SAISIE_PROD!$AB$5:$AB$204,SAISIE_PROD!$A$5:$A$204,$B23,SAISIE_PROD!$AS$5:$AS$204,1)) | E23: =IF($B23="","",SUMIFS(SAISIE_PROD!$AD$5:$AD$204,SAISIE_PROD!$A$5:$A$204,$B23,SAISIE_PROD!$AS$5:$AS$204,1)) | F23: =IF($B23="","",SUMIFS(SAISIE_PROD!$F$5:$F$204,SAISIE_PROD!$A$5:$A$204,$B23,SAISIE_PROD!$AS$5:$AS$204,1)) | G23: =IF($B23="","",SUMIFS(SAISIE_PROD!$P$5:$P$204,SAISIE_PROD!$A$5:$A$204,$B23,SAISIE_PROD!$AS$5:$AS$204,1)) | H23: =IF($B23="","",SUMIFS(SAISIE_PROD!$Q$5:$Q$204,SAISIE_PROD!$A$5:$A$204,$B23,SAISIE_PROD!$AS$5:$AS$204,1)) | I23: =IF($B23="","",SUMIFS(SAISIE_PROD!$R$5:$R$204,SAISIE_PROD!$A$5:$A$204,$B23,SAISIE_PROD!$AS$5:$AS$204,1)) | J23: =IF($B23="","",SUMIFS(SAISIE_PROD!$T$5:$T$204,SAISIE_PROD!$A$5:$A$204,$B23,SAISIE_PROD!$AS$5:$AS$204,1)) | K23: =IF($B23="","",SUMIFS(SAISIE_PROD!$X$5:$X$204,SAISIE_PROD!$A$5:$A$204,$B23,SAISIE_PROD!$AS$5:$AS$204,1)) | L23: =IF($B23="","",SUMIFS(SAISIE_PROD!$AC$5:$AC$204,SAISIE_PROD!$A$5:$A$204,$B23,SAISIE_PROD!$AS$5:$AS$204,1)) | M23: =IF(OR($B23="",$D23=0),"",$C23/$D23) | N23: =IF($B23="",NA(),$V$3) | O23: =IF(COUNT($M17:$M23)<3,"",AVERAGE($M17:$M23)) | P23: =IF(OR($B23="",$V$5=""),NA(),$V$6) | Q23: =IF(OR($B23="",$V$5=""),NA(),$V$7) | R23: =IF($M23="",NA(),$M23) | S23: =IF($O23="",NA(),$O23) | U23: Quantité conforme 1er passage | V23: =SUMIFS(SAISIE_PROD!$Q$5:$Q$204,SAISIE_PROD!$A$5:$A$204,">="&$B$7,SAISIE_PROD!$A$5:$A$204,"<="&$B$8,SAISIE_PROD!$AS$5:$AS$204,1)
A24: 13 | B24: =IF($A24>DAY($B$8),"",DATE($B$3,$B$4,$A24)) | C24: =IF($B24="","",SUMIFS(SAISIE_PROD!$AE$5:$AE$204,SAISIE_PROD!$A$5:$A$204,$B24,SAISIE_PROD!$AS$5:$AS$204,1)) | D24: =IF($B24="","",SUMIFS(SAISIE_PROD!$AB$5:$AB$204,SAISIE_PROD!$A$5:$A$204,$B24,SAISIE_PROD!$AS$5:$AS$204,1)) | E24: =IF($B24="","",SUMIFS(SAISIE_PROD!$AD$5:$AD$204,SAISIE_PROD!$A$5:$A$204,$B24,SAISIE_PROD!$AS$5:$AS$204,1)) | F24: =IF($B24="","",SUMIFS(SAISIE_PROD!$F$5:$F$204,SAISIE_PROD!$A$5:$A$204,$B24,SAISIE_PROD!$AS$5:$AS$204,1)) | G24: =IF($B24="","",SUMIFS(SAISIE_PROD!$P$5:$P$204,SAISIE_PROD!$A$5:$A$204,$B24,SAISIE_PROD!$AS$5:$AS$204,1)) | H24: =IF($B24="","",SUMIFS(SAISIE_PROD!$Q$5:$Q$204,SAISIE_PROD!$A$5:$A$204,$B24,SAISIE_PROD!$AS$5:$AS$204,1)) | I24: =IF($B24="","",SUMIFS(SAISIE_PROD!$R$5:$R$204,SAISIE_PROD!$A$5:$A$204,$B24,SAISIE_PROD!$AS$5:$AS$204,1)) | J24: =IF($B24="","",SUMIFS(SAISIE_PROD!$T$5:$T$204,SAISIE_PROD!$A$5:$A$204,$B24,SAISIE_PROD!$AS$5:$AS$204,1)) | K24: =IF($B24="","",SUMIFS(SAISIE_PROD!$X$5:$X$204,SAISIE_PROD!$A$5:$A$204,$B24,SAISIE_PROD!$AS$5:$AS$204,1)) | L24: =IF($B24="","",SUMIFS(SAISIE_PROD!$AC$5:$AC$204,SAISIE_PROD!$A$5:$A$204,$B24,SAISIE_PROD!$AS$5:$AS$204,1)) | M24: =IF(OR($B24="",$D24=0),"",$C24/$D24) | N24: =IF($B24="",NA(),$V$3) | O24: =IF(COUNT($M18:$M24)<3,"",AVERAGE($M18:$M24)) | P24: =IF(OR($B24="",$V$5=""),NA(),$V$6) | Q24: =IF(OR($B24="",$V$5=""),NA(),$V$7) | R24: =IF($M24="",NA(),$M24) | S24: =IF($O24="",NA(),$O24) | U24: Quantité retouchée | V24: =SUMIFS(SAISIE_PROD!$R$5:$R$204,SAISIE_PROD!$A$5:$A$204,">="&$B$7,SAISIE_PROD!$A$5:$A$204,"<="&$B$8,SAISIE_PROD!$AS$5:$AS$204,1)
A25: 14 | B25: =IF($A25>DAY($B$8),"",DATE($B$3,$B$4,$A25)) | C25: =IF($B25="","",SUMIFS(SAISIE_PROD!$AE$5:$AE$204,SAISIE_PROD!$A$5:$A$204,$B25,SAISIE_PROD!$AS$5:$AS$204,1)) | D25: =IF($B25="","",SUMIFS(SAISIE_PROD!$AB$5:$AB$204,SAISIE_PROD!$A$5:$A$204,$B25,SAISIE_PROD!$AS$5:$AS$204,1)) | E25: =IF($B25="","",SUMIFS(SAISIE_PROD!$AD$5:$AD$204,SAISIE_PROD!$A$5:$A$204,$B25,SAISIE_PROD!$AS$5:$AS$204,1)) | F25: =IF($B25="","",SUMIFS(SAISIE_PROD!$F$5:$F$204,SAISIE_PROD!$A$5:$A$204,$B25,SAISIE_PROD!$AS$5:$AS$204,1)) | G25: =IF($B25="","",SUMIFS(SAISIE_PROD!$P$5:$P$204,SAISIE_PROD!$A$5:$A$204,$B25,SAISIE_PROD!$AS$5:$AS$204,1)) | H25: =IF($B25="","",SUMIFS(SAISIE_PROD!$Q$5:$Q$204,SAISIE_PROD!$A$5:$A$204,$B25,SAISIE_PROD!$AS$5:$AS$204,1)) | I25: =IF($B25="","",SUMIFS(SAISIE_PROD!$R$5:$R$204,SAISIE_PROD!$A$5:$A$204,$B25,SAISIE_PROD!$AS$5:$AS$204,1)) | J25: =IF($B25="","",SUMIFS(SAISIE_PROD!$T$5:$T$204,SAISIE_PROD!$A$5:$A$204,$B25,SAISIE_PROD!$AS$5:$AS$204,1)) | K25: =IF($B25="","",SUMIFS(SAISIE_PROD!$X$5:$X$204,SAISIE_PROD!$A$5:$A$204,$B25,SAISIE_PROD!$AS$5:$AS$204,1)) | L25: =IF($B25="","",SUMIFS(SAISIE_PROD!$AC$5:$AC$204,SAISIE_PROD!$A$5:$A$204,$B25,SAISIE_PROD!$AS$5:$AS$204,1)) | M25: =IF(OR($B25="",$D25=0),"",$C25/$D25) | N25: =IF($B25="",NA(),$V$3) | O25: =IF(COUNT($M19:$M25)<3,"",AVERAGE($M19:$M25)) | P25: =IF(OR($B25="",$V$5=""),NA(),$V$6) | Q25: =IF(OR($B25="",$V$5=""),NA(),$V$7) | R25: =IF($M25="",NA(),$M25) | S25: =IF($O25="",NA(),$O25) | U25: Quantité demandée | V25: =SUMIFS(SAISIE_PROD!$T$5:$T$204,SAISIE_PROD!$A$5:$A$204,">="&$B$7,SAISIE_PROD!$A$5:$A$204,"<="&$B$8,SAISIE_PROD!$AS$5:$AS$204,1)
A26: 15 | B26: =IF($A26>DAY($B$8),"",DATE($B$3,$B$4,$A26)) | C26: =IF($B26="","",SUMIFS(SAISIE_PROD!$AE$5:$AE$204,SAISIE_PROD!$A$5:$A$204,$B26,SAISIE_PROD!$AS$5:$AS$204,1)) | D26: =IF($B26="","",SUMIFS(SAISIE_PROD!$AB$5:$AB$204,SAISIE_PROD!$A$5:$A$204,$B26,SAISIE_PROD!$AS$5:$AS$204,1)) | E26: =IF($B26="","",SUMIFS(SAISIE_PROD!$AD$5:$AD$204,SAISIE_PROD!$A$5:$A$204,$B26,SAISIE_PROD!$AS$5:$AS$204,1)) | F26: =IF($B26="","",SUMIFS(SAISIE_PROD!$F$5:$F$204,SAISIE_PROD!$A$5:$A$204,$B26,SAISIE_PROD!$AS$5:$AS$204,1)) | G26: =IF($B26="","",SUMIFS(SAISIE_PROD!$P$5:$P$204,SAISIE_PROD!$A$5:$A$204,$B26,SAISIE_PROD!$AS$5:$AS$204,1)) | H26: =IF($B26="","",SUMIFS(SAISIE_PROD!$Q$5:$Q$204,SAISIE_PROD!$A$5:$A$204,$B26,SAISIE_PROD!$AS$5:$AS$204,1)) | I26: =IF($B26="","",SUMIFS(SAISIE_PROD!$R$5:$R$204,SAISIE_PROD!$A$5:$A$204,$B26,SAISIE_PROD!$AS$5:$AS$204,1)) | J26: =IF($B26="","",SUMIFS(SAISIE_PROD!$T$5:$T$204,SAISIE_PROD!$A$5:$A$204,$B26,SAISIE_PROD!$AS$5:$AS$204,1)) | K26: =IF($B26="","",SUMIFS(SAISIE_PROD!$X$5:$X$204,SAISIE_PROD!$A$5:$A$204,$B26,SAISIE_PROD!$AS$5:$AS$204,1)) | L26: =IF($B26="","",SUMIFS(SAISIE_PROD!$AC$5:$AC$204,SAISIE_PROD!$A$5:$A$204,$B26,SAISIE_PROD!$AS$5:$AS$204,1)) | M26: =IF(OR($B26="",$D26=0),"",$C26/$D26) | N26: =IF($B26="",NA(),$V$3) | O26: =IF(COUNT($M20:$M26)<3,"",AVERAGE($M20:$M26)) | P26: =IF(OR($B26="",$V$5=""),NA(),$V$6) | Q26: =IF(OR($B26="",$V$5=""),NA(),$V$7) | R26: =IF($M26="",NA(),$M26) | S26: =IF($O26="",NA(),$O26) | U26: Accidents avec arrêt | V26: =SUMIFS(SAISIE_PROD!$X$5:$X$204,SAISIE_PROD!$A$5:$A$204,">="&$B$7,SAISIE_PROD!$A$5:$A$204,"<="&$B$8,SAISIE_PROD!$AS$5:$AS$204,1)
A27: 16 | B27: =IF($A27>DAY($B$8),"",DATE($B$3,$B$4,$A27)) | C27: =IF($B27="","",SUMIFS(SAISIE_PROD!$AE$5:$AE$204,SAISIE_PROD!$A$5:$A$204,$B27,SAISIE_PROD!$AS$5:$AS$204,1)) | D27: =IF($B27="","",SUMIFS(SAISIE_PROD!$AB$5:$AB$204,SAISIE_PROD!$A$5:$A$204,$B27,SAISIE_PROD!$AS$5:$AS$204,1)) | E27: =IF($B27="","",SUMIFS(SAISIE_PROD!$AD$5:$AD$204,SAISIE_PROD!$A$5:$A$204,$B27,SAISIE_PROD!$AS$5:$AS$204,1)) | F27: =IF($B27="","",SUMIFS(SAISIE_PROD!$F$5:$F$204,SAISIE_PROD!$A$5:$A$204,$B27,SAISIE_PROD!$AS$5:$AS$204,1)) | G27: =IF($B27="","",SUMIFS(SAISIE_PROD!$P$5:$P$204,SAISIE_PROD!$A$5:$A$204,$B27,SAISIE_PROD!$AS$5:$AS$204,1)) | H27: =IF($B27="","",SUMIFS(SAISIE_PROD!$Q$5:$Q$204,SAISIE_PROD!$A$5:$A$204,$B27,SAISIE_PROD!$AS$5:$AS$204,1)) | I27: =IF($B27="","",SUMIFS(SAISIE_PROD!$R$5:$R$204,SAISIE_PROD!$A$5:$A$204,$B27,SAISIE_PROD!$AS$5:$AS$204,1)) | J27: =IF($B27="","",SUMIFS(SAISIE_PROD!$T$5:$T$204,SAISIE_PROD!$A$5:$A$204,$B27,SAISIE_PROD!$AS$5:$AS$204,1)) | K27: =IF($B27="","",SUMIFS(SAISIE_PROD!$X$5:$X$204,SAISIE_PROD!$A$5:$A$204,$B27,SAISIE_PROD!$AS$5:$AS$204,1)) | L27: =IF($B27="","",SUMIFS(SAISIE_PROD!$AC$5:$AC$204,SAISIE_PROD!$A$5:$A$204,$B27,SAISIE_PROD!$AS$5:$AS$204,1)) | M27: =IF(OR($B27="",$D27=0),"",$C27/$D27) | N27: =IF($B27="",NA(),$V$3) | O27: =IF(COUNT($M21:$M27)<3,"",AVERAGE($M21:$M27)) | P27: =IF(OR($B27="",$V$5=""),NA(),$V$6) | Q27: =IF(OR($B27="",$V$5=""),NA(),$V$7) | R27: =IF($M27="",NA(),$M27) | S27: =IF($O27="",NA(),$O27) | U27: Nombre de pannes | V27: =SUMIFS(SAISIE_PROD!$N$5:$N$204,SAISIE_PROD!$A$5:$A$204,">="&$B$7,SAISIE_PROD!$A$5:$A$204,"<="&$B$8,SAISIE_PROD!$AS$5:$AS$204,1)
A28: 17 | B28: =IF($A28>DAY($B$8),"",DATE($B$3,$B$4,$A28)) | C28: =IF($B28="","",SUMIFS(SAISIE_PROD!$AE$5:$AE$204,SAISIE_PROD!$A$5:$A$204,$B28,SAISIE_PROD!$AS$5:$AS$204,1)) | D28: =IF($B28="","",SUMIFS(SAISIE_PROD!$AB$5:$AB$204,SAISIE_PROD!$A$5:$A$204,$B28,SAISIE_PROD!$AS$5:$AS$204,1)) | E28: =IF($B28="","",SUMIFS(SAISIE_PROD!$AD$5:$AD$204,SAISIE_PROD!$A$5:$A$204,$B28,SAISIE_PROD!$AS$5:$AS$204,1)) | F28: =IF($B28="","",SUMIFS(SAISIE_PROD!$F$5:$F$204,SAISIE_PROD!$A$5:$A$204,$B28,SAISIE_PROD!$AS$5:$AS$204,1)) | G28: =IF($B28="","",SUMIFS(SAISIE_PROD!$P$5:$P$204,SAISIE_PROD!$A$5:$A$204,$B28,SAISIE_PROD!$AS$5:$AS$204,1)) | H28: =IF($B28="","",SUMIFS(SAISIE_PROD!$Q$5:$Q$204,SAISIE_PROD!$A$5:$A$204,$B28,SAISIE_PROD!$AS$5:$AS$204,1)) | I28: =IF($B28="","",SUMIFS(SAISIE_PROD!$R$5:$R$204,SAISIE_PROD!$A$5:$A$204,$B28,SAISIE_PROD!$AS$5:$AS$204,1)) | J28: =IF($B28="","",SUMIFS(SAISIE_PROD!$T$5:$T$204,SAISIE_PROD!$A$5:$A$204,$B28,SAISIE_PROD!$AS$5:$AS$204,1)) | K28: =IF($B28="","",SUMIFS(SAISIE_PROD!$X$5:$X$204,SAISIE_PROD!$A$5:$A$204,$B28,SAISIE_PROD!$AS$5:$AS$204,1)) | L28: =IF($B28="","",SUMIFS(SAISIE_PROD!$AC$5:$AC$204,SAISIE_PROD!$A$5:$A$204,$B28,SAISIE_PROD!$AS$5:$AS$204,1)) | M28: =IF(OR($B28="",$D28=0),"",$C28/$D28) | N28: =IF($B28="",NA(),$V$3) | O28: =IF(COUNT($M22:$M28)<3,"",AVERAGE($M22:$M28)) | P28: =IF(OR($B28="",$V$5=""),NA(),$V$6) | Q28: =IF(OR($B28="",$V$5=""),NA(),$V$7) | R28: =IF($M28="",NA(),$M28) | S28: =IF($O28="",NA(),$O28) | U28: Effectif prévu (cumul) | V28: =SUMIFS(SAISIE_PROD!$U$5:$U$204,SAISIE_PROD!$A$5:$A$204,">="&$B$7,SAISIE_PROD!$A$5:$A$204,"<="&$B$8,SAISIE_PROD!$AS$5:$AS$204,1)
A29: 18 | B29: =IF($A29>DAY($B$8),"",DATE($B$3,$B$4,$A29)) | C29: =IF($B29="","",SUMIFS(SAISIE_PROD!$AE$5:$AE$204,SAISIE_PROD!$A$5:$A$204,$B29,SAISIE_PROD!$AS$5:$AS$204,1)) | D29: =IF($B29="","",SUMIFS(SAISIE_PROD!$AB$5:$AB$204,SAISIE_PROD!$A$5:$A$204,$B29,SAISIE_PROD!$AS$5:$AS$204,1)) | E29: =IF($B29="","",SUMIFS(SAISIE_PROD!$AD$5:$AD$204,SAISIE_PROD!$A$5:$A$204,$B29,SAISIE_PROD!$AS$5:$AS$204,1)) | F29: =IF($B29="","",SUMIFS(SAISIE_PROD!$F$5:$F$204,SAISIE_PROD!$A$5:$A$204,$B29,SAISIE_PROD!$AS$5:$AS$204,1)) | G29: =IF($B29="","",SUMIFS(SAISIE_PROD!$P$5:$P$204,SAISIE_PROD!$A$5:$A$204,$B29,SAISIE_PROD!$AS$5:$AS$204,1)) | H29: =IF($B29="","",SUMIFS(SAISIE_PROD!$Q$5:$Q$204,SAISIE_PROD!$A$5:$A$204,$B29,SAISIE_PROD!$AS$5:$AS$204,1)) | I29: =IF($B29="","",SUMIFS(SAISIE_PROD!$R$5:$R$204,SAISIE_PROD!$A$5:$A$204,$B29,SAISIE_PROD!$AS$5:$AS$204,1)) | J29: =IF($B29="","",SUMIFS(SAISIE_PROD!$T$5:$T$204,SAISIE_PROD!$A$5:$A$204,$B29,SAISIE_PROD!$AS$5:$AS$204,1)) | K29: =IF($B29="","",SUMIFS(SAISIE_PROD!$X$5:$X$204,SAISIE_PROD!$A$5:$A$204,$B29,SAISIE_PROD!$AS$5:$AS$204,1)) | L29: =IF($B29="","",SUMIFS(SAISIE_PROD!$AC$5:$AC$204,SAISIE_PROD!$A$5:$A$204,$B29,SAISIE_PROD!$AS$5:$AS$204,1)) | M29: =IF(OR($B29="",$D29=0),"",$C29/$D29) | N29: =IF($B29="",NA(),$V$3) | O29: =IF(COUNT($M23:$M29)<3,"",AVERAGE($M23:$M29)) | P29: =IF(OR($B29="",$V$5=""),NA(),$V$6) | Q29: =IF(OR($B29="",$V$5=""),NA(),$V$7) | R29: =IF($M29="",NA(),$M29) | S29: =IF($O29="",NA(),$O29) | U29: Effectif présent (cumul) | V29: =SUMIFS(SAISIE_PROD!$V$5:$V$204,SAISIE_PROD!$A$5:$A$204,">="&$B$7,SAISIE_PROD!$A$5:$A$204,"<="&$B$8,SAISIE_PROD!$AS$5:$AS$204,1)
A30: 19 | B30: =IF($A30>DAY($B$8),"",DATE($B$3,$B$4,$A30)) | C30: =IF($B30="","",SUMIFS(SAISIE_PROD!$AE$5:$AE$204,SAISIE_PROD!$A$5:$A$204,$B30,SAISIE_PROD!$AS$5:$AS$204,1)) | D30: =IF($B30="","",SUMIFS(SAISIE_PROD!$AB$5:$AB$204,SAISIE_PROD!$A$5:$A$204,$B30,SAISIE_PROD!$AS$5:$AS$204,1)) | E30: =IF($B30="","",SUMIFS(SAISIE_PROD!$AD$5:$AD$204,SAISIE_PROD!$A$5:$A$204,$B30,SAISIE_PROD!$AS$5:$AS$204,1)) | F30: =IF($B30="","",SUMIFS(SAISIE_PROD!$F$5:$F$204,SAISIE_PROD!$A$5:$A$204,$B30,SAISIE_PROD!$AS$5:$AS$204,1)) | G30: =IF($B30="","",SUMIFS(SAISIE_PROD!$P$5:$P$204,SAISIE_PROD!$A$5:$A$204,$B30,SAISIE_PROD!$AS$5:$AS$204,1)) | H30: =IF($B30="","",SUMIFS(SAISIE_PROD!$Q$5:$Q$204,SAISIE_PROD!$A$5:$A$204,$B30,SAISIE_PROD!$AS$5:$AS$204,1)) | I30: =IF($B30="","",SUMIFS(SAISIE_PROD!$R$5:$R$204,SAISIE_PROD!$A$5:$A$204,$B30,SAISIE_PROD!$AS$5:$AS$204,1)) | J30: =IF($B30="","",SUMIFS(SAISIE_PROD!$T$5:$T$204,SAISIE_PROD!$A$5:$A$204,$B30,SAISIE_PROD!$AS$5:$AS$204,1)) | K30: =IF($B30="","",SUMIFS(SAISIE_PROD!$X$5:$X$204,SAISIE_PROD!$A$5:$A$204,$B30,SAISIE_PROD!$AS$5:$AS$204,1)) | L30: =IF($B30="","",SUMIFS(SAISIE_PROD!$AC$5:$AC$204,SAISIE_PROD!$A$5:$A$204,$B30,SAISIE_PROD!$AS$5:$AS$204,1)) | M30: =IF(OR($B30="",$D30=0),"",$C30/$D30) | N30: =IF($B30="",NA(),$V$3) | O30: =IF(COUNT($M24:$M30)<3,"",AVERAGE($M24:$M30)) | P30: =IF(OR($B30="",$V$5=""),NA(),$V$6) | Q30: =IF(OR($B30="",$V$5=""),NA(),$V$7) | R30: =IF($M30="",NA(),$M30) | S30: =IF($O30="",NA(),$O30)
A31: 20 | B31: =IF($A31>DAY($B$8),"",DATE($B$3,$B$4,$A31)) | C31: =IF($B31="","",SUMIFS(SAISIE_PROD!$AE$5:$AE$204,SAISIE_PROD!$A$5:$A$204,$B31,SAISIE_PROD!$AS$5:$AS$204,1)) | D31: =IF($B31="","",SUMIFS(SAISIE_PROD!$AB$5:$AB$204,SAISIE_PROD!$A$5:$A$204,$B31,SAISIE_PROD!$AS$5:$AS$204,1)) | E31: =IF($B31="","",SUMIFS(SAISIE_PROD!$AD$5:$AD$204,SAISIE_PROD!$A$5:$A$204,$B31,SAISIE_PROD!$AS$5:$AS$204,1)) | F31: =IF($B31="","",SUMIFS(SAISIE_PROD!$F$5:$F$204,SAISIE_PROD!$A$5:$A$204,$B31,SAISIE_PROD!$AS$5:$AS$204,1)) | G31: =IF($B31="","",SUMIFS(SAISIE_PROD!$P$5:$P$204,SAISIE_PROD!$A$5:$A$204,$B31,SAISIE_PROD!$AS$5:$AS$204,1)) | H31: =IF($B31="","",SUMIFS(SAISIE_PROD!$Q$5:$Q$204,SAISIE_PROD!$A$5:$A$204,$B31,SAISIE_PROD!$AS$5:$AS$204,1)) | I31: =IF($B31="","",SUMIFS(SAISIE_PROD!$R$5:$R$204,SAISIE_PROD!$A$5:$A$204,$B31,SAISIE_PROD!$AS$5:$AS$204,1)) | J31: =IF($B31="","",SUMIFS(SAISIE_PROD!$T$5:$T$204,SAISIE_PROD!$A$5:$A$204,$B31,SAISIE_PROD!$AS$5:$AS$204,1)) | K31: =IF($B31="","",SUMIFS(SAISIE_PROD!$X$5:$X$204,SAISIE_PROD!$A$5:$A$204,$B31,SAISIE_PROD!$AS$5:$AS$204,1)) | L31: =IF($B31="","",SUMIFS(SAISIE_PROD!$AC$5:$AC$204,SAISIE_PROD!$A$5:$A$204,$B31,SAISIE_PROD!$AS$5:$AS$204,1)) | M31: =IF(OR($B31="",$D31=0),"",$C31/$D31) | N31: =IF($B31="",NA(),$V$3) | O31: =IF(COUNT($M25:$M31)<3,"",AVERAGE($M25:$M31)) | P31: =IF(OR($B31="",$V$5=""),NA(),$V$6) | Q31: =IF(OR($B31="",$V$5=""),NA(),$V$7) | R31: =IF($M31="",NA(),$M31) | S31: =IF($O31="",NA(),$O31)
A32: 21 | B32: =IF($A32>DAY($B$8),"",DATE($B$3,$B$4,$A32)) | C32: =IF($B32="","",SUMIFS(SAISIE_PROD!$AE$5:$AE$204,SAISIE_PROD!$A$5:$A$204,$B32,SAISIE_PROD!$AS$5:$AS$204,1)) | D32: =IF($B32="","",SUMIFS(SAISIE_PROD!$AB$5:$AB$204,SAISIE_PROD!$A$5:$A$204,$B32,SAISIE_PROD!$AS$5:$AS$204,1)) | E32: =IF($B32="","",SUMIFS(SAISIE_PROD!$AD$5:$AD$204,SAISIE_PROD!$A$5:$A$204,$B32,SAISIE_PROD!$AS$5:$AS$204,1)) | F32: =IF($B32="","",SUMIFS(SAISIE_PROD!$F$5:$F$204,SAISIE_PROD!$A$5:$A$204,$B32,SAISIE_PROD!$AS$5:$AS$204,1)) | G32: =IF($B32="","",SUMIFS(SAISIE_PROD!$P$5:$P$204,SAISIE_PROD!$A$5:$A$204,$B32,SAISIE_PROD!$AS$5:$AS$204,1)) | H32: =IF($B32="","",SUMIFS(SAISIE_PROD!$Q$5:$Q$204,SAISIE_PROD!$A$5:$A$204,$B32,SAISIE_PROD!$AS$5:$AS$204,1)) | I32: =IF($B32="","",SUMIFS(SAISIE_PROD!$R$5:$R$204,SAISIE_PROD!$A$5:$A$204,$B32,SAISIE_PROD!$AS$5:$AS$204,1)) | J32: =IF($B32="","",SUMIFS(SAISIE_PROD!$T$5:$T$204,SAISIE_PROD!$A$5:$A$204,$B32,SAISIE_PROD!$AS$5:$AS$204,1)) | K32: =IF($B32="","",SUMIFS(SAISIE_PROD!$X$5:$X$204,SAISIE_PROD!$A$5:$A$204,$B32,SAISIE_PROD!$AS$5:$AS$204,1)) | L32: =IF($B32="","",SUMIFS(SAISIE_PROD!$AC$5:$AC$204,SAISIE_PROD!$A$5:$A$204,$B32,SAISIE_PROD!$AS$5:$AS$204,1)) | M32: =IF(OR($B32="",$D32=0),"",$C32/$D32) | N32: =IF($B32="",NA(),$V$3) | O32: =IF(COUNT($M26:$M32)<3,"",AVERAGE($M26:$M32)) | P32: =IF(OR($B32="",$V$5=""),NA(),$V$6) | Q32: =IF(OR($B32="",$V$5=""),NA(),$V$7) | R32: =IF($M32="",NA(),$M32) | S32: =IF($O32="",NA(),$O32)
A33: 22 | B33: =IF($A33>DAY($B$8),"",DATE($B$3,$B$4,$A33)) | C33: =IF($B33="","",SUMIFS(SAISIE_PROD!$AE$5:$AE$204,SAISIE_PROD!$A$5:$A$204,$B33,SAISIE_PROD!$AS$5:$AS$204,1)) | D33: =IF($B33="","",SUMIFS(SAISIE_PROD!$AB$5:$AB$204,SAISIE_PROD!$A$5:$A$204,$B33,SAISIE_PROD!$AS$5:$AS$204,1)) | E33: =IF($B33="","",SUMIFS(SAISIE_PROD!$AD$5:$AD$204,SAISIE_PROD!$A$5:$A$204,$B33,SAISIE_PROD!$AS$5:$AS$204,1)) | F33: =IF($B33="","",SUMIFS(SAISIE_PROD!$F$5:$F$204,SAISIE_PROD!$A$5:$A$204,$B33,SAISIE_PROD!$AS$5:$AS$204,1)) | G33: =IF($B33="","",SUMIFS(SAISIE_PROD!$P$5:$P$204,SAISIE_PROD!$A$5:$A$204,$B33,SAISIE_PROD!$AS$5:$AS$204,1)) | H33: =IF($B33="","",SUMIFS(SAISIE_PROD!$Q$5:$Q$204,SAISIE_PROD!$A$5:$A$204,$B33,SAISIE_PROD!$AS$5:$AS$204,1)) | I33: =IF($B33="","",SUMIFS(SAISIE_PROD!$R$5:$R$204,SAISIE_PROD!$A$5:$A$204,$B33,SAISIE_PROD!$AS$5:$AS$204,1)) | J33: =IF($B33="","",SUMIFS(SAISIE_PROD!$T$5:$T$204,SAISIE_PROD!$A$5:$A$204,$B33,SAISIE_PROD!$AS$5:$AS$204,1)) | K33: =IF($B33="","",SUMIFS(SAISIE_PROD!$X$5:$X$204,SAISIE_PROD!$A$5:$A$204,$B33,SAISIE_PROD!$AS$5:$AS$204,1)) | L33: =IF($B33="","",SUMIFS(SAISIE_PROD!$AC$5:$AC$204,SAISIE_PROD!$A$5:$A$204,$B33,SAISIE_PROD!$AS$5:$AS$204,1)) | M33: =IF(OR($B33="",$D33=0),"",$C33/$D33) | N33: =IF($B33="",NA(),$V$3) | O33: =IF(COUNT($M27:$M33)<3,"",AVERAGE($M27:$M33)) | P33: =IF(OR($B33="",$V$5=""),NA(),$V$6) | Q33: =IF(OR($B33="",$V$5=""),NA(),$V$7) | R33: =IF($M33="",NA(),$M33) | S33: =IF($O33="",NA(),$O33)
A34: 23 | B34: =IF($A34>DAY($B$8),"",DATE($B$3,$B$4,$A34)) | C34: =IF($B34="","",SUMIFS(SAISIE_PROD!$AE$5:$AE$204,SAISIE_PROD!$A$5:$A$204,$B34,SAISIE_PROD!$AS$5:$AS$204,1)) | D34: =IF($B34="","",SUMIFS(SAISIE_PROD!$AB$5:$AB$204,SAISIE_PROD!$A$5:$A$204,$B34,SAISIE_PROD!$AS$5:$AS$204,1)) | E34: =IF($B34="","",SUMIFS(SAISIE_PROD!$AD$5:$AD$204,SAISIE_PROD!$A$5:$A$204,$B34,SAISIE_PROD!$AS$5:$AS$204,1)) | F34: =IF($B34="","",SUMIFS(SAISIE_PROD!$F$5:$F$204,SAISIE_PROD!$A$5:$A$204,$B34,SAISIE_PROD!$AS$5:$AS$204,1)) | G34: =IF($B34="","",SUMIFS(SAISIE_PROD!$P$5:$P$204,SAISIE_PROD!$A$5:$A$204,$B34,SAISIE_PROD!$AS$5:$AS$204,1)) | H34: =IF($B34="","",SUMIFS(SAISIE_PROD!$Q$5:$Q$204,SAISIE_PROD!$A$5:$A$204,$B34,SAISIE_PROD!$AS$5:$AS$204,1)) | I34: =IF($B34="","",SUMIFS(SAISIE_PROD!$R$5:$R$204,SAISIE_PROD!$A$5:$A$204,$B34,SAISIE_PROD!$AS$5:$AS$204,1)) | J34: =IF($B34="","",SUMIFS(SAISIE_PROD!$T$5:$T$204,SAISIE_PROD!$A$5:$A$204,$B34,SAISIE_PROD!$AS$5:$AS$204,1)) | K34: =IF($B34="","",SUMIFS(SAISIE_PROD!$X$5:$X$204,SAISIE_PROD!$A$5:$A$204,$B34,SAISIE_PROD!$AS$5:$AS$204,1)) | L34: =IF($B34="","",SUMIFS(SAISIE_PROD!$AC$5:$AC$204,SAISIE_PROD!$A$5:$A$204,$B34,SAISIE_PROD!$AS$5:$AS$204,1)) | M34: =IF(OR($B34="",$D34=0),"",$C34/$D34) | N34: =IF($B34="",NA(),$V$3) | O34: =IF(COUNT($M28:$M34)<3,"",AVERAGE($M28:$M34)) | P34: =IF(OR($B34="",$V$5=""),NA(),$V$6) | Q34: =IF(OR($B34="",$V$5=""),NA(),$V$7) | R34: =IF($M34="",NA(),$M34) | S34: =IF($O34="",NA(),$O34)
A35: 24 | B35: =IF($A35>DAY($B$8),"",DATE($B$3,$B$4,$A35)) | C35: =IF($B35="","",SUMIFS(SAISIE_PROD!$AE$5:$AE$204,SAISIE_PROD!$A$5:$A$204,$B35,SAISIE_PROD!$AS$5:$AS$204,1)) | D35: =IF($B35="","",SUMIFS(SAISIE_PROD!$AB$5:$AB$204,SAISIE_PROD!$A$5:$A$204,$B35,SAISIE_PROD!$AS$5:$AS$204,1)) | E35: =IF($B35="","",SUMIFS(SAISIE_PROD!$AD$5:$AD$204,SAISIE_PROD!$A$5:$A$204,$B35,SAISIE_PROD!$AS$5:$AS$204,1)) | F35: =IF($B35="","",SUMIFS(SAISIE_PROD!$F$5:$F$204,SAISIE_PROD!$A$5:$A$204,$B35,SAISIE_PROD!$AS$5:$AS$204,1)) | G35: =IF($B35="","",SUMIFS(SAISIE_PROD!$P$5:$P$204,SAISIE_PROD!$A$5:$A$204,$B35,SAISIE_PROD!$AS$5:$AS$204,1)) | H35: =IF($B35="","",SUMIFS(SAISIE_PROD!$Q$5:$Q$204,SAISIE_PROD!$A$5:$A$204,$B35,SAISIE_PROD!$AS$5:$AS$204,1)) | I35: =IF($B35="","",SUMIFS(SAISIE_PROD!$R$5:$R$204,SAISIE_PROD!$A$5:$A$204,$B35,SAISIE_PROD!$AS$5:$AS$204,1)) | J35: =IF($B35="","",SUMIFS(SAISIE_PROD!$T$5:$T$204,SAISIE_PROD!$A$5:$A$204,$B35,SAISIE_PROD!$AS$5:$AS$204,1)) | K35: =IF($B35="","",SUMIFS(SAISIE_PROD!$X$5:$X$204,SAISIE_PROD!$A$5:$A$204,$B35,SAISIE_PROD!$AS$5:$AS$204,1)) | L35: =IF($B35="","",SUMIFS(SAISIE_PROD!$AC$5:$AC$204,SAISIE_PROD!$A$5:$A$204,$B35,SAISIE_PROD!$AS$5:$AS$204,1)) | M35: =IF(OR($B35="",$D35=0),"",$C35/$D35) | N35: =IF($B35="",NA(),$V$3) | O35: =IF(COUNT($M29:$M35)<3,"",AVERAGE($M29:$M35)) | P35: =IF(OR($B35="",$V$5=""),NA(),$V$6) | Q35: =IF(OR($B35="",$V$5=""),NA(),$V$7) | R35: =IF($M35="",NA(),$M35) | S35: =IF($O35="",NA(),$O35)
A36: 25 | B36: =IF($A36>DAY($B$8),"",DATE($B$3,$B$4,$A36)) | C36: =IF($B36="","",SUMIFS(SAISIE_PROD!$AE$5:$AE$204,SAISIE_PROD!$A$5:$A$204,$B36,SAISIE_PROD!$AS$5:$AS$204,1)) | D36: =IF($B36="","",SUMIFS(SAISIE_PROD!$AB$5:$AB$204,SAISIE_PROD!$A$5:$A$204,$B36,SAISIE_PROD!$AS$5:$AS$204,1)) | E36: =IF($B36="","",SUMIFS(SAISIE_PROD!$AD$5:$AD$204,SAISIE_PROD!$A$5:$A$204,$B36,SAISIE_PROD!$AS$5:$AS$204,1)) | F36: =IF($B36="","",SUMIFS(SAISIE_PROD!$F$5:$F$204,SAISIE_PROD!$A$5:$A$204,$B36,SAISIE_PROD!$AS$5:$AS$204,1)) | G36: =IF($B36="","",SUMIFS(SAISIE_PROD!$P$5:$P$204,SAISIE_PROD!$A$5:$A$204,$B36,SAISIE_PROD!$AS$5:$AS$204,1)) | H36: =IF($B36="","",SUMIFS(SAISIE_PROD!$Q$5:$Q$204,SAISIE_PROD!$A$5:$A$204,$B36,SAISIE_PROD!$AS$5:$AS$204,1)) | I36: =IF($B36="","",SUMIFS(SAISIE_PROD!$R$5:$R$204,SAISIE_PROD!$A$5:$A$204,$B36,SAISIE_PROD!$AS$5:$AS$204,1)) | J36: =IF($B36="","",SUMIFS(SAISIE_PROD!$T$5:$T$204,SAISIE_PROD!$A$5:$A$204,$B36,SAISIE_PROD!$AS$5:$AS$204,1)) | K36: =IF($B36="","",SUMIFS(SAISIE_PROD!$X$5:$X$204,SAISIE_PROD!$A$5:$A$204,$B36,SAISIE_PROD!$AS$5:$AS$204,1)) | L36: =IF($B36="","",SUMIFS(SAISIE_PROD!$AC$5:$AC$204,SAISIE_PROD!$A$5:$A$204,$B36,SAISIE_PROD!$AS$5:$AS$204,1)) | M36: =IF(OR($B36="",$D36=0),"",$C36/$D36) | N36: =IF($B36="",NA(),$V$3) | O36: =IF(COUNT($M30:$M36)<3,"",AVERAGE($M30:$M36)) | P36: =IF(OR($B36="",$V$5=""),NA(),$V$6) | Q36: =IF(OR($B36="",$V$5=""),NA(),$V$7) | R36: =IF($M36="",NA(),$M36) | S36: =IF($O36="",NA(),$O36)
A37: 26 | B37: =IF($A37>DAY($B$8),"",DATE($B$3,$B$4,$A37)) | C37: =IF($B37="","",SUMIFS(SAISIE_PROD!$AE$5:$AE$204,SAISIE_PROD!$A$5:$A$204,$B37,SAISIE_PROD!$AS$5:$AS$204,1)) | D37: =IF($B37="","",SUMIFS(SAISIE_PROD!$AB$5:$AB$204,SAISIE_PROD!$A$5:$A$204,$B37,SAISIE_PROD!$AS$5:$AS$204,1)) | E37: =IF($B37="","",SUMIFS(SAISIE_PROD!$AD$5:$AD$204,SAISIE_PROD!$A$5:$A$204,$B37,SAISIE_PROD!$AS$5:$AS$204,1)) | F37: =IF($B37="","",SUMIFS(SAISIE_PROD!$F$5:$F$204,SAISIE_PROD!$A$5:$A$204,$B37,SAISIE_PROD!$AS$5:$AS$204,1)) | G37: =IF($B37="","",SUMIFS(SAISIE_PROD!$P$5:$P$204,SAISIE_PROD!$A$5:$A$204,$B37,SAISIE_PROD!$AS$5:$AS$204,1)) | H37: =IF($B37="","",SUMIFS(SAISIE_PROD!$Q$5:$Q$204,SAISIE_PROD!$A$5:$A$204,$B37,SAISIE_PROD!$AS$5:$AS$204,1)) | I37: =IF($B37="","",SUMIFS(SAISIE_PROD!$R$5:$R$204,SAISIE_PROD!$A$5:$A$204,$B37,SAISIE_PROD!$AS$5:$AS$204,1)) | J37: =IF($B37="","",SUMIFS(SAISIE_PROD!$T$5:$T$204,SAISIE_PROD!$A$5:$A$204,$B37,SAISIE_PROD!$AS$5:$AS$204,1)) | K37: =IF($B37="","",SUMIFS(SAISIE_PROD!$X$5:$X$204,SAISIE_PROD!$A$5:$A$204,$B37,SAISIE_PROD!$AS$5:$AS$204,1)) | L37: =IF($B37="","",SUMIFS(SAISIE_PROD!$AC$5:$AC$204,SAISIE_PROD!$A$5:$A$204,$B37,SAISIE_PROD!$AS$5:$AS$204,1)) | M37: =IF(OR($B37="",$D37=0),"",$C37/$D37) | N37: =IF($B37="",NA(),$V$3) | O37: =IF(COUNT($M31:$M37)<3,"",AVERAGE($M31:$M37)) | P37: =IF(OR($B37="",$V$5=""),NA(),$V$6) | Q37: =IF(OR($B37="",$V$5=""),NA(),$V$7) | R37: =IF($M37="",NA(),$M37) | S37: =IF($O37="",NA(),$O37)
A38: 27 | B38: =IF($A38>DAY($B$8),"",DATE($B$3,$B$4,$A38)) | C38: =IF($B38="","",SUMIFS(SAISIE_PROD!$AE$5:$AE$204,SAISIE_PROD!$A$5:$A$204,$B38,SAISIE_PROD!$AS$5:$AS$204,1)) | D38: =IF($B38="","",SUMIFS(SAISIE_PROD!$AB$5:$AB$204,SAISIE_PROD!$A$5:$A$204,$B38,SAISIE_PROD!$AS$5:$AS$204,1)) | E38: =IF($B38="","",SUMIFS(SAISIE_PROD!$AD$5:$AD$204,SAISIE_PROD!$A$5:$A$204,$B38,SAISIE_PROD!$AS$5:$AS$204,1)) | F38: =IF($B38="","",SUMIFS(SAISIE_PROD!$F$5:$F$204,SAISIE_PROD!$A$5:$A$204,$B38,SAISIE_PROD!$AS$5:$AS$204,1)) | G38: =IF($B38="","",SUMIFS(SAISIE_PROD!$P$5:$P$204,SAISIE_PROD!$A$5:$A$204,$B38,SAISIE_PROD!$AS$5:$AS$204,1)) | H38: =IF($B38="","",SUMIFS(SAISIE_PROD!$Q$5:$Q$204,SAISIE_PROD!$A$5:$A$204,$B38,SAISIE_PROD!$AS$5:$AS$204,1)) | I38: =IF($B38="","",SUMIFS(SAISIE_PROD!$R$5:$R$204,SAISIE_PROD!$A$5:$A$204,$B38,SAISIE_PROD!$AS$5:$AS$204,1)) | J38: =IF($B38="","",SUMIFS(SAISIE_PROD!$T$5:$T$204,SAISIE_PROD!$A$5:$A$204,$B38,SAISIE_PROD!$AS$5:$AS$204,1)) | K38: =IF($B38="","",SUMIFS(SAISIE_PROD!$X$5:$X$204,SAISIE_PROD!$A$5:$A$204,$B38,SAISIE_PROD!$AS$5:$AS$204,1)) | L38: =IF($B38="","",SUMIFS(SAISIE_PROD!$AC$5:$AC$204,SAISIE_PROD!$A$5:$A$204,$B38,SAISIE_PROD!$AS$5:$AS$204,1)) | M38: =IF(OR($B38="",$D38=0),"",$C38/$D38) | N38: =IF($B38="",NA(),$V$3) | O38: =IF(COUNT($M32:$M38)<3,"",AVERAGE($M32:$M38)) | P38: =IF(OR($B38="",$V$5=""),NA(),$V$6) | Q38: =IF(OR($B38="",$V$5=""),NA(),$V$7) | R38: =IF($M38="",NA(),$M38) | S38: =IF($O38="",NA(),$O38)
A39: 28 | B39: =IF($A39>DAY($B$8),"",DATE($B$3,$B$4,$A39)) | C39: =IF($B39="","",SUMIFS(SAISIE_PROD!$AE$5:$AE$204,SAISIE_PROD!$A$5:$A$204,$B39,SAISIE_PROD!$AS$5:$AS$204,1)) | D39: =IF($B39="","",SUMIFS(SAISIE_PROD!$AB$5:$AB$204,SAISIE_PROD!$A$5:$A$204,$B39,SAISIE_PROD!$AS$5:$AS$204,1)) | E39: =IF($B39="","",SUMIFS(SAISIE_PROD!$AD$5:$AD$204,SAISIE_PROD!$A$5:$A$204,$B39,SAISIE_PROD!$AS$5:$AS$204,1)) | F39: =IF($B39="","",SUMIFS(SAISIE_PROD!$F$5:$F$204,SAISIE_PROD!$A$5:$A$204,$B39,SAISIE_PROD!$AS$5:$AS$204,1)) | G39: =IF($B39="","",SUMIFS(SAISIE_PROD!$P$5:$P$204,SAISIE_PROD!$A$5:$A$204,$B39,SAISIE_PROD!$AS$5:$AS$204,1)) | H39: =IF($B39="","",SUMIFS(SAISIE_PROD!$Q$5:$Q$204,SAISIE_PROD!$A$5:$A$204,$B39,SAISIE_PROD!$AS$5:$AS$204,1)) | I39: =IF($B39="","",SUMIFS(SAISIE_PROD!$R$5:$R$204,SAISIE_PROD!$A$5:$A$204,$B39,SAISIE_PROD!$AS$5:$AS$204,1)) | J39: =IF($B39="","",SUMIFS(SAISIE_PROD!$T$5:$T$204,SAISIE_PROD!$A$5:$A$204,$B39,SAISIE_PROD!$AS$5:$AS$204,1)) | K39: =IF($B39="","",SUMIFS(SAISIE_PROD!$X$5:$X$204,SAISIE_PROD!$A$5:$A$204,$B39,SAISIE_PROD!$AS$5:$AS$204,1)) | L39: =IF($B39="","",SUMIFS(SAISIE_PROD!$AC$5:$AC$204,SAISIE_PROD!$A$5:$A$204,$B39,SAISIE_PROD!$AS$5:$AS$204,1)) | M39: =IF(OR($B39="",$D39=0),"",$C39/$D39) | N39: =IF($B39="",NA(),$V$3) | O39: =IF(COUNT($M33:$M39)<3,"",AVERAGE($M33:$M39)) | P39: =IF(OR($B39="",$V$5=""),NA(),$V$6) | Q39: =IF(OR($B39="",$V$5=""),NA(),$V$7) | R39: =IF($M39="",NA(),$M39) | S39: =IF($O39="",NA(),$O39)
A40: 29 | B40: =IF($A40>DAY($B$8),"",DATE($B$3,$B$4,$A40)) | C40: =IF($B40="","",SUMIFS(SAISIE_PROD!$AE$5:$AE$204,SAISIE_PROD!$A$5:$A$204,$B40,SAISIE_PROD!$AS$5:$AS$204,1)) | D40: =IF($B40="","",SUMIFS(SAISIE_PROD!$AB$5:$AB$204,SAISIE_PROD!$A$5:$A$204,$B40,SAISIE_PROD!$AS$5:$AS$204,1)) | E40: =IF($B40="","",SUMIFS(SAISIE_PROD!$AD$5:$AD$204,SAISIE_PROD!$A$5:$A$204,$B40,SAISIE_PROD!$AS$5:$AS$204,1)) | F40: =IF($B40="","",SUMIFS(SAISIE_PROD!$F$5:$F$204,SAISIE_PROD!$A$5:$A$204,$B40,SAISIE_PROD!$AS$5:$AS$204,1)) | G40: =IF($B40="","",SUMIFS(SAISIE_PROD!$P$5:$P$204,SAISIE_PROD!$A$5:$A$204,$B40,SAISIE_PROD!$AS$5:$AS$204,1)) | H40: =IF($B40="","",SUMIFS(SAISIE_PROD!$Q$5:$Q$204,SAISIE_PROD!$A$5:$A$204,$B40,SAISIE_PROD!$AS$5:$AS$204,1)) | I40: =IF($B40="","",SUMIFS(SAISIE_PROD!$R$5:$R$204,SAISIE_PROD!$A$5:$A$204,$B40,SAISIE_PROD!$AS$5:$AS$204,1)) | J40: =IF($B40="","",SUMIFS(SAISIE_PROD!$T$5:$T$204,SAISIE_PROD!$A$5:$A$204,$B40,SAISIE_PROD!$AS$5:$AS$204,1)) | K40: =IF($B40="","",SUMIFS(SAISIE_PROD!$X$5:$X$204,SAISIE_PROD!$A$5:$A$204,$B40,SAISIE_PROD!$AS$5:$AS$204,1)) | L40: =IF($B40="","",SUMIFS(SAISIE_PROD!$AC$5:$AC$204,SAISIE_PROD!$A$5:$A$204,$B40,SAISIE_PROD!$AS$5:$AS$204,1)) | M40: =IF(OR($B40="",$D40=0),"",$C40/$D40) | N40: =IF($B40="",NA(),$V$3) | O40: =IF(COUNT($M34:$M40)<3,"",AVERAGE($M34:$M40)) | P40: =IF(OR($B40="",$V$5=""),NA(),$V$6) | Q40: =IF(OR($B40="",$V$5=""),NA(),$V$7) | R40: =IF($M40="",NA(),$M40) | S40: =IF($O40="",NA(),$O40)
A41: 30 | B41: =IF($A41>DAY($B$8),"",DATE($B$3,$B$4,$A41)) | C41: =IF($B41="","",SUMIFS(SAISIE_PROD!$AE$5:$AE$204,SAISIE_PROD!$A$5:$A$204,$B41,SAISIE_PROD!$AS$5:$AS$204,1)) | D41: =IF($B41="","",SUMIFS(SAISIE_PROD!$AB$5:$AB$204,SAISIE_PROD!$A$5:$A$204,$B41,SAISIE_PROD!$AS$5:$AS$204,1)) | E41: =IF($B41="","",SUMIFS(SAISIE_PROD!$AD$5:$AD$204,SAISIE_PROD!$A$5:$A$204,$B41,SAISIE_PROD!$AS$5:$AS$204,1)) | F41: =IF($B41="","",SUMIFS(SAISIE_PROD!$F$5:$F$204,SAISIE_PROD!$A$5:$A$204,$B41,SAISIE_PROD!$AS$5:$AS$204,1)) | G41: =IF($B41="","",SUMIFS(SAISIE_PROD!$P$5:$P$204,SAISIE_PROD!$A$5:$A$204,$B41,SAISIE_PROD!$AS$5:$AS$204,1)) | H41: =IF($B41="","",SUMIFS(SAISIE_PROD!$Q$5:$Q$204,SAISIE_PROD!$A$5:$A$204,$B41,SAISIE_PROD!$AS$5:$AS$204,1)) | I41: =IF($B41="","",SUMIFS(SAISIE_PROD!$R$5:$R$204,SAISIE_PROD!$A$5:$A$204,$B41,SAISIE_PROD!$AS$5:$AS$204,1)) | J41: =IF($B41="","",SUMIFS(SAISIE_PROD!$T$5:$T$204,SAISIE_PROD!$A$5:$A$204,$B41,SAISIE_PROD!$AS$5:$AS$204,1)) | K41: =IF($B41="","",SUMIFS(SAISIE_PROD!$X$5:$X$204,SAISIE_PROD!$A$5:$A$204,$B41,SAISIE_PROD!$AS$5:$AS$204,1)) | L41: =IF($B41="","",SUMIFS(SAISIE_PROD!$AC$5:$AC$204,SAISIE_PROD!$A$5:$A$204,$B41,SAISIE_PROD!$AS$5:$AS$204,1)) | M41: =IF(OR($B41="",$D41=0),"",$C41/$D41) | N41: =IF($B41="",NA(),$V$3) | O41: =IF(COUNT($M35:$M41)<3,"",AVERAGE($M35:$M41)) | P41: =IF(OR($B41="",$V$5=""),NA(),$V$6) | Q41: =IF(OR($B41="",$V$5=""),NA(),$V$7) | R41: =IF($M41="",NA(),$M41) | S41: =IF($O41="",NA(),$O41)
A42: 31 | B42: =IF($A42>DAY($B$8),"",DATE($B$3,$B$4,$A42)) | C42: =IF($B42="","",SUMIFS(SAISIE_PROD!$AE$5:$AE$204,SAISIE_PROD!$A$5:$A$204,$B42,SAISIE_PROD!$AS$5:$AS$204,1)) | D42: =IF($B42="","",SUMIFS(SAISIE_PROD!$AB$5:$AB$204,SAISIE_PROD!$A$5:$A$204,$B42,SAISIE_PROD!$AS$5:$AS$204,1)) | E42: =IF($B42="","",SUMIFS(SAISIE_PROD!$AD$5:$AD$204,SAISIE_PROD!$A$5:$A$204,$B42,SAISIE_PROD!$AS$5:$AS$204,1)) | F42: =IF($B42="","",SUMIFS(SAISIE_PROD!$F$5:$F$204,SAISIE_PROD!$A$5:$A$204,$B42,SAISIE_PROD!$AS$5:$AS$204,1)) | G42: =IF($B42="","",SUMIFS(SAISIE_PROD!$P$5:$P$204,SAISIE_PROD!$A$5:$A$204,$B42,SAISIE_PROD!$AS$5:$AS$204,1)) | H42: =IF($B42="","",SUMIFS(SAISIE_PROD!$Q$5:$Q$204,SAISIE_PROD!$A$5:$A$204,$B42,SAISIE_PROD!$AS$5:$AS$204,1)) | I42: =IF($B42="","",SUMIFS(SAISIE_PROD!$R$5:$R$204,SAISIE_PROD!$A$5:$A$204,$B42,SAISIE_PROD!$AS$5:$AS$204,1)) | J42: =IF($B42="","",SUMIFS(SAISIE_PROD!$T$5:$T$204,SAISIE_PROD!$A$5:$A$204,$B42,SAISIE_PROD!$AS$5:$AS$204,1)) | K42: =IF($B42="","",SUMIFS(SAISIE_PROD!$X$5:$X$204,SAISIE_PROD!$A$5:$A$204,$B42,SAISIE_PROD!$AS$5:$AS$204,1)) | L42: =IF($B42="","",SUMIFS(SAISIE_PROD!$AC$5:$AC$204,SAISIE_PROD!$A$5:$A$204,$B42,SAISIE_PROD!$AS$5:$AS$204,1)) | M42: =IF(OR($B42="",$D42=0),"",$C42/$D42) | N42: =IF($B42="",NA(),$V$3) | O42: =IF(COUNT($M36:$M42)<3,"",AVERAGE($M36:$M42)) | P42: =IF(OR($B42="",$V$5=""),NA(),$V$6) | Q42: =IF(OR($B42="",$V$5=""),NA(),$V$7) | R42: =IF($M42="",NA(),$M42) | S42: =IF($O42="",NA(),$O42)
A44: PARETO DES PERTES DE TEMPS SUBIES (hors arrêts planifiés)
A45: Rubrique de perte | B45: Minutes perdues | C45: Valeur départagée | D45: Rang | F45: Rubrique classée | G45: Minutes | H45: Part | I45: Part cumulée
A46: Pannes machine | B46: =SUMIFS(SAISIE_PROD!$H$5:$H$204,SAISIE_PROD!$A$5:$A$204,">="&$B$7,SAISIE_PROD!$A$5:$A$204,"<="&$B$8,SAISIE_PROD!$AS$5:$AS$204,1) | C46: =$B46+(54-ROW())/100000 | D46: =RANK($C46,$C$46:$C$53) | F46: =INDEX($A$46:$A$53,MATCH(LARGE($C$46:$C$53,1),$C$46:$C$53,0)) | G46: =INDEX($B$46:$B$53,MATCH(LARGE($C$46:$C$53,1),$C$46:$C$53,0)) | H46: =IFERROR($G46/SUM($B$46:$B$53),"") | I46: =IFERROR(SUM($G$46:$G46)/SUM($B$46:$B$53),"")
A47: Changement de série | B47: =SUMIFS(SAISIE_PROD!$I$5:$I$204,SAISIE_PROD!$A$5:$A$204,">="&$B$7,SAISIE_PROD!$A$5:$A$204,"<="&$B$8,SAISIE_PROD!$AS$5:$AS$204,1) | C47: =$B47+(54-ROW())/100000 | D47: =RANK($C47,$C$46:$C$53) | F47: =INDEX($A$46:$A$53,MATCH(LARGE($C$46:$C$53,2),$C$46:$C$53,0)) | G47: =INDEX($B$46:$B$53,MATCH(LARGE($C$46:$C$53,2),$C$46:$C$53,0)) | H47: =IFERROR($G47/SUM($B$46:$B$53),"") | I47: =IFERROR(SUM($G$46:$G47)/SUM($B$46:$B$53),"")
A48: Réglages et micro-arrêts | B48: =SUMIFS(SAISIE_PROD!$J$5:$J$204,SAISIE_PROD!$A$5:$A$204,">="&$B$7,SAISIE_PROD!$A$5:$A$204,"<="&$B$8,SAISIE_PROD!$AS$5:$AS$204,1) | C48: =$B48+(54-ROW())/100000 | D48: =RANK($C48,$C$46:$C$53) | F48: =INDEX($A$46:$A$53,MATCH(LARGE($C$46:$C$53,3),$C$46:$C$53,0)) | G48: =INDEX($B$46:$B$53,MATCH(LARGE($C$46:$C$53,3),$C$46:$C$53,0)) | H48: =IFERROR($G48/SUM($B$46:$B$53),"") | I48: =IFERROR(SUM($G$46:$G48)/SUM($B$46:$B$53),"")
A49: Manque matière | B49: =SUMIFS(SAISIE_PROD!$K$5:$K$204,SAISIE_PROD!$A$5:$A$204,">="&$B$7,SAISIE_PROD!$A$5:$A$204,"<="&$B$8,SAISIE_PROD!$AS$5:$AS$204,1) | C49: =$B49+(54-ROW())/100000 | D49: =RANK($C49,$C$46:$C$53) | F49: =INDEX($A$46:$A$53,MATCH(LARGE($C$46:$C$53,4),$C$46:$C$53,0)) | G49: =INDEX($B$46:$B$53,MATCH(LARGE($C$46:$C$53,4),$C$46:$C$53,0)) | H49: =IFERROR($G49/SUM($B$46:$B$53),"") | I49: =IFERROR(SUM($G$46:$G49)/SUM($B$46:$B$53),"")
A50: Manque personnel | B50: =SUMIFS(SAISIE_PROD!$L$5:$L$204,SAISIE_PROD!$A$5:$A$204,">="&$B$7,SAISIE_PROD!$A$5:$A$204,"<="&$B$8,SAISIE_PROD!$AS$5:$AS$204,1) | C50: =$B50+(54-ROW())/100000 | D50: =RANK($C50,$C$46:$C$53) | F50: =INDEX($A$46:$A$53,MATCH(LARGE($C$46:$C$53,5),$C$46:$C$53,0)) | G50: =INDEX($B$46:$B$53,MATCH(LARGE($C$46:$C$53,5),$C$46:$C$53,0)) | H50: =IFERROR($G50/SUM($B$46:$B$53),"") | I50: =IFERROR(SUM($G$46:$G50)/SUM($B$46:$B$53),"")
A51: Autres arrêts subis | B51: =SUMIFS(SAISIE_PROD!$M$5:$M$204,SAISIE_PROD!$A$5:$A$204,">="&$B$7,SAISIE_PROD!$A$5:$A$204,"<="&$B$8,SAISIE_PROD!$AS$5:$AS$204,1) | C51: =$B51+(54-ROW())/100000 | D51: =RANK($C51,$C$46:$C$53) | F51: =INDEX($A$46:$A$53,MATCH(LARGE($C$46:$C$53,6),$C$46:$C$53,0)) | G51: =INDEX($B$46:$B$53,MATCH(LARGE($C$46:$C$53,6),$C$46:$C$53,0)) | H51: =IFERROR($G51/SUM($B$46:$B$53),"") | I51: =IFERROR(SUM($G$46:$G51)/SUM($B$46:$B$53),"")
A52: Perte de cadence | B52: =SUMIFS(SAISIE_PROD!$AP$5:$AP$204,SAISIE_PROD!$A$5:$A$204,">="&$B$7,SAISIE_PROD!$A$5:$A$204,"<="&$B$8,SAISIE_PROD!$AS$5:$AS$204,1) | C52: =$B52+(54-ROW())/100000 | D52: =RANK($C52,$C$46:$C$53) | F52: =INDEX($A$46:$A$53,MATCH(LARGE($C$46:$C$53,7),$C$46:$C$53,0)) | G52: =INDEX($B$46:$B$53,MATCH(LARGE($C$46:$C$53,7),$C$46:$C$53,0)) | H52: =IFERROR($G52/SUM($B$46:$B$53),"") | I52: =IFERROR(SUM($G$46:$G52)/SUM($B$46:$B$53),"")
A53: Pertes non-qualité | B53: =SUMIFS(SAISIE_PROD!$AQ$5:$AQ$204,SAISIE_PROD!$A$5:$A$204,">="&$B$7,SAISIE_PROD!$A$5:$A$204,"<="&$B$8,SAISIE_PROD!$AS$5:$AS$204,1) | C53: =$B53+(54-ROW())/100000 | D53: =RANK($C53,$C$46:$C$53) | F53: =INDEX($A$46:$A$53,MATCH(LARGE($C$46:$C$53,8),$C$46:$C$53,0)) | G53: =INDEX($B$46:$B$53,MATCH(LARGE($C$46:$C$53,8),$C$46:$C$53,0)) | H53: =IFERROR($G53/SUM($B$46:$B$53),"") | I53: =IFERROR(SUM($G$46:$G53)/SUM($B$46:$B$53),"")
A55: CASCADE DES PERTES DE TEMPS (du temps d'ouverture au temps utile)
A56: Étape | B56: Socle (invisible) | C56: Valeur affichée | D56: Jalon
A57: Temps d'ouverture | B57: 0 | C57: =$V$8 | D57: 1
A58: Arrêts planifiés | B58: =$V$8-$V$9 | C58: =$V$9 | D58: 0
A59: Temps requis | B59: 0 | C59: =$V$18 | D59: 1
A60: Pannes machine | B60: =$V$18-$V$10 | C60: =$V$10 | D60: 0
A61: Changement de série | B61: =$V$18-SUM($V$10:$V$11) | C61: =$V$11 | D61: 0
A62: Réglages, micro-arrêts | B62: =$V$18-SUM($V$10:$V$12) | C62: =$V$12 | D62: 0
A63: Manque matière | B63: =$V$18-SUM($V$10:$V$13) | C63: =$V$13 | D63: 0
A64: Manque personnel | B64: =$V$18-SUM($V$10:$V$14) | C64: =$V$14 | D64: 0
A65: Autres arrêts subis | B65: =$V$18-SUM($V$10:$V$15) | C65: =$V$15 | D65: 0
A66: Temps de marche | B66: 0 | C66: =$V$19 | D66: 1
A67: Perte de cadence | B67: =$V$19-$V$16 | C67: =$V$16 | D67: 0
A68: Pertes non-qualité | B68: =$V$19-SUM($V$16:$V$17) | C68: =$V$17 | D68: 0
A69: Temps utile | B69: 0 | C69: =$V$20 | D69: 1
A70: TRS PAR LIGNE DE PRODUCTION (mois sélectionné — comparaison entre lignes, hors filtres du cockpit)
A71: Libellé | B71: Temps utile | C71: Temps requis | D71: TRS | E71: TRS (graphique)
A72: =IF(PARAMETRES!$I7="","",PARAMETRES!$I7) | B72: =IF($A72="","",SUMIFS(SAISIE_PROD!$AE$5:$AE$204,SAISIE_PROD!$A$5:$A$204,">="&$B$7,SAISIE_PROD!$A$5:$A$204,"<="&$B$8,SAISIE_PROD!$C$5:$C$204,$A72)) | C72: =IF($A72="","",SUMIFS(SAISIE_PROD!$AB$5:$AB$204,SAISIE_PROD!$A$5:$A$204,">="&$B$7,SAISIE_PROD!$A$5:$A$204,"<="&$B$8,SAISIE_PROD!$C$5:$C$204,$A72)) | D72: =IF(OR($A72="",$C72=0),"",$B72/$C72) | E72: =IF($D72="",NA(),$D72)
A73: =IF(PARAMETRES!$I8="","",PARAMETRES!$I8) | B73: =IF($A73="","",SUMIFS(SAISIE_PROD!$AE$5:$AE$204,SAISIE_PROD!$A$5:$A$204,">="&$B$7,SAISIE_PROD!$A$5:$A$204,"<="&$B$8,SAISIE_PROD!$C$5:$C$204,$A73)) | C73: =IF($A73="","",SUMIFS(SAISIE_PROD!$AB$5:$AB$204,SAISIE_PROD!$A$5:$A$204,">="&$B$7,SAISIE_PROD!$A$5:$A$204,"<="&$B$8,SAISIE_PROD!$C$5:$C$204,$A73)) | D73: =IF(OR($A73="",$C73=0),"",$B73/$C73) | E73: =IF($D73="",NA(),$D73)
A74: =IF(PARAMETRES!$I9="","",PARAMETRES!$I9) | B74: =IF($A74="","",SUMIFS(SAISIE_PROD!$AE$5:$AE$204,SAISIE_PROD!$A$5:$A$204,">="&$B$7,SAISIE_PROD!$A$5:$A$204,"<="&$B$8,SAISIE_PROD!$C$5:$C$204,$A74)) | C74: =IF($A74="","",SUMIFS(SAISIE_PROD!$AB$5:$AB$204,SAISIE_PROD!$A$5:$A$204,">="&$B$7,SAISIE_PROD!$A$5:$A$204,"<="&$B$8,SAISIE_PROD!$C$5:$C$204,$A74)) | D74: =IF(OR($A74="",$C74=0),"",$B74/$C74) | E74: =IF($D74="",NA(),$D74)
A75: =IF(PARAMETRES!$I10="","",PARAMETRES!$I10) | B75: =IF($A75="","",SUMIFS(SAISIE_PROD!$AE$5:$AE$204,SAISIE_PROD!$A$5:$A$204,">="&$B$7,SAISIE_PROD!$A$5:$A$204,"<="&$B$8,SAISIE_PROD!$C$5:$C$204,$A75)) | C75: =IF($A75="","",SUMIFS(SAISIE_PROD!$AB$5:$AB$204,SAISIE_PROD!$A$5:$A$204,">="&$B$7,SAISIE_PROD!$A$5:$A$204,"<="&$B$8,SAISIE_PROD!$C$5:$C$204,$A75)) | D75: =IF(OR($A75="",$C75=0),"",$B75/$C75) | E75: =IF($D75="",NA(),$D75)
A76: =IF(PARAMETRES!$I11="","",PARAMETRES!$I11) | B76: =IF($A76="","",SUMIFS(SAISIE_PROD!$AE$5:$AE$204,SAISIE_PROD!$A$5:$A$204,">="&$B$7,SAISIE_PROD!$A$5:$A$204,"<="&$B$8,SAISIE_PROD!$C$5:$C$204,$A76)) | C76: =IF($A76="","",SUMIFS(SAISIE_PROD!$AB$5:$AB$204,SAISIE_PROD!$A$5:$A$204,">="&$B$7,SAISIE_PROD!$A$5:$A$204,"<="&$B$8,SAISIE_PROD!$C$5:$C$204,$A76)) | D76: =IF(OR($A76="",$C76=0),"",$B76/$C76) | E76: =IF($D76="",NA(),$D76)
A77: TRS PAR ÉQUIPE (mois sélectionné — comparaison entre équipes, hors filtres du cockpit)
A78: Libellé | B78: Temps utile | C78: Temps requis | D78: TRS | E78: TRS (graphique)
A79: =IF(PARAMETRES!$J7="","",PARAMETRES!$J7) | B79: =IF($A79="","",SUMIFS(SAISIE_PROD!$AE$5:$AE$204,SAISIE_PROD!$A$5:$A$204,">="&$B$7,SAISIE_PROD!$A$5:$A$204,"<="&$B$8,SAISIE_PROD!$B$5:$B$204,$A79)) | C79: =IF($A79="","",SUMIFS(SAISIE_PROD!$AB$5:$AB$204,SAISIE_PROD!$A$5:$A$204,">="&$B$7,SAISIE_PROD!$A$5:$A$204,"<="&$B$8,SAISIE_PROD!$B$5:$B$204,$A79)) | D79: =IF(OR($A79="",$C79=0),"",$B79/$C79) | E79: =IF($D79="",NA(),$D79)
A80: =IF(PARAMETRES!$J8="","",PARAMETRES!$J8) | B80: =IF($A80="","",SUMIFS(SAISIE_PROD!$AE$5:$AE$204,SAISIE_PROD!$A$5:$A$204,">="&$B$7,SAISIE_PROD!$A$5:$A$204,"<="&$B$8,SAISIE_PROD!$B$5:$B$204,$A80)) | C80: =IF($A80="","",SUMIFS(SAISIE_PROD!$AB$5:$AB$204,SAISIE_PROD!$A$5:$A$204,">="&$B$7,SAISIE_PROD!$A$5:$A$204,"<="&$B$8,SAISIE_PROD!$B$5:$B$204,$A80)) | D80: =IF(OR($A80="",$C80=0),"",$B80/$C80) | E80: =IF($D80="",NA(),$D80)
A81: =IF(PARAMETRES!$J9="","",PARAMETRES!$J9) | B81: =IF($A81="","",SUMIFS(SAISIE_PROD!$AE$5:$AE$204,SAISIE_PROD!$A$5:$A$204,">="&$B$7,SAISIE_PROD!$A$5:$A$204,"<="&$B$8,SAISIE_PROD!$B$5:$B$204,$A81)) | C81: =IF($A81="","",SUMIFS(SAISIE_PROD!$AB$5:$AB$204,SAISIE_PROD!$A$5:$A$204,">="&$B$7,SAISIE_PROD!$A$5:$A$204,"<="&$B$8,SAISIE_PROD!$B$5:$B$204,$A81)) | D81: =IF(OR($A81="",$C81=0),"",$B81/$C81) | E81: =IF($D81="",NA(),$D81)
A82: =IF(PARAMETRES!$J10="","",PARAMETRES!$J10) | B82: =IF($A82="","",SUMIFS(SAISIE_PROD!$AE$5:$AE$204,SAISIE_PROD!$A$5:$A$204,">="&$B$7,SAISIE_PROD!$A$5:$A$204,"<="&$B$8,SAISIE_PROD!$B$5:$B$204,$A82)) | C82: =IF($A82="","",SUMIFS(SAISIE_PROD!$AB$5:$AB$204,SAISIE_PROD!$A$5:$A$204,">="&$B$7,SAISIE_PROD!$A$5:$A$204,"<="&$B$8,SAISIE_PROD!$B$5:$B$204,$A82)) | D82: =IF(OR($A82="",$C82=0),"",$B82/$C82) | E82: =IF($D82="",NA(),$D82)
A83: =IF(PARAMETRES!$J11="","",PARAMETRES!$J11) | B83: =IF($A83="","",SUMIFS(SAISIE_PROD!$AE$5:$AE$204,SAISIE_PROD!$A$5:$A$204,">="&$B$7,SAISIE_PROD!$A$5:$A$204,"<="&$B$8,SAISIE_PROD!$B$5:$B$204,$A83)) | C83: =IF($A83="","",SUMIFS(SAISIE_PROD!$AB$5:$AB$204,SAISIE_PROD!$A$5:$A$204,">="&$B$7,SAISIE_PROD!$A$5:$A$204,"<="&$B$8,SAISIE_PROD!$B$5:$B$204,$A83)) | D83: =IF(OR($A83="",$C83=0),"",$B83/$C83) | E83: =IF($D83="",NA(),$D83)
A86: HISTORIQUE SUR 13 MOIS GLISSANTS (même périmètre de filtrage)
A87: Mois | B87: Date de début | C87: Temps utile | D87: Temps requis | E87: Temps de marche | F87: Temps d'ouverture | G87: Qté produite | H87: Qté conforme | I87: Qté retouchée | J87: Qté demandée | K87: Accidents | L87: TRS | M87: Disponibilité | N87: Performance | O87: Qualité RFT | P87: TRG | Q87: Taux de service | R87: TRS (graphique) | S87: Cible (graphique)
A88: =INDEX(PARAMETRES!$AM$7:$AM$18,MONTH($B88))&" "&TEXT(YEAR($B88),"0000") | B88: =EDATE($B$7,-12) | C88: =SUMIFS(SAISIE_PROD!$AE$5:$AE$204,SAISIE_PROD!$A$5:$A$204,">="&$B88,SAISIE_PROD!$A$5:$A$204,"<"&EDATE($B88,1),SAISIE_PROD!$AS$5:$AS$204,1) | D88: =SUMIFS(SAISIE_PROD!$AB$5:$AB$204,SAISIE_PROD!$A$5:$A$204,">="&$B88,SAISIE_PROD!$A$5:$A$204,"<"&EDATE($B88,1),SAISIE_PROD!$AS$5:$AS$204,1) | E88: =SUMIFS(SAISIE_PROD!$AD$5:$AD$204,SAISIE_PROD!$A$5:$A$204,">="&$B88,SAISIE_PROD!$A$5:$A$204,"<"&EDATE($B88,1),SAISIE_PROD!$AS$5:$AS$204,1) | F88: =SUMIFS(SAISIE_PROD!$F$5:$F$204,SAISIE_PROD!$A$5:$A$204,">="&$B88,SAISIE_PROD!$A$5:$A$204,"<"&EDATE($B88,1),SAISIE_PROD!$AS$5:$AS$204,1) | G88: =SUMIFS(SAISIE_PROD!$P$5:$P$204,SAISIE_PROD!$A$5:$A$204,">="&$B88,SAISIE_PROD!$A$5:$A$204,"<"&EDATE($B88,1),SAISIE_PROD!$AS$5:$AS$204,1) | H88: =SUMIFS(SAISIE_PROD!$Q$5:$Q$204,SAISIE_PROD!$A$5:$A$204,">="&$B88,SAISIE_PROD!$A$5:$A$204,"<"&EDATE($B88,1),SAISIE_PROD!$AS$5:$AS$204,1) | I88: =SUMIFS(SAISIE_PROD!$R$5:$R$204,SAISIE_PROD!$A$5:$A$204,">="&$B88,SAISIE_PROD!$A$5:$A$204,"<"&EDATE($B88,1),SAISIE_PROD!$AS$5:$AS$204,1) | J88: =SUMIFS(SAISIE_PROD!$T$5:$T$204,SAISIE_PROD!$A$5:$A$204,">="&$B88,SAISIE_PROD!$A$5:$A$204,"<"&EDATE($B88,1),SAISIE_PROD!$AS$5:$AS$204,1) | K88: =SUMIFS(SAISIE_PROD!$X$5:$X$204,SAISIE_PROD!$A$5:$A$204,">="&$B88,SAISIE_PROD!$A$5:$A$204,"<"&EDATE($B88,1),SAISIE_PROD!$AS$5:$AS$204,1) | L88: =IFERROR($C88/$D88,"") | M88: =IFERROR($E88/$D88,"") | N88: =IFERROR($C88*($G88/$H88)/$E88,"") | O88: =IFERROR($H88/$G88,"") | P88: =IFERROR($C88/$F88,"") | Q88: =IFERROR(($H88+$I88)/$J88,"") | R88: =IF($L88="",NA(),$L88) | S88: =$V$3
A89: =INDEX(PARAMETRES!$AM$7:$AM$18,MONTH($B89))&" "&TEXT(YEAR($B89),"0000") | B89: =EDATE($B$7,-11) | C89: =SUMIFS(SAISIE_PROD!$AE$5:$AE$204,SAISIE_PROD!$A$5:$A$204,">="&$B89,SAISIE_PROD!$A$5:$A$204,"<"&EDATE($B89,1),SAISIE_PROD!$AS$5:$AS$204,1) | D89: =SUMIFS(SAISIE_PROD!$AB$5:$AB$204,SAISIE_PROD!$A$5:$A$204,">="&$B89,SAISIE_PROD!$A$5:$A$204,"<"&EDATE($B89,1),SAISIE_PROD!$AS$5:$AS$204,1) | E89: =SUMIFS(SAISIE_PROD!$AD$5:$AD$204,SAISIE_PROD!$A$5:$A$204,">="&$B89,SAISIE_PROD!$A$5:$A$204,"<"&EDATE($B89,1),SAISIE_PROD!$AS$5:$AS$204,1) | F89: =SUMIFS(SAISIE_PROD!$F$5:$F$204,SAISIE_PROD!$A$5:$A$204,">="&$B89,SAISIE_PROD!$A$5:$A$204,"<"&EDATE($B89,1),SAISIE_PROD!$AS$5:$AS$204,1) | G89: =SUMIFS(SAISIE_PROD!$P$5:$P$204,SAISIE_PROD!$A$5:$A$204,">="&$B89,SAISIE_PROD!$A$5:$A$204,"<"&EDATE($B89,1),SAISIE_PROD!$AS$5:$AS$204,1) | H89: =SUMIFS(SAISIE_PROD!$Q$5:$Q$204,SAISIE_PROD!$A$5:$A$204,">="&$B89,SAISIE_PROD!$A$5:$A$204,"<"&EDATE($B89,1),SAISIE_PROD!$AS$5:$AS$204,1) | I89: =SUMIFS(SAISIE_PROD!$R$5:$R$204,SAISIE_PROD!$A$5:$A$204,">="&$B89,SAISIE_PROD!$A$5:$A$204,"<"&EDATE($B89,1),SAISIE_PROD!$AS$5:$AS$204,1) | J89: =SUMIFS(SAISIE_PROD!$T$5:$T$204,SAISIE_PROD!$A$5:$A$204,">="&$B89,SAISIE_PROD!$A$5:$A$204,"<"&EDATE($B89,1),SAISIE_PROD!$AS$5:$AS$204,1) | K89: =SUMIFS(SAISIE_PROD!$X$5:$X$204,SAISIE_PROD!$A$5:$A$204,">="&$B89,SAISIE_PROD!$A$5:$A$204,"<"&EDATE($B89,1),SAISIE_PROD!$AS$5:$AS$204,1) | L89: =IFERROR($C89/$D89,"") | M89: =IFERROR($E89/$D89,"") | N89: =IFERROR($C89*($G89/$H89)/$E89,"") | O89: =IFERROR($H89/$G89,"") | P89: =IFERROR($C89/$F89,"") | Q89: =IFERROR(($H89+$I89)/$J89,"") | R89: =IF($L89="",NA(),$L89) | S89: =$V$3
A90: =INDEX(PARAMETRES!$AM$7:$AM$18,MONTH($B90))&" "&TEXT(YEAR($B90),"0000") | B90: =EDATE($B$7,-10) | C90: =SUMIFS(SAISIE_PROD!$AE$5:$AE$204,SAISIE_PROD!$A$5:$A$204,">="&$B90,SAISIE_PROD!$A$5:$A$204,"<"&EDATE($B90,1),SAISIE_PROD!$AS$5:$AS$204,1) | D90: =SUMIFS(SAISIE_PROD!$AB$5:$AB$204,SAISIE_PROD!$A$5:$A$204,">="&$B90,SAISIE_PROD!$A$5:$A$204,"<"&EDATE($B90,1),SAISIE_PROD!$AS$5:$AS$204,1) | E90: =SUMIFS(SAISIE_PROD!$AD$5:$AD$204,SAISIE_PROD!$A$5:$A$204,">="&$B90,SAISIE_PROD!$A$5:$A$204,"<"&EDATE($B90,1),SAISIE_PROD!$AS$5:$AS$204,1) | F90: =SUMIFS(SAISIE_PROD!$F$5:$F$204,SAISIE_PROD!$A$5:$A$204,">="&$B90,SAISIE_PROD!$A$5:$A$204,"<"&EDATE($B90,1),SAISIE_PROD!$AS$5:$AS$204,1) | G90: =SUMIFS(SAISIE_PROD!$P$5:$P$204,SAISIE_PROD!$A$5:$A$204,">="&$B90,SAISIE_PROD!$A$5:$A$204,"<"&EDATE($B90,1),SAISIE_PROD!$AS$5:$AS$204,1) | H90: =SUMIFS(SAISIE_PROD!$Q$5:$Q$204,SAISIE_PROD!$A$5:$A$204,">="&$B90,SAISIE_PROD!$A$5:$A$204,"<"&EDATE($B90,1),SAISIE_PROD!$AS$5:$AS$204,1) | I90: =SUMIFS(SAISIE_PROD!$R$5:$R$204,SAISIE_PROD!$A$5:$A$204,">="&$B90,SAISIE_PROD!$A$5:$A$204,"<"&EDATE($B90,1),SAISIE_PROD!$AS$5:$AS$204,1) | J90: =SUMIFS(SAISIE_PROD!$T$5:$T$204,SAISIE_PROD!$A$5:$A$204,">="&$B90,SAISIE_PROD!$A$5:$A$204,"<"&EDATE($B90,1),SAISIE_PROD!$AS$5:$AS$204,1) | K90: =SUMIFS(SAISIE_PROD!$X$5:$X$204,SAISIE_PROD!$A$5:$A$204,">="&$B90,SAISIE_PROD!$A$5:$A$204,"<"&EDATE($B90,1),SAISIE_PROD!$AS$5:$AS$204,1) | L90: =IFERROR($C90/$D90,"") | M90: =IFERROR($E90/$D90,"") | N90: =IFERROR($C90*($G90/$H90)/$E90,"") | O90: =IFERROR($H90/$G90,"") | P90: =IFERROR($C90/$F90,"") | Q90: =IFERROR(($H90+$I90)/$J90,"") | R90: =IF($L90="",NA(),$L90) | S90: =$V$3
A91: =INDEX(PARAMETRES!$AM$7:$AM$18,MONTH($B91))&" "&TEXT(YEAR($B91),"0000") | B91: =EDATE($B$7,-9) | C91: =SUMIFS(SAISIE_PROD!$AE$5:$AE$204,SAISIE_PROD!$A$5:$A$204,">="&$B91,SAISIE_PROD!$A$5:$A$204,"<"&EDATE($B91,1),SAISIE_PROD!$AS$5:$AS$204,1) | D91: =SUMIFS(SAISIE_PROD!$AB$5:$AB$204,SAISIE_PROD!$A$5:$A$204,">="&$B91,SAISIE_PROD!$A$5:$A$204,"<"&EDATE($B91,1),SAISIE_PROD!$AS$5:$AS$204,1) | E91: =SUMIFS(SAISIE_PROD!$AD$5:$AD$204,SAISIE_PROD!$A$5:$A$204,">="&$B91,SAISIE_PROD!$A$5:$A$204,"<"&EDATE($B91,1),SAISIE_PROD!$AS$5:$AS$204,1) | F91: =SUMIFS(SAISIE_PROD!$F$5:$F$204,SAISIE_PROD!$A$5:$A$204,">="&$B91,SAISIE_PROD!$A$5:$A$204,"<"&EDATE($B91,1),SAISIE_PROD!$AS$5:$AS$204,1) | G91: =SUMIFS(SAISIE_PROD!$P$5:$P$204,SAISIE_PROD!$A$5:$A$204,">="&$B91,SAISIE_PROD!$A$5:$A$204,"<"&EDATE($B91,1),SAISIE_PROD!$AS$5:$AS$204,1) | H91: =SUMIFS(SAISIE_PROD!$Q$5:$Q$204,SAISIE_PROD!$A$5:$A$204,">="&$B91,SAISIE_PROD!$A$5:$A$204,"<"&EDATE($B91,1),SAISIE_PROD!$AS$5:$AS$204,1) | I91: =SUMIFS(SAISIE_PROD!$R$5:$R$204,SAISIE_PROD!$A$5:$A$204,">="&$B91,SAISIE_PROD!$A$5:$A$204,"<"&EDATE($B91,1),SAISIE_PROD!$AS$5:$AS$204,1) | J91: =SUMIFS(SAISIE_PROD!$T$5:$T$204,SAISIE_PROD!$A$5:$A$204,">="&$B91,SAISIE_PROD!$A$5:$A$204,"<"&EDATE($B91,1),SAISIE_PROD!$AS$5:$AS$204,1) | K91: =SUMIFS(SAISIE_PROD!$X$5:$X$204,SAISIE_PROD!$A$5:$A$204,">="&$B91,SAISIE_PROD!$A$5:$A$204,"<"&EDATE($B91,1),SAISIE_PROD!$AS$5:$AS$204,1) | L91: =IFERROR($C91/$D91,"") | M91: =IFERROR($E91/$D91,"") | N91: =IFERROR($C91*($G91/$H91)/$E91,"") | O91: =IFERROR($H91/$G91,"") | P91: =IFERROR($C91/$F91,"") | Q91: =IFERROR(($H91+$I91)/$J91,"") | R91: =IF($L91="",NA(),$L91) | S91: =$V$3
